Workbook

Sheet Prix des produits et services 
C1: Nom du produit ou service | D1: Prix année 1 | E1: Prix année 2 | F1: Prix année 3 | G1: Prix année 4 | H1: Prix année 5 | I1: Prix année 6 | J1: Prix année 7
B2: Produit ou Service 1 | C2: Habits | D2: 35000 | E2: 35000 | F2: 40000 | J2: 5500
B3: Produit ou Service 2 | J3: 800
B4: Produit ou Service 3 | J4: 0.2
B5: Produit ou Service 4
B6: Produit ou Service 5
B7: Produit ou Service 6
B8: Produit ou Service 7
B9: Produit ou Service 8
B10: Produit ou Service 9
B11: Produit ou Service 10
B12: Produit ou Service 11
B13: Produit ou Service 12
B14: Produit ou Service 13
B15: Produit ou Service 14
B16: Produit ou Service 15
... B21: Produit ou Service 20
B24: Cout d'achat unitaire | C24: Régime de bananes | D24: 1000 | E24: 1500 | F24: 2000 | G24: 2500 | H24: 2700 | I24: 3000 | J24: 3200
C25: Mangue | D25: 150 | E25: 175 | F25: 200 | G25: 250 | H25: 300 | I25: 325 | J25: 350
C26: Poire | D26: 150 | E26: 175 | F26: 200 | G26: 250 | H26: 300 | I26: 325 | J26: 350

Sheet Calcul intermédiaire 

Sheet Objectifs de ventes (quantité)
B1: Nom du produit ou du service | C1: Mois 1 | D1: Mois 2 | E1: Mois 3 | F1: Mois 4 | G1: Mois 5 | H1: Mois 6 | I1: Mois 7 | J1: Mois 8 | K1: Mois 9 | L1: Mois 10 | M1: Mois 11 | N1: Mois 12 | O1: Année 1 | P1: Mois 13 | Q1: Mois 14 | R1: Mois 15 | S1: Mois 16 | T1: Mois 17 | U1: Mois 18 | V1: Mois 19 | W1: Mois 20 | X1: Mois 21 | Y1: Mois 22 | Z1: Mois 23 | AA1: Mois 24 | AB1: Année 2 | AC1: Mois 25 | AD1: Mois 26 | AE1: Mois 27 | AF1: Mois 28 | AG1: Mois 29 | AH1: Mois 30 | AI1: Mois 31 | AJ1: Mois 32 | AK1: Mois 33 | AL1: Mois 34 | AM1: Mois 35 | AN1: Mois 36 | AO1: Année 3 | AP1: Mois 37 | AQ1: Mois 38 | AR1: Mois 39 | AS1: Mois 40 | AT1: Mois 41 | AU1: Mois 42 | AV1: Mois 43 | AW1: Mois 44 | AX1: Mois 45 | AY1: Mois 46 | AZ1: Mois 47 | BA1: Mois 48 | BB1: Année 4 | BC1: Mois 49 | BD1: Mois 50 | BE1: Mois 51 | BF1: Mois 52 | BG1: Mois 53 | BH1: Mois 54 | BI1: Mois 55 | BJ1: Mois 56 | BK1: Mois 57 | BL1: Mois 58 | BM1: Mois 59 | BN1: Mois 60 | BO1: Année 5 | BP1: Mois 61 | BQ1: Mois 62 | BR1: Mois 63 | BS1: Mois 64 | BT1: Mois 65 | BU1: Mois 66 | BV1: Mois 67 | BW1: Mois 68 | BX1: Mois 69 | BY1: Mois 70 | BZ1: Mois 71 | CA1: Mois 72 | CB1: Année 6 | CC1: Mois 73 | CD1: Mois 74 | CE1: Mois 75 | CF1: Mois 76 | CG1: Mois 77 | CH1: Mois 78 | CI1: Mois 79 | CJ1: Mois 80 | CK1: Mois 81 | CL1: Mois 82 | CM1: Mois 83 | CN1: Mois 84 | CO1: Année 7
A2: ='Prix des produits et services '!B2 -> Produit ou Service 1 | B2: ='Prix des produits et services '!C2 -> Habits | C2: 5 | D2: 10 | E2: 15 | F2: 20 | G2: 25 | H2: 30 | I2: 40 | J2: 45 | K2: 45 | L2: 45 | M2: 45 | N2: 45 | O2: =SUM(C2:N2) -> 370 | P2: 50 | Q2: 55 | R2: 60 | S2: 65 | T2: 70 | U2: 75 | V2: 80 | W2: 85 | X2: 90 | Y2: 95 | Z2: 100 | AA2: 110 | AB2: =SUM(P2:AA2) -> 935 | AC2: 130 | AD2: =AC2*1.01 -> 131.3 | AE2: =AD2*1.01 -> 132.613 | AF2: =AE2*1.01 -> 133.93913 | AG2: =AF2*1.01 -> 135.27852 | AH2: =AG2*1.01 -> 136.63131 | AI2: =AH2*1.01 -> 137.99762 | AJ2: =AI2*1.01 -> 139.3776 | AK2: =AJ2*1.01 -> 140.77137 | ... AN2: =AM2*1.01 -> 145.03689 | AO2: =SUM(AC2:AN2) -> 1648.7254 | AP2: =AN2*1.03 -> 149.38799 | AQ2: =AO2*1.03 -> 1698.1872 | AR2: =AP2*1.03 -> 153.86963 | AS2: =AQ2*1.03 -> 1749.1328 | AT2: =AR2*1.03 -> 158.48572 | AU2: =AS2*1.03 -> 1801.6068 | AV2: =AT2*1.03 -> 163.24029 | AW2: =AU2*1.03 -> 1855.655 | ... BA2: =AY2*1.03 -> 1968.6643 | BB2: =SUM(AP2:BA2) -> 11950.873 | BC2: =BA2*1.03 -> 2027.7243 | BD2: =BB2*1.03 -> 12309.4 | BE2: =BC2*1.03 -> 2088.556 | BF2: =BD2*1.03 -> 12678.682 | BG2: =BE2*1.03 -> 2151.2127 | BH2: =BF2*1.03 -> 13059.042 | BI2: =BG2*1.03 -> 2215.7491 | BJ2: =BH2*1.03 -> 13450.813 | ... BN2: =BL2*1.03 -> 14269.968 | BO2: =SUM(BC2:BN2) -> 92738.393 | BP2: =BN2*1.03 -> 14698.067 | BQ2: =BO2*1.03 -> 95520.545 | BR2: =BP2*1.03 -> 15139.009 | BS2: =BQ2*1.03 -> 98386.161 | BT2: =BR2*1.03 -> 15593.179 | BU2: =BS2*1.03 -> 101337.75 | BV2: =BT2*1.03 -> 16060.974 | BW2: =BU2*1.03 -> 104377.88 | ... CA2: =BY2*1.03 -> 110734.49 | CB2: =SUM(BP2:CA2) -> 712939.16 | CC2: =CA2*1.03 -> 114056.53 | CD2: =CB2*1.03 -> 734327.33 | CE2: =CC2*1.03 -> 117478.22 | CF2: =CD2*1.03 -> 756357.15 | CG2: =CE2*1.03 -> 121002.57 | CH2: =CF2*1.03 -> 779047.87 | CI2: =CG2*1.03 -> 124632.65 | CJ2: =CH2*1.03 -> 802419.3 | ... CN2: =CL2*1.03 -> 851286.64 | CO2: =SUM(CC2:CN2) -> 5487694.5
A3: ='Prix des produits et services '!B3 -> Produit ou Service 2 | B3: ='Prix des produits et services '!C3 -> 0 | O3: =SUM(C3:N3) -> 0 | AB3: =SUM(P3:AA3) -> 0 | AO3: =SUM(AC3:AN3) -> 0 | AP3: =AN3*1.045 -> 0 | AQ3: =AO3*1.045 -> 0 | AR3: =AP3*1.045 -> 0 | AS3: =AQ3*1.045 -> 0 | AT3: =AR3*1.045 -> 0 | AU3: =AS3*1.045 -> 0 | AV3: =AT3*1.045 -> 0 | AW3: =AU3*1.045 -> 0 | ... BA3: =AY3*1.045 -> 0 | BB3: =SUM(AP3:BA3) -> 0 | BC3: =BA3*1.045 -> 0 | BD3: =BB3*1.045 -> 0 | BE3: =BC3*1.045 -> 0 | BF3: =BD3*1.045 -> 0 | BG3: =BE3*1.045 -> 0 | BH3: =BF3*1.045 -> 0 | BI3: =BG3*1.045 -> 0 | BJ3: =BH3*1.045 -> 0 | ... BN3: =BL3*1.045 -> 0 | BO3: =SUM(BC3:BN3) -> 0 | BP3: =BN3*1.045 -> 0 | BQ3: =BO3*1.045 -> 0 | BR3: =BP3*1.045 -> 0 | BS3: =BQ3*1.045 -> 0 | BT3: =BR3*1.045 -> 0 | BU3: =BS3*1.045 -> 0 | BV3: =BT3*1.045 -> 0 | BW3: =BU3*1.045 -> 0 | ... CA3: =BY3*1.045 -> 0 | CB3: =SUM(BP3:CA3) -> 0 | CC3: =CA3*1.045 -> 0 | CD3: =CB3*1.045 -> 0 | CE3: =CC3*1.045 -> 0 | CF3: =CD3*1.045 -> 0 | CG3: =CE3*1.045 -> 0 | CH3: =CF3*1.045 -> 0 | CI3: =CG3*1.045 -> 0 | CJ3: =CH3*1.045 -> 0 | ... CN3: =CL3*1.045 -> 0 | CO3: =SUM(CC3:CN3) -> 0
A4: ='Prix des produits et services '!B4 -> Produit ou Service 3 | B4: ='Prix des produits et services '!C4 -> 0 | O4: =SUM(C4:N4) -> 0 | AB4: =SUM(P4:AA4) -> 0 | AO4: =SUM(AC4:AN4) -> 0 | AP4: =AN4*1.045 -> 0 | AQ4: =AO4*1.045 -> 0 | AR4: =AP4*1.045 -> 0 | AS4: =AQ4*1.045 -> 0 | AT4: =AR4*1.045 -> 0 | AU4: =AS4*1.045 -> 0 | AV4: =AT4*1.045 -> 0 | AW4: =AU4*1.045 -> 0 | ... BA4: =AY4*1.045 -> 0 | BB4: =SUM(AP4:BA4) -> 0 | BC4: =BA4*1.045 -> 0 | BD4: =BB4*1.045 -> 0 | BE4: =BC4*1.045 -> 0 | BF4: =BD4*1.045 -> 0 | BG4: =BE4*1.045 -> 0 | BH4: =BF4*1.045 -> 0 | BI4: =BG4*1.045 -> 0 | BJ4: =BH4*1.045 -> 0 | ... BN4: =BL4*1.045 -> 0 | BO4: =SUM(BC4:BN4) -> 0 | BP4: =BN4*1.045 -> 0 | BQ4: =BO4*1.045 -> 0 | BR4: =BP4*1.045 -> 0 | BS4: =BQ4*1.045 -> 0 | BT4: =BR4*1.045 -> 0 | BU4: =BS4*1.045 -> 0 | BV4: =BT4*1.045 -> 0 | BW4: =BU4*1.045 -> 0 | ... CA4: =BY4*1.045 -> 0 | CB4: =SUM(BP4:CA4) -> 0 | CC4: =CA4*1.045 -> 0 | CD4: =CB4*1.045 -> 0 | CE4: =CC4*1.045 -> 0 | CF4: =CD4*1.045 -> 0 | CG4: =CE4*1.045 -> 0 | CH4: =CF4*1.045 -> 0 | CI4: =CG4*1.045 -> 0 | CJ4: =CH4*1.045 -> 0 | ... CN4: =CL4*1.045 -> 0 | CO4: =SUM(CC4:CN4) -> 0
A5: ='Prix des produits et services '!B5 -> Produit ou Service 4 | B5: ='Prix des produits et services '!C5 -> 0 | O5: =SUM(C5:N5) -> 0 | AB5: =SUM(P5:AA5) -> 0 | AO5: =SUM(AC5:AN5) -> 0 | BB5: =SUM(AP5:BA5) -> 0 | BO5: =SUM(BC5:BN5) -> 0 | CB5: =SUM(BP5:CA5) -> 0 | CO5: =SUM(CC5:CN5) -> 0
A6: ='Prix des produits et services '!B6 -> Produit ou Service 5 | B6: ='Prix des produits et services '!C6 -> 0 | O6: =SUM(C6:N6) -> 0 | AB6: =SUM(P6:AA6) -> 0 | AO6: =SUM(AC6:AN6) -> 0 | BB6: =SUM(AP6:BA6) -> 0 | BO6: =SUM(BC6:BN6) -> 0 | CB6: =SUM(BP6:CA6) -> 0 | CO6: =SUM(CC6:CN6) -> 0
A7: ='Prix des produits et services '!B7 -> Produit ou Service 6 | B7: ='Prix des produits et services '!C7 -> 0 | O7: =SUM(C7:N7) -> 0 | AB7: =SUM(P7:AA7) -> 0 | AO7: =SUM(AC7:AN7) -> 0 | BB7: =SUM(AP7:BA7) -> 0 | BO7: =SUM(BC7:BN7) -> 0 | CB7: =SUM(BP7:CA7) -> 0 | CO7: =SUM(CC7:CN7) -> 0
A8: ='Prix des produits et services '!B8 -> Produit ou Service 7 | B8: ='Prix des produits et services '!C8 -> 0 | O8: =SUM(C8:N8) -> 0 | AB8: =SUM(P8:AA8) -> 0 | AO8: =SUM(AC8:AN8) -> 0 | BB8: =SUM(AP8:BA8) -> 0 | BO8: =SUM(BC8:BN8) -> 0 | CB8: =SUM(BP8:CA8) -> 0 | CO8: =SUM(CC8:CN8) -> 0
A9: ='Prix des produits et services '!B9 -> Produit ou Service 8 | B9: ='Prix des produits et services '!C9 -> 0 | O9: =SUM(C9:N9) -> 0 | AB9: =SUM(P9:AA9) -> 0 | AO9: =SUM(AC9:AN9) -> 0 | BB9: =SUM(AP9:BA9) -> 0 | BO9: =SUM(BC9:BN9) -> 0 | CB9: =SUM(BP9:CA9) -> 0 | CO9: =SUM(CC9:CN9) -> 0
A10: ='Prix des produits et services '!B10 -> Produit ou Service 9 | B10: ='Prix des produits et services '!C10 -> 0 | O10: =SUM(C10:N10) -> 0 | AB10: =SUM(P10:AA10) -> 0 | AO10: =SUM(AC10:AN10) -> 0 | BB10: =SUM(AP10:BA10) -> 0 | BO10: =SUM(BC10:BN10) -> 0 | CB10: =SUM(BP10:CA10) -> 0 | CO10: =SUM(CC10:CN10) -> 0
A11: ='Prix des produits et services '!B11 -> Produit ou Service 10 | B11: ='Prix des produits et services '!C11 -> 0 | O11: =SUM(C11:N11) -> 0 | AB11: =SUM(P11:AA11) -> 0 | AO11: =SUM(AC11:AN11) -> 0 | BB11: =SUM(AP11:BA11) -> 0 | BO11: =SUM(BC11:BN11) -> 0 | CB11: =SUM(BP11:CA11) -> 0 | CO11: =SUM(CC11:CN11) -> 0
A12: ='Prix des produits et services '!B12 -> Produit ou Service 11 | B12: ='Prix des produits et services '!C12 -> 0 | O12: =SUM(C12:N12) -> 0 | AB12: =SUM(P12:AA12) -> 0 | AO12: =SUM(AC12:AN12) -> 0 | BB12: =SUM(AP12:BA12) -> 0 | BO12: =SUM(BC12:BN12) -> 0 | CB12: =SUM(BP12:CA12) -> 0 | CO12: =SUM(CC12:CN12) -> 0
A13: ='Prix des produits et services '!B13 -> Produit ou Service 12 | B13: ='Prix des produits et services '!C13 -> 0 | O13: =SUM(C13:N13) -> 0 | AB13: =SUM(P13:AA13) -> 0 | AO13: =SUM(AC13:AN13) -> 0 | BB13: =SUM(AP13:BA13) -> 0 | BO13: =SUM(BC13:BN13) -> 0 | CB13: =SUM(BP13:CA13) -> 0 | CO13: =SUM(CC13:CN13) -> 0
A14: ='Prix des produits et services '!B14 -> Produit ou Service 13 | B14: ='Prix des produits et services '!C14 -> 0 | O14: =SUM(C14:N14) -> 0 | AB14: =SUM(P14:AA14) -> 0 | AO14: =SUM(AC14:AN14) -> 0 | BB14: =SUM(AP14:BA14) -> 0 | BO14: =SUM(BC14:BN14) -> 0 | CB14: =SUM(BP14:CA14) -> 0 | CO14: =SUM(CC14:CN14) -> 0
A15: ='Prix des produits et services '!B15 -> Produit ou Service 14 | B15: ='Prix des produits et services '!C15 -> 0 | O15: =SUM(C15:N15) -> 0 | AB15: =SUM(P15:AA15) -> 0 | AO15: =SUM(AC15:AN15) -> 0 | BB15: =SUM(AP15:BA15) -> 0 | BO15: =SUM(BC15:BN15) -> 0 | CB15: =SUM(BP15:CA15) -> 0 | CO15: =SUM(CC15:CN15) -> 0
A16: ='Prix des produits et services '!B16 -> Produit ou Service 15 | B16: ='Prix des produits et services '!C16 -> 0 | O16: =SUM(C16:N16) -> 0 | AB16: =SUM(P16:AA16) -> 0 | AO16: =SUM(AC16:AN16) -> 0 | BB16: =SUM(AP16:BA16) -> 0 | BO16: =SUM(BC16:BN16) -> 0 | CB16: =SUM(BP16:CA16) -> 0 | CO16: =SUM(CC16:CN16) -> 0
... A21: ='Prix des produits et services '!B21 -> Produit ou Service 20 | B21: ='Prix des produits et services '!C21 -> 0 | O21: =SUM(C21:N21) -> 0 | AB21: =SUM(P21:AA21) -> 0 | AO21: =SUM(AC21:AN21) -> 0 | BB21: =SUM(AP21:BA21) -> 0 | BO21: =SUM(BC21:BN21) -> 0 | CB21: =SUM(BP21:CA21) -> 0 | CO21: =SUM(CC21:CN21) -> 0

Sheet Chiffre d'affaires prévisionnel
B1: Nom du produit ou du service | C1: Mois 1 | D1: Mois 2 | E1: Mois 3 | F1: Mois 4 | G1: Mois 5 | H1: Mois 6 | I1: Mois 7 | J1: Mois 8 | K1: Mois 9 | L1: Mois 10 | M1: Mois 11 | N1: Mois 12 | O1: Année 1 | P1: Mois 13 | Q1: Mois 14 | R1: Mois 15 | S1: Mois 16 | T1: Mois 17 | U1: Mois 18 | V1: Mois 19 | W1: Mois 20 | X1: Mois 21 | Y1: Mois 22 | Z1: Mois 23 | AA1: Mois 24 | AB1: Année 2 | AC1: Mois 25 | AD1: Mois 26 | AE1: Mois 27 | AF1: Mois 28 | AG1: Mois 29 | AH1: Mois 30 | AI1: Mois 31 | AJ1: Mois 32 | AK1: Mois 33 | AL1: Mois 34 | AM1: Mois 35 | AN1: Mois 36 | AO1: Année 3 | AP1: Mois 37 | AQ1: Mois 38 | AR1: Mois 39 | AS1: Mois 40 | AT1: Mois 41 | AU1: Mois 42 | AV1: Mois 43 | AW1: Mois 44 | AX1: Mois 45 | AY1: Mois 46 | AZ1: Mois 47 | BA1: Mois 48 | BB1: Année 4 | BC1: Mois 49 | BD1: Mois 50 | BE1: Mois 51 | BF1: Mois 52 | BG1: Mois 53 | BH1: Mois 54 | BI1: Mois 55 | BJ1: Mois 56 | BK1: Mois 57 | BL1: Mois 58 | BM1: Mois 59 | BN1: Mois 60 | BO1: Année 5
A2: ='Prix des produits et services '!B2 -> Produit ou Service 1 | B2: ='Prix des produits et services '!C2 -> Habits | C2: ='Prix des produits et services '!$D$2*'Objectifs de ventes (quantité)'!C2 -> 175000 | D2: ='Prix des produits et services '!$D$2*'Objectifs de ventes (quantité)'!D2 -> 350000 | E2: ='Prix des produits et services '!$D$2*'Objectifs de ventes (quantité)'!E2 -> 525000 | F2: ='Prix des produits et services '!$D$2*'Objectifs de ventes (quantité)'!F2 -> 700000 | G2: ='Prix des produits et services '!$D$2*'Objectifs de ventes (quantité)'!G2 -> 875000 | H2: ='Prix des produits et services '!$D$2*'Objectifs de ventes (quantité)'!H2 -> 1050000 | I2: ='Prix des produits et services '!$D$2*'Objectifs de ventes (quantité)'!I2 -> 1400000 | J2: ='Prix des produits et services '!$D$2*'Objectifs de ventes (quantité)'!J2 -> 1575000 | ... N2: ='Prix des produits et services '!$D$2*'Objectifs de ventes (quantité)'!N2 -> 1575000 | O2: =SUM(C2:N2) -> 12950000 | P2: ='Prix des produits et services '!$E$2*'Objectifs de ventes (quantité)'!P2 -> 1750000 | Q2: ='Prix des produits et services '!$E$2*'Objectifs de ventes (quantité)'!Q2 -> 1925000 | R2: ='Prix des produits et services '!$E$2*'Objectifs de ventes (quantité)'!R2 -> 2100000 | S2: ='Prix des produits et services '!$E$2*'Objectifs de ventes (quantité)'!S2 -> 2275000 | T2: ='Prix des produits et services '!$E$2*'Objectifs de ventes (quantité)'!T2 -> 2450000 | U2: ='Prix des produits et services '!$E$2*'Objectifs de ventes (quantité)'!U2 -> 2625000 | V2: ='Prix des produits et services '!$E$2*'Objectifs de ventes (quantité)'!V2 -> 2800000 | W2: ='Prix des produits et services '!$E$2*'Objectifs de ventes (quantité)'!W2 -> 2975000 | ... AA2: ='Prix des produits et services '!$E$2*'Objectifs de ventes (quantité)'!AA2 -> 3850000 | AB2: =SUM(P2:AA2) -> 32725000 | AC2: ='Prix des produits et services '!F2*'Objectifs de ventes (quantité)'!AC2 -> 5200000 | AD2: ='Prix des produits et services '!$F$2*'Objectifs de ventes (quantité)'!AD2 -> 5252000 | AE2: ='Prix des produits et services '!$F$2*'Objectifs de ventes (quantité)'!AE2 -> 5304520 | AF2: ='Prix des produits et services '!$F$2*'Objectifs de ventes (quantité)'!AF2 -> 5357565.2 | AG2: ='Prix des produits et services '!$F$2*'Objectifs de ventes (quantité)'!AG2 -> 5411140.9 | AH2: ='Prix des produits et services '!$F$2*'Objectifs de ventes (quantité)'!AH2 -> 5465252.3 | AI2: ='Prix des produits et services '!$F$2*'Objectifs de ventes (quantité)'!AI2 -> 5519904.8 | AJ2: ='Prix des produits et services '!$F$2*'Objectifs de ventes (quantité)'!AJ2 -> 5575103.8 | AK2: ='Prix des produits et services '!$F$2*'Objectifs de ventes (quantité)'!AK2 -> 5630854.9 | ... AN2: ='Prix des produits et services '!$F$2*'Objectifs de ventes (quantité)'!AN2 -> 5801475.4 | AO2: =SUM(AC2:AN2) -> 65949016 | AP2: ='Prix des produits et services '!$G$2*'Objectifs de ventes (quantité)'!AP2 -> 0 | AQ2: ='Prix des produits et services '!$G$2*'Objectifs de ventes (quantité)'!AQ2 -> 0 | AR2: ='Prix des produits et services '!$G$2*'Objectifs de ventes (quantité)'!AR2 -> 0 | AS2: ='Prix des produits et services '!$G$2*'Objectifs de ventes (quantité)'!AS2 -> 0 | AT2: ='Prix des produits et services '!$G$2*'Objectifs de ventes (quantité)'!AT2 -> 0 | AU2: ='Prix des produits et services '!$G$2*'Objectifs de ventes (quantité)'!AU2 -> 0 | AV2: ='Prix des produits et services '!$G$2*'Objectifs de ventes (quantité)'!AV2 -> 0 | AW2: ='Prix des produits et services '!$G$2*'Objectifs de ventes (quantité)'!AW2 -> 0 | ... BA2: ='Prix des produits et services '!$G$2*'Objectifs de ventes (quantité)'!BA2 -> 0 | BB2: =SUM(AP2:BA2) -> 0 | BC2: ='Prix des produits et services '!$H$2*'Objectifs de ventes (quantité)'!BC2 -> 0 | BD2: ='Prix des produits et services '!$H$2*'Objectifs de ventes (quantité)'!BD2 -> 0 | BE2: ='Prix des produits et services '!$H$2*'Objectifs de ventes (quantité)'!BE2 -> 0 | BF2: ='Prix des produits et services '!$H$2*'Objectifs de ventes (quantité)'!BF2 -> 0 | BG2: ='Prix des produits et services '!$H$2*'Objectifs de ventes (quantité)'!BG2 -> 0 | BH2: ='Prix des produits et services '!$H$2*'Objectifs de ventes (quantité)'!BH2 -> 0 | BI2: ='Prix des produits et services '!$H$2*'Objectifs de ventes (quantité)'!BI2 -> 0 | BJ2: ='Prix des produits et services '!$H$2*'Objectifs de ventes (quantité)'!BJ2 -> 0 | ... BN2: ='Prix des produits et services '!$H$2*'Objectifs de ventes (quantité)'!BN2 -> 0 | BO2: =SUM(BC2:BN2) -> 0
A3: ='Prix des produits et services '!B3 -> Produit ou Service 2 | B3: ='Prix des produits et services '!C3 -> 0 | C3: ='Prix des produits et services '!$D$3*'Objectifs de ventes (quantité)'!C3 -> 0 | D3: ='Prix des produits et services '!$D$3*'Objectifs de ventes (quantité)'!D3 -> 0 | E3: ='Prix des produits et services '!$D$3*'Objectifs de ventes (quantité)'!E3 -> 0 | F3: ='Prix des produits et services '!$D$3*'Objectifs de ventes (quantité)'!F3 -> 0 | G3: ='Prix des produits et services '!$D$3*'Objectifs de ventes (quantité)'!G3 -> 0 | H3: ='Prix des produits et services '!$D$3*'Objectifs de ventes (quantité)'!H3 -> 0 | I3: ='Prix des produits et services '!$D$3*'Objectifs de ventes (quantité)'!I3 -> 0 | J3: ='Prix des produits et services '!$D$3*'Objectifs de ventes (quantité)'!J3 -> 0 | ... N3: ='Prix des produits et services '!$D$3*'Objectifs de ventes (quantité)'!N3 -> 0 | O3: =SUM(C3:N3) -> 0 | P3: ='Prix des produits et services '!$E$3*'Objectifs de ventes (quantité)'!P3 -> 0 | Q3: ='Prix des produits et services '!$E$3*'Objectifs de ventes (quantité)'!Q3 -> 0 | R3: ='Prix des produits et services '!$E$3*'Objectifs de ventes (quantité)'!R3 -> 0 | S3: ='Prix des produits et services '!$E$3*'Objectifs de ventes (quantité)'!S3 -> 0 | T3: ='Prix des produits et services '!$E$3*'Objectifs de ventes (quantité)'!T3 -> 0 | U3: ='Prix des produits et services '!$E$3*'Objectifs de ventes (quantité)'!U3 -> 0 | V3: ='Prix des produits et services '!$E$3*'Objectifs de ventes (quantité)'!V3 -> 0 | W3: ='Prix des produits et services '!$E$3*'Objectifs de ventes (quantité)'!W3 -> 0 | ... AA3: ='Prix des produits et services '!$E$3*'Objectifs de ventes (quantité)'!AA3 -> 0 | AB3: =SUM(P3:AA3) -> 0 | AC3: ='Prix des produits et services '!$F$3*'Objectifs de ventes (quantité)'!AC3 -> 0 | AD3: ='Prix des produits et services '!$F$3*'Objectifs de ventes (quantité)'!AD3 -> 0 | AE3: ='Prix des produits et services '!$F$3*'Objectifs de ventes (quantité)'!AE3 -> 0 | AF3: ='Prix des produits et services '!$F$3*'Objectifs de ventes (quantité)'!AF3 -> 0 | AG3: ='Prix des produits et services '!$F$3*'Objectifs de ventes (quantité)'!AG3 -> 0 | AH3: ='Prix des produits et services '!$F$3*'Objectifs de ventes (quantité)'!AH3 -> 0 | AI3: ='Prix des produits et services '!$F$3*'Objectifs de ventes (quantité)'!AI3 -> 0 | AJ3: ='Prix des produits et services '!$F$3*'Objectifs de ventes (quantité)'!AJ3 -> 0 | ... AN3: ='Prix des produits et services '!$F$3*'Objectifs de ventes (quantité)'!AN3 -> 0 | AO3: =SUM(AC3:AN3) -> 0 | AP3: ='Prix des produits et services '!$G$3*'Objectifs de ventes (quantité)'!AP3 -> 0 | AQ3: ='Prix des produits et services '!$G$3*'Objectifs de ventes (quantité)'!AQ3 -> 0 | AR3: ='Prix des produits et services '!$G$3*'Objectifs de ventes (quantité)'!AR3 -> 0 | AS3: ='Prix des produits et services '!$G$3*'Objectifs de ventes (quantité)'!AS3 -> 0 | AT3: ='Prix des produits et services '!$G$3*'Objectifs de ventes (quantité)'!AT3 -> 0 | AU3: ='Prix des produits et services '!$G$3*'Objectifs de ventes (quantité)'!AU3 -> 0 | AV3: ='Prix des produits et services '!$G$3*'Objectifs de ventes (quantité)'!AV3 -> 0 | AW3: ='Prix des produits et services '!$G$3*'Objectifs de ventes (quantité)'!AW3 -> 0 | ... BA3: ='Prix des produits et services '!$G$3*'Objectifs de ventes (quantité)'!BA3 -> 0 | BB3: =SUM(AP3:BA3) -> 0 | BC3: ='Prix des produits et services '!$H$3*'Objectifs de ventes (quantité)'!BC3 -> 0 | BD3: ='Prix des produits et services '!$H$3*'Objectifs de ventes (quantité)'!BD3 -> 0 | BE3: ='Prix des produits et services '!$H$3*'Objectifs de ventes (quantité)'!BE3 -> 0 | BF3: ='Prix des produits et services '!$H$3*'Objectifs de ventes (quantité)'!BF3 -> 0 | BG3: ='Prix des produits et services '!$H$3*'Objectifs de ventes (quantité)'!BG3 -> 0 | BH3: ='Prix des produits et services '!$H$3*'Objectifs de ventes (quantité)'!BH3 -> 0 | BI3: ='Prix des produits et services '!$H$3*'Objectifs de ventes (quantité)'!BI3 -> 0 | BJ3: ='Prix des produits et services '!$H$3*'Objectifs de ventes (quantité)'!BJ3 -> 0 | ... BN3: ='Prix des produits et services '!$H$3*'Objectifs de ventes (quantité)'!BN3 -> 0 | BO3: =SUM(BC3:BN3) -> 0
A4: ='Prix des produits et services '!B4 -> Produit ou Service 3 | B4: ='Prix des produits et services '!C4 -> 0 | C4: ='Prix des produits et services '!$D$4*'Objectifs de ventes (quantité)'!C4 -> 0 | D4: ='Prix des produits et services '!$D$4*'Objectifs de ventes (quantité)'!D4 -> 0 | E4: ='Prix des produits et services '!$D$4*'Objectifs de ventes (quantité)'!E4 -> 0 | F4: ='Prix des produits et services '!$D$4*'Objectifs de ventes (quantité)'!F4 -> 0 | G4: ='Prix des produits et services '!$D$4*'Objectifs de ventes (quantité)'!G4 -> 0 | H4: ='Prix des produits et services '!$D$4*'Objectifs de ventes (quantité)'!H4 -> 0 | I4: ='Prix des produits et services '!$D$4*'Objectifs de ventes (quantité)'!I4 -> 0 | J4: ='Prix des produits et services '!$D$4*'Objectifs de ventes (quantité)'!J4 -> 0 | ... N4: ='Prix des produits et services '!$D$4*'Objectifs de ventes (quantité)'!N4 -> 0 | O4: =SUM(C4:N4) -> 0 | P4: ='Prix des produits et services '!$E$4*'Objectifs de ventes (quantité)'!P4 -> 0 | Q4: ='Prix des produits et services '!$E$4*'Objectifs de ventes (quantité)'!Q4 -> 0 | R4: ='Prix des produits et services '!$E$4*'Objectifs de ventes (quantité)'!R4 -> 0 | S4: ='Prix des produits et services '!$E$4*'Objectifs de ventes (quantité)'!S4 -> 0 | T4: ='Prix des produits et services '!$E$4*'Objectifs de ventes (quantité)'!T4 -> 0 | U4: ='Prix des produits et services '!$E$4*'Objectifs de ventes (quantité)'!U4 -> 0 | V4: ='Prix des produits et services '!$E$4*'Objectifs de ventes (quantité)'!V4 -> 0 | W4: ='Prix des produits et services '!$E$4*'Objectifs de ventes (quantité)'!W4 -> 0 | ... AA4: ='Prix des produits et services '!$E$4*'Objectifs de ventes (quantité)'!AA4 -> 0 | AB4: =SUM(P4:AA4) -> 0 | AC4: ='Prix des produits et services '!$F$4*'Objectifs de ventes (quantité)'!AC4 -> 0 | AD4: ='Prix des produits et services '!$F$4*'Objectifs de ventes (quantité)'!AD4 -> 0 | AE4: ='Prix des produits et services '!$F$4*'Objectifs de ventes (quantité)'!AE4 -> 0 | AF4: ='Prix des produits et services '!$F$4*'Objectifs de ventes (quantité)'!AF4 -> 0 | AG4: ='Prix des produits et services '!$F$4*'Objectifs de ventes (quantité)'!AG4 -> 0 | AH4: ='Prix des produits et services '!$F$4*'Objectifs de ventes (quantité)'!AH4 -> 0 | AI4: ='Prix des produits et services '!$F$4*'Objectifs de ventes (quantité)'!AI4 -> 0 | AJ4: ='Prix des produits et services '!$F$4*'Objectifs de ventes (quantité)'!AJ4 -> 0 | ... AN4: ='Prix des produits et services '!$F$4*'Objectifs de ventes (quantité)'!AN4 -> 0 | AO4: =SUM(AC4:AN4) -> 0 | AP4: ='Prix des produits et services '!$G$4*'Objectifs de ventes (quantité)'!AP4 -> 0 | AQ4: ='Prix des produits et services '!$G$4*'Objectifs de ventes (quantité)'!AQ4 -> 0 | AR4: ='Prix des produits et services '!$G$4*'Objectifs de ventes (quantité)'!AR4 -> 0 | AS4: ='Prix des produits et services '!$G$4*'Objectifs de ventes (quantité)'!AS4 -> 0 | AT4: ='Prix des produits et services '!$G$4*'Objectifs de ventes (quantité)'!AT4 -> 0 | AU4: ='Prix des produits et services '!$G$4*'Objectifs de ventes (quantité)'!AU4 -> 0 | AV4: ='Prix des produits et services '!$G$4*'Objectifs de ventes (quantité)'!AV4 -> 0 | AW4: ='Prix des produits et services '!$G$4*'Objectifs de ventes (quantité)'!AW4 -> 0 | ... BA4: ='Prix des produits et services '!$G$4*'Objectifs de ventes (quantité)'!BA4 -> 0 | BB4: =SUM(AP4:BA4) -> 0 | BC4: ='Prix des produits et services '!$H$4*'Objectifs de ventes (quantité)'!BC4 -> 0 | BD4: ='Prix des produits et services '!$H$4*'Objectifs de ventes (quantité)'!BD4 -> 0 | BE4: ='Prix des produits et services '!$H$4*'Objectifs de ventes (quantité)'!BE4 -> 0 | BF4: ='Prix des produits et services '!$H$4*'Objectifs de ventes (quantité)'!BF4 -> 0 | BG4: ='Prix des produits et services '!$H$4*'Objectifs de ventes (quantité)'!BG4 -> 0 | BH4: ='Prix des produits et services '!$H$4*'Objectifs de ventes (quantité)'!BH4 -> 0 | BI4: ='Prix des produits et services '!$H$4*'Objectifs de ventes (quantité)'!BI4 -> 0 | BJ4: ='Prix des produits et services '!$H$4*'Objectifs de ventes (quantité)'!BJ4 -> 0 | ... BN4: ='Prix des produits et services '!$H$4*'Objectifs de ventes (quantité)'!BN4 -> 0 | BO4: =SUM(BC4:BN4) -> 0
A5: ='Prix des produits et services '!B5 -> Produit ou Service 4 | B5: ='Prix des produits et services '!C5 -> 0 | C5: ='Prix des produits et services '!$D$5*'Objectifs de ventes (quantité)'!C5 -> 0 | D5: ='Prix des produits et services '!$D$5*'Objectifs de ventes (quantité)'!D5 -> 0 | E5: ='Prix des produits et services '!$D$5*'Objectifs de ventes (quantité)'!E5 -> 0 | F5: ='Prix des produits et services '!$D$5*'Objectifs de ventes (quantité)'!F5 -> 0 | G5: ='Prix des produits et services '!$D$5*'Objectifs de ventes (quantité)'!G5 -> 0 | H5: ='Prix des produits et services '!$D$5*'Objectifs de ventes (quantité)'!H5 -> 0 | I5: ='Prix des produits et services '!$D$5*'Objectifs de ventes (quantité)'!I5 -> 0 | J5: ='Prix des produits et services '!$D$5*'Objectifs de ventes (quantité)'!J5 -> 0 | ... N5: ='Prix des produits et services '!$D$5*'Objectifs de ventes (quantité)'!N5 -> 0 | O5: =SUM(C5:N5) -> 0 | P5: ='Prix des produits et services '!$E$5*'Objectifs de ventes (quantité)'!P5 -> 0 | Q5: ='Prix des produits et services '!$E$5*'Objectifs de ventes (quantité)'!Q5 -> 0 | R5: ='Prix des produits et services '!$E$5*'Objectifs de ventes (quantité)'!R5 -> 0 | S5: ='Prix des produits et services '!$E$5*'Objectifs de ventes (quantité)'!S5 -> 0 | T5: ='Prix des produits et services '!$E$5*'Objectifs de ventes (quantité)'!T5 -> 0 | U5: ='Prix des produits et services '!$E$5*'Objectifs de ventes (quantité)'!U5 -> 0 | V5: ='Prix des produits et services '!$E$5*'Objectifs de ventes (quantité)'!V5 -> 0 | W5: ='Prix des produits et services '!$E$5*'Objectifs de ventes (quantité)'!W5 -> 0 | ... AA5: ='Prix des produits et services '!$E$5*'Objectifs de ventes (quantité)'!AA5 -> 0 | AB5: =SUM(P5:AA5) -> 0 | AC5: ='Prix des produits et services '!$F$5*'Objectifs de ventes (quantité)'!AC5 -> 0 | AD5: ='Prix des produits et services '!$F$5*'Objectifs de ventes (quantité)'!AD5 -> 0 | AE5: ='Prix des produits et services '!$F$5*'Objectifs de ventes (quantité)'!AE5 -> 0 | AF5: ='Prix des produits et services '!$F$5*'Objectifs de ventes (quantité)'!AF5 -> 0 | AG5: ='Prix des produits et services '!$F$5*'Objectifs de ventes (quantité)'!AG5 -> 0 | AH5: ='Prix des produits et services '!$F$5*'Objectifs de ventes (quantité)'!AH5 -> 0 | AI5: ='Prix des produits et services '!$F$5*'Objectifs de ventes (quantité)'!AI5 -> 0 | AJ5: ='Prix des produits et services '!$F$5*'Objectifs de ventes (quantité)'!AJ5 -> 0 | ... AN5: ='Prix des produits et services '!$F$5*'Objectifs de ventes (quantité)'!AN5 -> 0 | AO5: =SUM(AC5:AN5) -> 0 | AP5: ='Prix des produits et services '!$G$5*'Objectifs de ventes (quantité)'!AP5 -> 0 | AQ5: ='Prix des produits et services '!$G$5*'Objectifs de ventes (quantité)'!AQ5 -> 0 | AR5: ='Prix des produits et services '!$G$5*'Objectifs de ventes (quantité)'!AR5 -> 0 | AS5: ='Prix des produits et services '!$G$5*'Objectifs de ventes (quantité)'!AS5 -> 0 | AT5: ='Prix des produits et services '!$G$5*'Objectifs de ventes (quantité)'!AT5 -> 0 | AU5: ='Prix des produits et services '!$G$5*'Objectifs de ventes (quantité)'!AU5 -> 0 | AV5: ='Prix des produits et services '!$G$5*'Objectifs de ventes (quantité)'!AV5 -> 0 | AW5: ='Prix des produits et services '!$G$5*'Objectifs de ventes (quantité)'!AW5 -> 0 | ... BA5: ='Prix des produits et services '!$G$5*'Objectifs de ventes (quantité)'!BA5 -> 0 | BB5: =SUM(AP5:BA5) -> 0 | BC5: ='Prix des produits et services '!$H$5*'Objectifs de ventes (quantité)'!BC5 -> 0 | BD5: ='Prix des produits et services '!$H$5*'Objectifs de ventes (quantité)'!BD5 -> 0 | BE5: ='Prix des produits et services '!$H$5*'Objectifs de ventes (quantité)'!BE5 -> 0 | BF5: ='Prix des produits et services '!$H$5*'Objectifs de ventes (quantité)'!BF5 -> 0 | BG5: ='Prix des produits et services '!$H$5*'Objectifs de ventes (quantité)'!BG5 -> 0 | BH5: ='Prix des produits et services '!$H$5*'Objectifs de ventes (quantité)'!BH5 -> 0 | BI5: ='Prix des produits et services '!$H$5*'Objectifs de ventes (quantité)'!BI5 -> 0 | BJ5: ='Prix des produits et services '!$H$5*'Objectifs de ventes (quantité)'!BJ5 -> 0 | ... BN5: ='Prix des produits et services '!$H$5*'Objectifs de ventes (quantité)'!BN5 -> 0 | BO5: =SUM(BC5:BN5) -> 0
A6: ='Prix des produits et services '!B6 -> Produit ou Service 5 | B6: ='Prix des produits et services '!C6 -> 0 | C6: ='Prix des produits et services '!$D$6*'Objectifs de ventes (quantité)'!C6 -> 0 | D6: ='Prix des produits et services '!$D$6*'Objectifs de ventes (quantité)'!D6 -> 0 | E6: ='Prix des produits et services '!$D$6*'Objectifs de ventes (quantité)'!E6 -> 0 | F6: ='Prix des produits et services '!$D$6*'Objectifs de ventes (quantité)'!F6 -> 0 | G6: ='Prix des produits et services '!$D$6*'Objectifs de ventes (quantité)'!G6 -> 0 | H6: ='Prix des produits et services '!$D$6*'Objectifs de ventes (quantité)'!H6 -> 0 | I6: ='Prix des produits et services '!$D$6*'Objectifs de ventes (quantité)'!I6 -> 0 | J6: ='Prix des produits et services '!$D$6*'Objectifs de ventes (quantité)'!J6 -> 0 | ... N6: ='Prix des produits et services '!$D$6*'Objectifs de ventes (quantité)'!N6 -> 0 | O6: =SUM(C6:N6) -> 0 | P6: ='Prix des produits et services '!$E$6*'Objectifs de ventes (quantité)'!P6 -> 0 | Q6: ='Prix des produits et services '!$E$6*'Objectifs de ventes (quantité)'!Q6 -> 0 | R6: ='Prix des produits et services '!$E$6*'Objectifs de ventes (quantité)'!R6 -> 0 | S6: ='Prix des produits et services '!$E$6*'Objectifs de ventes (quantité)'!S6 -> 0 | T6: ='Prix des produits et services '!$E$6*'Objectifs de ventes (quantité)'!T6 -> 0 | U6: ='Prix des produits et services '!$E$6*'Objectifs de ventes (quantité)'!U6 -> 0 | V6: ='Prix des produits et services '!$E$6*'Objectifs de ventes (quantité)'!V6 -> 0 | W6: ='Prix des produits et services '!$E$6*'Objectifs de ventes (quantité)'!W6 -> 0 | ... AA6: ='Prix des produits et services '!$E$6*'Objectifs de ventes (quantité)'!AA6 -> 0 | AB6: =SUM(P6:AA6) -> 0 | AC6: ='Prix des produits et services '!$F$6*'Objectifs de ventes (quantité)'!AC6 -> 0 | AD6: ='Prix des produits et services '!$F$6*'Objectifs de ventes (quantité)'!AD6 -> 0 | AE6: ='Prix des produits et services '!$F$6*'Objectifs de ventes (quantité)'!AE6 -> 0 | AF6: ='Prix des produits et services '!$F$6*'Objectifs de ventes (quantité)'!AF6 -> 0 | AG6: ='Prix des produits et services '!$F$6*'Objectifs de ventes (quantité)'!AG6 -> 0 | AH6: ='Prix des produits et services '!$F$6*'Objectifs de ventes (quantité)'!AH6 -> 0 | AI6: ='Prix des produits et services '!$F$6*'Objectifs de ventes (quantité)'!AI6 -> 0 | AJ6: ='Prix des produits et services '!$F$6*'Objectifs de ventes (quantité)'!AJ6 -> 0 | ... AN6: ='Prix des produits et services '!$F$6*'Objectifs de ventes (quantité)'!AN6 -> 0 | AO6: =SUM(AC6:AN6) -> 0 | AP6: ='Prix des produits et services '!$G$6*'Objectifs de ventes (quantité)'!AP6 -> 0 | AQ6: ='Prix des produits et services '!$G$6*'Objectifs de ventes (quantité)'!AQ6 -> 0 | AR6: ='Prix des produits et services '!$G$6*'Objectifs de ventes (quantité)'!AR6 -> 0 | AS6: ='Prix des produits et services '!$G$6*'Objectifs de ventes (quantité)'!AS6 -> 0 | AT6: ='Prix des produits et services '!$G$6*'Objectifs de ventes (quantité)'!AT6 -> 0 | AU6: ='Prix des produits et services '!$G$6*'Objectifs de ventes (quantité)'!AU6 -> 0 | AV6: ='Prix des produits et services '!$G$6*'Objectifs de ventes (quantité)'!AV6 -> 0 | AW6: ='Prix des produits et services '!$G$6*'Objectifs de ventes (quantité)'!AW6 -> 0 | ... BA6: ='Prix des produits et services '!$G$6*'Objectifs de ventes (quantité)'!BA6 -> 0 | BB6: =SUM(AP6:BA6) -> 0 | BC6: ='Prix des produits et services '!$H$6*'Objectifs de ventes (quantité)'!BC6 -> 0 | BD6: ='Prix des produits et services '!$H$6*'Objectifs de ventes (quantité)'!BD6 -> 0 | BE6: ='Prix des produits et services '!$H$6*'Objectifs de ventes (quantité)'!BE6 -> 0 | BF6: ='Prix des produits et services '!$H$6*'Objectifs de ventes (quantité)'!BF6 -> 0 | BG6: ='Prix des produits et services '!$H$6*'Objectifs de ventes (quantité)'!BG6 -> 0 | BH6: ='Prix des produits et services '!$H$6*'Objectifs de ventes (quantité)'!BH6 -> 0 | BI6: ='Prix des produits et services '!$H$6*'Objectifs de ventes (quantité)'!BI6 -> 0 | BJ6: ='Prix des produits et services '!$H$6*'Objectifs de ventes (quantité)'!BJ6 -> 0 | ... BN6: ='Prix des produits et services '!$H$6*'Objectifs de ventes (quantité)'!BN6 -> 0 | BO6: =SUM(BC6:BN6) -> 0
A7: ='Prix des produits et services '!B7 -> Produit ou Service 6 | B7: ='Prix des produits et services '!C7 -> 0 | C7: ='Prix des produits et services '!$D$7*'Objectifs de ventes (quantité)'!C7 -> 0 | D7: ='Prix des produits et services '!$D$7*'Objectifs de ventes (quantité)'!D7 -> 0 | E7: ='Prix des produits et services '!$D$7*'Objectifs de ventes (quantité)'!E7 -> 0 | F7: ='Prix des produits et services '!$D$7*'Objectifs de ventes (quantité)'!F7 -> 0 | G7: ='Prix des produits et services '!$D$7*'Objectifs de ventes (quantité)'!G7 -> 0 | H7: ='Prix des produits et services '!$D$7*'Objectifs de ventes (quantité)'!H7 -> 0 | I7: ='Prix des produits et services '!$D$7*'Objectifs de ventes (quantité)'!I7 -> 0 | J7: ='Prix des produits et services '!$D$7*'Objectifs de ventes (quantité)'!J7 -> 0 | ... N7: ='Prix des produits et services '!$D$7*'Objectifs de ventes (quantité)'!N7 -> 0 | O7: =SUM(C7:N7) -> 0 | P7: ='Prix des produits et services '!$E$7*'Objectifs de ventes (quantité)'!P7 -> 0 | Q7: ='Prix des produits et services '!$E$7*'Objectifs de ventes (quantité)'!Q7 -> 0 | R7: ='Prix des produits et services '!$E$7*'Objectifs de ventes (quantité)'!R7 -> 0 | S7: ='Prix des produits et services '!$E$7*'Objectifs de ventes (quantité)'!S7 -> 0 | T7: ='Prix des produits et services '!$E$7*'Objectifs de ventes (quantité)'!T7 -> 0 | U7: ='Prix des produits et services '!$E$7*'Objectifs de ventes (quantité)'!U7 -> 0 | V7: ='Prix des produits et services '!$E$7*'Objectifs de ventes (quantité)'!V7 -> 0 | W7: ='Prix des produits et services '!$E$7*'Objectifs de ventes (quantité)'!W7 -> 0 | ... AA7: ='Prix des produits et services '!$E$7*'Objectifs de ventes (quantité)'!AA7 -> 0 | AB7: =SUM(P7:AA7) -> 0 | AC7: ='Prix des produits et services '!F7*'Objectifs de ventes (quantité)'!AC7 -> 0 | AD7: ='Prix des produits et services '!G7*'Objectifs de ventes (quantité)'!AD7 -> 0 | AE7: ='Prix des produits et services '!H7*'Objectifs de ventes (quantité)'!AE7 -> 0 | AF7: ='Prix des produits et services '!I7*'Objectifs de ventes (quantité)'!AF7 -> 0 | AG7: ='Prix des produits et services '!J7*'Objectifs de ventes (quantité)'!AG7 -> 0 | AH7: ='Prix des produits et services '!K7*'Objectifs de ventes (quantité)'!AH7 -> 0 | AI7: ='Prix des produits et services '!L7*'Objectifs de ventes (quantité)'!AI7 -> 0 | AJ7: ='Prix des produits et services '!M7*'Objectifs de ventes (quantité)'!AJ7 -> 0 | ... AN7: ='Prix des produits et services '!Q7*'Objectifs de ventes (quantité)'!AN7 -> 0 | AO7: =SUM(AC7:AN7) -> 0 | AP7: ='Prix des produits et services '!$G$7*'Objectifs de ventes (quantité)'!AP7 -> 0 | AQ7: ='Prix des produits et services '!$G$7*'Objectifs de ventes (quantité)'!AQ7 -> 0 | AR7: ='Prix des produits et services '!$G$7*'Objectifs de ventes (quantité)'!AR7 -> 0 | AS7: ='Prix des produits et services '!$G$7*'Objectifs de ventes (quantité)'!AS7 -> 0 | AT7: ='Prix des produits et services '!$G$7*'Objectifs de ventes (quantité)'!AT7 -> 0 | AU7: ='Prix des produits et services '!$G$7*'Objectifs de ventes (quantité)'!AU7 -> 0 | AV7: ='Prix des produits et services '!$G$7*'Objectifs de ventes (quantité)'!AV7 -> 0 | AW7: ='Prix des produits et services '!$G$7*'Objectifs de ventes (quantité)'!AW7 -> 0 | ... BA7: ='Prix des produits et services '!$G$7*'Objectifs de ventes (quantité)'!BA7 -> 0 | BB7: =SUM(AP7:BA7) -> 0 | BC7: ='Prix des produits et services '!$H$7*'Objectifs de ventes (quantité)'!BC7 -> 0 | BD7: ='Prix des produits et services '!$H$7*'Objectifs de ventes (quantité)'!BD7 -> 0 | BE7: ='Prix des produits et services '!$H$7*'Objectifs de ventes (quantité)'!BE7 -> 0 | BF7: ='Prix des produits et services '!$H$7*'Objectifs de ventes (quantité)'!BF7 -> 0 | BG7: ='Prix des produits et services '!$H$7*'Objectifs de ventes (quantité)'!BG7 -> 0 | BH7: ='Prix des produits et services '!$H$7*'Objectifs de ventes (quantité)'!BH7 -> 0 | BI7: ='Prix des produits et services '!$H$7*'Objectifs de ventes (quantité)'!BI7 -> 0 | BJ7: ='Prix des produits et services '!$H$7*'Objectifs de ventes (quantité)'!BJ7 -> 0 | ... BN7: ='Prix des produits et services '!$H$7*'Objectifs de ventes (quantité)'!BN7 -> 0 | BO7: =SUM(BC7:BN7) -> 0
A8: ='Prix des produits et services '!B8 -> Produit ou Service 7 | B8: ='Prix des produits et services '!C8 -> 0 | C8: ='Prix des produits et services '!$D$8*'Objectifs de ventes (quantité)'!C8 -> 0 | D8: ='Prix des produits et services '!$D$8*'Objectifs de ventes (quantité)'!D8 -> 0 | E8: ='Prix des produits et services '!$D$8*'Objectifs de ventes (quantité)'!E8 -> 0 | F8: ='Prix des produits et services '!$D$8*'Objectifs de ventes (quantité)'!F8 -> 0 | G8: ='Prix des produits et services '!$D$8*'Objectifs de ventes (quantité)'!G8 -> 0 | H8: ='Prix des produits et services '!$D$8*'Objectifs de ventes (quantité)'!H8 -> 0 | I8: ='Prix des produits et services '!$D$8*'Objectifs de ventes (quantité)'!I8 -> 0 | J8: ='Prix des produits et services '!$D$8*'Objectifs de ventes (quantité)'!J8 -> 0 | ... N8: ='Prix des produits et services '!$D$8*'Objectifs de ventes (quantité)'!N8 -> 0 | O8: =SUM(C8:N8) -> 0 | P8: ='Prix des produits et services '!$E$8*'Objectifs de ventes (quantité)'!P8 -> 0 | Q8: ='Prix des produits et services '!$E$8*'Objectifs de ventes (quantité)'!Q8 -> 0 | R8: ='Prix des produits et services '!$E$8*'Objectifs de ventes (quantité)'!R8 -> 0 | S8: ='Prix des produits et services '!$E$8*'Objectifs de ventes (quantité)'!S8 -> 0 | T8: ='Prix des produits et services '!$E$8*'Objectifs de ventes (quantité)'!T8 -> 0 | U8: ='Prix des produits et services '!$E$8*'Objectifs de ventes (quantité)'!U8 -> 0 | V8: ='Prix des produits et services '!$E$8*'Objectifs de ventes (quantité)'!V8 -> 0 | W8: ='Prix des produits et services '!$E$8*'Objectifs de ventes (quantité)'!W8 -> 0 | ... AA8: ='Prix des produits et services '!$E$8*'Objectifs de ventes (quantité)'!AA8 -> 0 | AB8: =SUM(P8:AA8) -> 0 | AC8: ='Prix des produits et services '!$F$8*'Objectifs de ventes (quantité)'!AC8 -> 0 | AD8: ='Prix des produits et services '!$F$8*'Objectifs de ventes (quantité)'!AD8 -> 0 | AE8: ='Prix des produits et services '!$F$8*'Objectifs de ventes (quantité)'!AE8 -> 0 | AF8: ='Prix des produits et services '!$F$8*'Objectifs de ventes (quantité)'!AF8 -> 0 | AG8: ='Prix des produits et services '!$F$8*'Objectifs de ventes (quantité)'!AG8 -> 0 | AH8: ='Prix des produits et services '!$F$8*'Objectifs de ventes (quantité)'!AH8 -> 0 | AI8: ='Prix des produits et services '!$F$8*'Objectifs de ventes (quantité)'!AI8 -> 0 | AJ8: ='Prix des produits et services '!$F$8*'Objectifs de ventes (quantité)'!AJ8 -> 0 | ... AN8: ='Prix des produits et services '!$F$8*'Objectifs de ventes (quantité)'!AN8 -> 0 | AO8: =SUM(AC8:AN8) -> 0 | AP8: ='Prix des produits et services '!$G$8*'Objectifs de ventes (quantité)'!AP8 -> 0 | AQ8: ='Prix des produits et services '!$G$8*'Objectifs de ventes (quantité)'!AQ8 -> 0 | AR8: ='Prix des produits et services '!$G$8*'Objectifs de ventes (quantité)'!AR8 -> 0 | AS8: ='Prix des produits et services '!$G$8*'Objectifs de ventes (quantité)'!AS8 -> 0 | AT8: ='Prix des produits et services '!$G$8*'Objectifs de ventes (quantité)'!AT8 -> 0 | AU8: ='Prix des produits et services '!$G$8*'Objectifs de ventes (quantité)'!AU8 -> 0 | AV8: ='Prix des produits et services '!$G$8*'Objectifs de ventes (quantité)'!AV8 -> 0 | AW8: ='Prix des produits et services '!$G$8*'Objectifs de ventes (quantité)'!AW8 -> 0 | ... BA8: ='Prix des produits et services '!$G$8*'Objectifs de ventes (quantité)'!BA8 -> 0 | BB8: =SUM(AP8:BA8) -> 0 | BC8: ='Prix des produits et services '!$H$8*'Objectifs de ventes (quantité)'!BC8 -> 0 | BD8: ='Prix des produits et services '!$H$8*'Objectifs de ventes (quantité)'!BD8 -> 0 | BE8: ='Prix des produits et services '!$H$8*'Objectifs de ventes (quantité)'!BE8 -> 0 | BF8: ='Prix des produits et services '!$H$8*'Objectifs de ventes (quantité)'!BF8 -> 0 | BG8: ='Prix des produits et services '!$H$8*'Objectifs de ventes (quantité)'!BG8 -> 0 | BH8: ='Prix des produits et services '!$H$8*'Objectifs de ventes (quantité)'!BH8 -> 0 | BI8: ='Prix des produits et services '!$H$8*'Objectifs de ventes (quantité)'!BI8 -> 0 | BJ8: ='Prix des produits et services '!$H$8*'Objectifs de ventes (quantité)'!BJ8 -> 0 | ... BN8: ='Prix des produits et services '!$H$8*'Objectifs de ventes (quantité)'!BN8 -> 0 | BO8: =SUM(BC8:BN8) -> 0
A9: ='Prix des produits et services '!B9 -> Produit ou Service 8 | B9: ='Prix des produits et services '!C9 -> 0 | C9: ='Prix des produits et services '!$D$9*'Objectifs de ventes (quantité)'!C9 -> 0 | D9: ='Prix des produits et services '!$D$9*'Objectifs de ventes (quantité)'!D9 -> 0 | E9: ='Prix des produits et services '!$D$9*'Objectifs de ventes (quantité)'!E9 -> 0 | F9: ='Prix des produits et services '!$D$9*'Objectifs de ventes (quantité)'!F9 -> 0 | G9: ='Prix des produits et services '!$D$9*'Objectifs de ventes (quantité)'!G9 -> 0 | H9: ='Prix des produits et services '!$D$9*'Objectifs de ventes (quantité)'!H9 -> 0 | I9: ='Prix des produits et services '!$D$9*'Objectifs de ventes (quantité)'!I9 -> 0 | J9: ='Prix des produits et services '!$D$9*'Objectifs de ventes (quantité)'!J9 -> 0 | ... N9: ='Prix des produits et services '!$D$9*'Objectifs de ventes (quantité)'!N9 -> 0 | O9: =SUM(C9:N9) -> 0 | P9: ='Prix des produits et services '!$E$9*'Objectifs de ventes (quantité)'!P9 -> 0 | Q9: ='Prix des produits et services '!$E$9*'Objectifs de ventes (quantité)'!Q9 -> 0 | R9: ='Prix des produits et services '!$E$9*'Objectifs de ventes (quantité)'!R9 -> 0 | S9: ='Prix des produits et services '!$E$9*'Objectifs de ventes (quantité)'!S9 -> 0 | T9: ='Prix des produits et services '!$E$9*'Objectifs de ventes (quantité)'!T9 -> 0 | U9: ='Prix des produits et services '!$E$9*'Objectifs de ventes (quantité)'!U9 -> 0 | V9: ='Prix des produits et services '!$E$9*'Objectifs de ventes (quantité)'!V9 -> 0 | W9: ='Prix des produits et services '!$E$9*'Objectifs de ventes (quantité)'!W9 -> 0 | ... AA9: ='Prix des produits et services '!$E$9*'Objectifs de ventes (quantité)'!AA9 -> 0 | AB9: =SUM(P9:AA9) -> 0 | AC9: ='Prix des produits et services '!$F$9*'Objectifs de ventes (quantité)'!AC9 -> 0 | AD9: ='Prix des produits et services '!$F$9*'Objectifs de ventes (quantité)'!AD9 -> 0 | AE9: ='Prix des produits et services '!$F$9*'Objectifs de ventes (quantité)'!AE9 -> 0 | AF9: ='Prix des produits et services '!$F$9*'Objectifs de ventes (quantité)'!AF9 -> 0 | AG9: ='Prix des produits et services '!$F$9*'Objectifs de ventes (quantité)'!AG9 -> 0 | AH9: ='Prix des produits et services '!$F$9*'Objectifs de ventes (quantité)'!AH9 -> 0 | AI9: ='Prix des produits et services '!$F$9*'Objectifs de ventes (quantité)'!AI9 -> 0 | AJ9: ='Prix des produits et services '!$F$9*'Objectifs de ventes (quantité)'!AJ9 -> 0 | ... AN9: ='Prix des produits et services '!$F$9*'Objectifs de ventes (quantité)'!AN9 -> 0 | AO9: =SUM(AC9:AN9) -> 0 | AP9: ='Prix des produits et services '!$G$9*'Objectifs de ventes (quantité)'!AP9 -> 0 | AQ9: ='Prix des produits et services '!$G$9*'Objectifs de ventes (quantité)'!AQ9 -> 0 | AR9: ='Prix des produits et services '!$G$9*'Objectifs de ventes (quantité)'!AR9 -> 0 | AS9: ='Prix des produits et services '!$G$9*'Objectifs de ventes (quantité)'!AS9 -> 0 | AT9: ='Prix des produits et services '!$G$9*'Objectifs de ventes (quantité)'!AT9 -> 0 | AU9: ='Prix des produits et services '!$G$9*'Objectifs de ventes (quantité)'!AU9 -> 0 | AV9: ='Prix des produits et services '!$G$9*'Objectifs de ventes (quantité)'!AV9 -> 0 | AW9: ='Prix des produits et services '!$G$9*'Objectifs de ventes (quantité)'!AW9 -> 0 | ... BA9: ='Prix des produits et services '!$G$9*'Objectifs de ventes (quantité)'!BA9 -> 0 | BB9: =SUM(AP9:BA9) -> 0 | BC9: ='Prix des produits et services '!$H$9*'Objectifs de ventes (quantité)'!BC9 -> 0 | BD9: ='Prix des produits et services '!$H$9*'Objectifs de ventes (quantité)'!BD9 -> 0 | BE9: ='Prix des produits et services '!$H$9*'Objectifs de ventes (quantité)'!BE9 -> 0 | BF9: ='Prix des produits et services '!$H$9*'Objectifs de ventes (quantité)'!BF9 -> 0 | BG9: ='Prix des produits et services '!$H$9*'Objectifs de ventes (quantité)'!BG9 -> 0 | BH9: ='Prix des produits et services '!$H$9*'Objectifs de ventes (quantité)'!BH9 -> 0 | BI9: ='Prix des produits et services '!$H$9*'Objectifs de ventes (quantité)'!BI9 -> 0 | BJ9: ='Prix des produits et services '!$H$9*'Objectifs de ventes (quantité)'!BJ9 -> 0 | ... BN9: ='Prix des produits et services '!$H$9*'Objectifs de ventes (quantité)'!BN9 -> 0 | BO9: =SUM(BC9:BN9) -> 0
A10: ='Prix des produits et services '!B10 -> Produit ou Service 9 | B10: ='Prix des produits et services '!C10 -> 0 | C10: ='Prix des produits et services '!$D$10*'Objectifs de ventes (quantité)'!C10 -> 0 | D10: ='Prix des produits et services '!$D$10*'Objectifs de ventes (quantité)'!D10 -> 0 | E10: ='Prix des produits et services '!$D$10*'Objectifs de ventes (quantité)'!E10 -> 0 | F10: ='Prix des produits et services '!$D$10*'Objectifs de ventes (quantité)'!F10 -> 0 | G10: ='Prix des produits et services '!$D$10*'Objectifs de ventes (quantité)'!G10 -> 0 | H10: ='Prix des produits et services '!$D$10*'Objectifs de ventes (quantité)'!H10 -> 0 | I10: ='Prix des produits et services '!$D$10*'Objectifs de ventes (quantité)'!I10 -> 0 | J10: ='Prix des produits et services '!$D$10*'Objectifs de ventes (quantité)'!J10 -> 0 | ... N10: ='Prix des produits et services '!$D$10*'Objectifs de ventes (quantité)'!N10 -> 0 | O10: =SUM(C10:N10) -> 0 | P10: ='Prix des produits et services '!$E$10*'Objectifs de ventes (quantité)'!P10 -> 0 | Q10: ='Prix des produits et services '!$E$10*'Objectifs de ventes (quantité)'!Q10 -> 0 | R10: ='Prix des produits et services '!$E$10*'Objectifs de ventes (quantité)'!R10 -> 0 | S10: ='Prix des produits et services '!$E$10*'Objectifs de ventes (quantité)'!S10 -> 0 | T10: ='Prix des produits et services '!$E$10*'Objectifs de ventes (quantité)'!T10 -> 0 | U10: ='Prix des produits et services '!$E$10*'Objectifs de ventes (quantité)'!U10 -> 0 | V10: ='Prix des produits et services '!$E$10*'Objectifs de ventes (quantité)'!V10 -> 0 | W10: ='Prix des produits et services '!$E$10*'Objectifs de ventes (quantité)'!W10 -> 0 | ... AA10: ='Prix des produits et services '!$E$10*'Objectifs de ventes (quantité)'!AA10 -> 0 | AB10: =SUM(P10:AA10) -> 0 | AC10: ='Prix des produits et services '!$F$10*'Objectifs de ventes (quantité)'!AC10 -> 0 | AD10: ='Prix des produits et services '!$F$10*'Objectifs de ventes (quantité)'!AD10 -> 0 | AE10: ='Prix des produits et services '!$F$10*'Objectifs de ventes (quantité)'!AE10 -> 0 | AF10: ='Prix des produits et services '!$F$10*'Objectifs de ventes (quantité)'!AF10 -> 0 | AG10: ='Prix des produits et services '!$F$10*'Objectifs de ventes (quantité)'!AG10 -> 0 | AH10: ='Prix des produits et services '!$F$10*'Objectifs de ventes (quantité)'!AH10 -> 0 | AI10: ='Prix des produits et services '!$F$10*'Objectifs de ventes (quantité)'!AI10 -> 0 | AJ10: ='Prix des produits et services '!$F$10*'Objectifs de ventes (quantité)'!AJ10 -> 0 | ... AN10: ='Prix des produits et services '!$F$10*'Objectifs de ventes (quantité)'!AN10 -> 0 | AO10: =SUM(AC10:AN10) -> 0 | AP10: ='Prix des produits et services '!$G$10*'Objectifs de ventes (quantité)'!AP10 -> 0 | AQ10: ='Prix des produits et services '!$G$10*'Objectifs de ventes (quantité)'!AQ10 -> 0 | AR10: ='Prix des produits et services '!$G$10*'Objectifs de ventes (quantité)'!AR10 -> 0 | AS10: ='Prix des produits et services '!$G$10*'Objectifs de ventes (quantité)'!AS10 -> 0 | AT10: ='Prix des produits et services '!$G$10*'Objectifs de ventes (quantité)'!AT10 -> 0 | AU10: ='Prix des produits et services '!$G$10*'Objectifs de ventes (quantité)'!AU10 -> 0 | AV10: ='Prix des produits et services '!$G$10*'Objectifs de ventes (quantité)'!AV10 -> 0 | AW10: ='Prix des produits et services '!$G$10*'Objectifs de ventes (quantité)'!AW10 -> 0 | ... BA10: ='Prix des produits et services '!$G$10*'Objectifs de ventes (quantité)'!BA10 -> 0 | BB10: =SUM(AP10:BA10) -> 0 | BC10: ='Prix des produits et services '!$H$10*'Objectifs de ventes (quantité)'!BC10 -> 0 | BD10: ='Prix des produits et services '!$H$10*'Objectifs de ventes (quantité)'!BD10 -> 0 | BE10: ='Prix des produits et services '!$H$10*'Objectifs de ventes (quantité)'!BE10 -> 0 | BF10: ='Prix des produits et services '!$H$10*'Objectifs de ventes (quantité)'!BF10 -> 0 | BG10: ='Prix des produits et services '!$H$10*'Objectifs de ventes (quantité)'!BG10 -> 0 | BH10: ='Prix des produits et services '!$H$10*'Objectifs de ventes (quantité)'!BH10 -> 0 | BI10: ='Prix des produits et services '!$H$10*'Objectifs de ventes (quantité)'!BI10 -> 0 | BJ10: ='Prix des produits et services '!$H$10*'Objectifs de ventes (quantité)'!BJ10 -> 0 | ... BN10: ='Prix des produits et services '!$H$10*'Objectifs de ventes (quantité)'!BN10 -> 0 | BO10: =SUM(BC10:BN10) -> 0
A11: ='Prix des produits et services '!B11 -> Produit ou Service 10 | B11: ='Prix des produits et services '!C11 -> 0 | C11: ='Prix des produits et services '!$D$11*'Objectifs de ventes (quantité)'!C11 -> 0 | D11: ='Prix des produits et services '!$D$11*'Objectifs de ventes (quantité)'!D11 -> 0 | E11: ='Prix des produits et services '!$D$11*'Objectifs de ventes (quantité)'!E11 -> 0 | F11: ='Prix des produits et services '!$D$11*'Objectifs de ventes (quantité)'!F11 -> 0 | G11: ='Prix des produits et services '!$D$11*'Objectifs de ventes (quantité)'!G11 -> 0 | H11: ='Prix des produits et services '!$D$11*'Objectifs de ventes (quantité)'!H11 -> 0 | I11: ='Prix des produits et services '!$D$11*'Objectifs de ventes (quantité)'!I11 -> 0 | J11: ='Prix des produits et services '!$D$11*'Objectifs de ventes (quantité)'!J11 -> 0 | ... N11: ='Prix des produits et services '!$D$11*'Objectifs de ventes (quantité)'!N11 -> 0 | O11: =SUM(C11:N11) -> 0 | P11: ='Prix des produits et services '!$E$11*'Objectifs de ventes (quantité)'!P11 -> 0 | Q11: ='Prix des produits et services '!$E$11*'Objectifs de ventes (quantité)'!Q11 -> 0 | R11: ='Prix des produits et services '!$E$11*'Objectifs de ventes (quantité)'!R11 -> 0 | S11: ='Prix des produits et services '!$E$11*'Objectifs de ventes (quantité)'!S11 -> 0 | T11: ='Prix des produits et services '!$E$11*'Objectifs de ventes (quantité)'!T11 -> 0 | U11: ='Prix des produits et services '!$E$11*'Objectifs de ventes (quantité)'!U11 -> 0 | V11: ='Prix des produits et services '!$E$11*'Objectifs de ventes (quantité)'!V11 -> 0 | W11: ='Prix des produits et services '!$E$11*'Objectifs de ventes (quantité)'!W11 -> 0 | ... AA11: ='Prix des produits et services '!$E$11*'Objectifs de ventes (quantité)'!AA11 -> 0 | AB11: =SUM(P11:AA11) -> 0 | AC11: ='Prix des produits et services '!$F$11*'Objectifs de ventes (quantité)'!AC11 -> 0 | AD11: ='Prix des produits et services '!$F$11*'Objectifs de ventes (quantité)'!AD11 -> 0 | AE11: ='Prix des produits et services '!$F$11*'Objectifs de ventes (quantité)'!AE11 -> 0 | AF11: ='Prix des produits et services '!$F$11*'Objectifs de ventes (quantité)'!AF11 -> 0 | AG11: ='Prix des produits et services '!$F$11*'Objectifs de ventes (quantité)'!AG11 -> 0 | AH11: ='Prix des produits et services '!$F$11*'Objectifs de ventes (quantité)'!AH11 -> 0 | AI11: ='Prix des produits et services '!$F$11*'Objectifs de ventes (quantité)'!AI11 -> 0 | AJ11: ='Prix des produits et services '!$F$11*'Objectifs de ventes (quantité)'!AJ11 -> 0 | ... AN11: ='Prix des produits et services '!$F$11*'Objectifs de ventes (quantité)'!AN11 -> 0 | AO11: =SUM(AC11:AN11) -> 0 | AP11: ='Prix des produits et services '!$G$11*'Objectifs de ventes (quantité)'!AP11 -> 0 | AQ11: ='Prix des produits et services '!$G$11*'Objectifs de ventes (quantité)'!AQ11 -> 0 | AR11: ='Prix des produits et services '!$G$11*'Objectifs de ventes (quantité)'!AR11 -> 0 | AS11: ='Prix des produits et services '!$G$11*'Objectifs de ventes (quantité)'!AS11 -> 0 | AT11: ='Prix des produits et services '!$G$11*'Objectifs de ventes (quantité)'!AT11 -> 0 | AU11: ='Prix des produits et services '!$G$11*'Objectifs de ventes (quantité)'!AU11 -> 0 | AV11: ='Prix des produits et services '!$G$11*'Objectifs de ventes (quantité)'!AV11 -> 0 | AW11: ='Prix des produits et services '!$G$11*'Objectifs de ventes (quantité)'!AW11 -> 0 | ... BA11: ='Prix des produits et services '!$G$11*'Objectifs de ventes (quantité)'!BA11 -> 0 | BB11: =SUM(AP11:BA11) -> 0 | BC11: ='Prix des produits et services '!$H$11*'Objectifs de ventes (quantité)'!BC11 -> 0 | BD11: ='Prix des produits et services '!$H$11*'Objectifs de ventes (quantité)'!BD11 -> 0 | BE11: ='Prix des produits et services '!$H$11*'Objectifs de ventes (quantité)'!BE11 -> 0 | BF11: ='Prix des produits et services '!$H$11*'Objectifs de ventes (quantité)'!BF11 -> 0 | BG11: ='Prix des produits et services '!$H$11*'Objectifs de ventes (quantité)'!BG11 -> 0 | BH11: ='Prix des produits et services '!$H$11*'Objectifs de ventes (quantité)'!BH11 -> 0 | BI11: ='Prix des produits et services '!$H$11*'Objectifs de ventes (quantité)'!BI11 -> 0 | BJ11: ='Prix des produits et services '!$H$11*'Objectifs de ventes (quantité)'!BJ11 -> 0 | ... BN11: ='Prix des produits et services '!$H$11*'Objectifs de ventes (quantité)'!BN11 -> 0 | BO11: =SUM(BC11:BN11) -> 0
A12: ='Prix des produits et services '!B12 -> Produit ou Service 11 | B12: ='Prix des produits et services '!C12 -> 0 | C12: ='Prix des produits et services '!$D$12*'Objectifs de ventes (quantité)'!C12 -> 0 | D12: ='Prix des produits et services '!$D$12*'Objectifs de ventes (quantité)'!D12 -> 0 | E12: ='Prix des produits et services '!$D$12*'Objectifs de ventes (quantité)'!E12 -> 0 | F12: ='Prix des produits et services '!$D$12*'Objectifs de ventes (quantité)'!F12 -> 0 | G12: ='Prix des produits et services '!$D$12*'Objectifs de ventes (quantité)'!G12 -> 0 | H12: ='Prix des produits et services '!$D$12*'Objectifs de ventes (quantité)'!H12 -> 0 | I12: ='Prix des produits et services '!$D$12*'Objectifs de ventes (quantité)'!I12 -> 0 | J12: ='Prix des produits et services '!$D$12*'Objectifs de ventes (quantité)'!J12 -> 0 | ... N12: ='Prix des produits et services '!$D$12*'Objectifs de ventes (quantité)'!N12 -> 0 | O12: =SUM(C12:N12) -> 0 | P12: ='Prix des produits et services '!$E$12*'Objectifs de ventes (quantité)'!P12 -> 0 | Q12: ='Prix des produits et services '!$E$12*'Objectifs de ventes (quantité)'!Q12 -> 0 | R12: ='Prix des produits et services '!$E$12*'Objectifs de ventes (quantité)'!R12 -> 0 | S12: ='Prix des produits et services '!$E$12*'Objectifs de ventes (quantité)'!S12 -> 0 | T12: ='Prix des produits et services '!$E$12*'Objectifs de ventes (quantité)'!T12 -> 0 | U12: ='Prix des produits et services '!$E$12*'Objectifs de ventes (quantité)'!U12 -> 0 | V12: ='Prix des produits et services '!$E$12*'Objectifs de ventes (quantité)'!V12 -> 0 | W12: ='Prix des produits et services '!$E$12*'Objectifs de ventes (quantité)'!W12 -> 0 | ... AA12: ='Prix des produits et services '!$E$12*'Objectifs de ventes (quantité)'!AA12 -> 0 | AB12: =SUM(P12:AA12) -> 0 | AC12: ='Prix des produits et services '!$F$12*'Objectifs de ventes (quantité)'!AC12 -> 0 | AD12: ='Prix des produits et services '!$F$12*'Objectifs de ventes (quantité)'!AD12 -> 0 | AE12: ='Prix des produits et services '!$F$12*'Objectifs de ventes (quantité)'!AE12 -> 0 | AF12: ='Prix des produits et services '!$F$12*'Objectifs de ventes (quantité)'!AF12 -> 0 | AG12: ='Prix des produits et services '!$F$12*'Objectifs de ventes (quantité)'!AG12 -> 0 | AH12: ='Prix des produits et services '!$F$12*'Objectifs de ventes (quantité)'!AH12 -> 0 | AI12: ='Prix des produits et services '!$F$12*'Objectifs de ventes (quantité)'!AI12 -> 0 | AJ12: ='Prix des produits et services '!$F$12*'Objectifs de ventes (quantité)'!AJ12 -> 0 | ... AN12: ='Prix des produits et services '!$F$12*'Objectifs de ventes (quantité)'!AN12 -> 0 | AO12: =SUM(AC12:AN12) -> 0 | AP12: ='Prix des produits et services '!$G$12*'Objectifs de ventes (quantité)'!AP12 -> 0 | AQ12: ='Prix des produits et services '!$G$12*'Objectifs de ventes (quantité)'!AQ12 -> 0 | AR12: ='Prix des produits et services '!$G$12*'Objectifs de ventes (quantité)'!AR12 -> 0 | AS12: ='Prix des produits et services '!$G$12*'Objectifs de ventes (quantité)'!AS12 -> 0 | AT12: ='Prix des produits et services '!$G$12*'Objectifs de ventes (quantité)'!AT12 -> 0 | AU12: ='Prix des produits et services '!$G$12*'Objectifs de ventes (quantité)'!AU12 -> 0 | AV12: ='Prix des produits et services '!$G$12*'Objectifs de ventes (quantité)'!AV12 -> 0 | AW12: ='Prix des produits et services '!$G$12*'Objectifs de ventes (quantité)'!AW12 -> 0 | ... BA12: ='Prix des produits et services '!$G$12*'Objectifs de ventes (quantité)'!BA12 -> 0 | BB12: =SUM(AP12:BA12) -> 0 | BC12: ='Prix des produits et services '!$H$12*'Objectifs de ventes (quantité)'!BC12 -> 0 | BD12: ='Prix des produits et services '!$H$12*'Objectifs de ventes (quantité)'!BD12 -> 0 | BE12: ='Prix des produits et services '!$H$12*'Objectifs de ventes (quantité)'!BE12 -> 0 | BF12: ='Prix des produits et services '!$H$12*'Objectifs de ventes (quantité)'!BF12 -> 0 | BG12: ='Prix des produits et services '!$H$12*'Objectifs de ventes (quantité)'!BG12 -> 0 | BH12: ='Prix des produits et services '!$H$12*'Objectifs de ventes (quantité)'!BH12 -> 0 | BI12: ='Prix des produits et services '!$H$12*'Objectifs de ventes (quantité)'!BI12 -> 0 | BJ12: ='Prix des produits et services '!$H$12*'Objectifs de ventes (quantité)'!BJ12 -> 0 | ... BN12: ='Prix des produits et services '!$H$12*'Objectifs de ventes (quantité)'!BN12 -> 0 | BO12: =SUM(BC12:BN12) -> 0
A13: ='Prix des produits et services '!B13 -> Produit ou Service 12 | B13: ='Prix des produits et services '!C13 -> 0 | C13: ='Prix des produits et services '!$D$13*'Objectifs de ventes (quantité)'!C13 -> 0 | D13: ='Prix des produits et services '!$D$13*'Objectifs de ventes (quantité)'!D13 -> 0 | E13: ='Prix des produits et services '!$D$13*'Objectifs de ventes (quantité)'!E13 -> 0 | F13: ='Prix des produits et services '!$D$13*'Objectifs de ventes (quantité)'!F13 -> 0 | G13: ='Prix des produits et services '!$D$13*'Objectifs de ventes (quantité)'!G13 -> 0 | H13: ='Prix des produits et services '!$D$13*'Objectifs de ventes (quantité)'!H13 -> 0 | I13: ='Prix des produits et services '!$D$13*'Objectifs de ventes (quantité)'!I13 -> 0 | J13: ='Prix des produits et services '!$D$13*'Objectifs de ventes (quantité)'!J13 -> 0 | ... N13: ='Prix des produits et services '!$D$13*'Objectifs de ventes (quantité)'!N13 -> 0 | O13: =SUM(C13:N13) -> 0 | P13: ='Prix des produits et services '!$E$13*'Objectifs de ventes (quantité)'!P13 -> 0 | Q13: ='Prix des produits et services '!$E$13*'Objectifs de ventes (quantité)'!Q13 -> 0 | R13: ='Prix des produits et services '!$E$13*'Objectifs de ventes (quantité)'!R13 -> 0 | S13: ='Prix des produits et services '!$E$13*'Objectifs de ventes (quantité)'!S13 -> 0 | T13: ='Prix des produits et services '!$E$13*'Objectifs de ventes (quantité)'!T13 -> 0 | U13: ='Prix des produits et services '!$E$13*'Objectifs de ventes (quantité)'!U13 -> 0 | V13: ='Prix des produits et services '!$E$13*'Objectifs de ventes (quantité)'!V13 -> 0 | W13: ='Prix des produits et services '!$E$13*'Objectifs de ventes (quantité)'!W13 -> 0 | ... AA13: ='Prix des produits et services '!$E$13*'Objectifs de ventes (quantité)'!AA13 -> 0 | AB13: =SUM(P13:AA13) -> 0 | AC13: ='Prix des produits et services '!$F$13*'Objectifs de ventes (quantité)'!AC13 -> 0 | AD13: ='Prix des produits et services '!$F$13*'Objectifs de ventes (quantité)'!AD13 -> 0 | AE13: ='Prix des produits et services '!$F$13*'Objectifs de ventes (quantité)'!AE13 -> 0 | AF13: ='Prix des produits et services '!$F$13*'Objectifs de ventes (quantité)'!AF13 -> 0 | AG13: ='Prix des produits et services '!$F$13*'Objectifs de ventes (quantité)'!AG13 -> 0 | AH13: ='Prix des produits et services '!$F$13*'Objectifs de ventes (quantité)'!AH13 -> 0 | AI13: ='Prix des produits et services '!$F$13*'Objectifs de ventes (quantité)'!AI13 -> 0 | AJ13: ='Prix des produits et services '!$F$13*'Objectifs de ventes (quantité)'!AJ13 -> 0 | ... AN13: ='Prix des produits et services '!$F$13*'Objectifs de ventes (quantité)'!AN13 -> 0 | AO13: =SUM(AC13:AN13) -> 0 | AP13: ='Prix des produits et services '!$G$13*'Objectifs de ventes (quantité)'!AP13 -> 0 | AQ13: ='Prix des produits et services '!$G$13*'Objectifs de ventes (quantité)'!AQ13 -> 0 | AR13: ='Prix des produits et services '!$G$13*'Objectifs de ventes (quantité)'!AR13 -> 0 | AS13: ='Prix des produits et services '!$G$13*'Objectifs de ventes (quantité)'!AS13 -> 0 | AT13: ='Prix des produits et services '!$G$13*'Objectifs de ventes (quantité)'!AT13 -> 0 | AU13: ='Prix des produits et services '!$G$13*'Objectifs de ventes (quantité)'!AU13 -> 0 | AV13: ='Prix des produits et services '!$G$13*'Objectifs de ventes (quantité)'!AV13 -> 0 | AW13: ='Prix des produits et services '!$G$13*'Objectifs de ventes (quantité)'!AW13 -> 0 | ... BA13: ='Prix des produits et services '!$G$13*'Objectifs de ventes (quantité)'!BA13 -> 0 | BB13: =SUM(AP13:BA13) -> 0 | BC13: ='Prix des produits et services '!$H$13*'Objectifs de ventes (quantité)'!BC13 -> 0 | BD13: ='Prix des produits et services '!$H$13*'Objectifs de ventes (quantité)'!BD13 -> 0 | BE13: ='Prix des produits et services '!$H$13*'Objectifs de ventes (quantité)'!BE13 -> 0 | BF13: ='Prix des produits et services '!$H$13*'Objectifs de ventes (quantité)'!BF13 -> 0 | BG13: ='Prix des produits et services '!$H$13*'Objectifs de ventes (quantité)'!BG13 -> 0 | BH13: ='Prix des produits et services '!$H$13*'Objectifs de ventes (quantité)'!BH13 -> 0 | BI13: ='Prix des produits et services '!$H$13*'Objectifs de ventes (quantité)'!BI13 -> 0 | BJ13: ='Prix des produits et services '!$H$13*'Objectifs de ventes (quantité)'!BJ13 -> 0 | ... BN13: ='Prix des produits et services '!$H$13*'Objectifs de ventes (quantité)'!BN13 -> 0 | BO13: =SUM(BC13:BN13) -> 0
A14: ='Prix des produits et services '!B14 -> Produit ou Service 13 | B14: ='Prix des produits et services '!C14 -> 0 | C14: ='Prix des produits et services '!$D$14*'Objectifs de ventes (quantité)'!C14 -> 0 | D14: ='Prix des produits et services '!$D$14*'Objectifs de ventes (quantité)'!D14 -> 0 | E14: ='Prix des produits et services '!$D$14*'Objectifs de ventes (quantité)'!E14 -> 0 | F14: ='Prix des produits et services '!$D$14*'Objectifs de ventes (quantité)'!F14 -> 0 | G14: ='Prix des produits et services '!$D$14*'Objectifs de ventes (quantité)'!G14 -> 0 | H14: ='Prix des produits et services '!$D$14*'Objectifs de ventes (quantité)'!H14 -> 0 | I14: ='Prix des produits et services '!$D$14*'Objectifs de ventes (quantité)'!I14 -> 0 | J14: ='Prix des produits et services '!$D$14*'Objectifs de ventes (quantité)'!J14 -> 0 | ... N14: ='Prix des produits et services '!$D$14*'Objectifs de ventes (quantité)'!N14 -> 0 | O14: =SUM(C14:N14) -> 0 | P14: ='Prix des produits et services '!$E$14*'Objectifs de ventes (quantité)'!P14 -> 0 | Q14: ='Prix des produits et services '!$E$14*'Objectifs de ventes (quantité)'!Q14 -> 0 | R14: ='Prix des produits et services '!$E$14*'Objectifs de ventes (quantité)'!R14 -> 0 | S14: ='Prix des produits et services '!$E$14*'Objectifs de ventes (quantité)'!S14 -> 0 | T14: ='Prix des produits et services '!$E$14*'Objectifs de ventes (quantité)'!T14 -> 0 | U14: ='Prix des produits et services '!$E$14*'Objectifs de ventes (quantité)'!U14 -> 0 | V14: ='Prix des produits et services '!$E$14*'Objectifs de ventes (quantité)'!V14 -> 0 | W14: ='Prix des produits et services '!$E$14*'Objectifs de ventes (quantité)'!W14 -> 0 | ... AA14: ='Prix des produits et services '!$E$14*'Objectifs de ventes (quantité)'!AA14 -> 0 | AB14: =SUM(P14:AA14) -> 0 | AC14: ='Prix des produits et services '!$F$14*'Objectifs de ventes (quantité)'!AC14 -> 0 | AD14: ='Prix des produits et services '!$F$14*'Objectifs de ventes (quantité)'!AD14 -> 0 | AE14: ='Prix des produits et services '!$F$14*'Objectifs de ventes (quantité)'!AE14 -> 0 | AF14: ='Prix des produits et services '!$F$14*'Objectifs de ventes (quantité)'!AF14 -> 0 | AG14: ='Prix des produits et services '!$F$14*'Objectifs de ventes (quantité)'!AG14 -> 0 | AH14: ='Prix des produits et services '!$F$14*'Objectifs de ventes (quantité)'!AH14 -> 0 | AI14: ='Prix des produits et services '!$F$14*'Objectifs de ventes (quantité)'!AI14 -> 0 | AJ14: ='Prix des produits et services '!$F$14*'Objectifs de ventes (quantité)'!AJ14 -> 0 | ... AN14: ='Prix des produits et services '!$F$14*'Objectifs de ventes (quantité)'!AN14 -> 0 | AO14: =SUM(AC14:AN14) -> 0 | AP14: ='Prix des produits et services '!$G$14*'Objectifs de ventes (quantité)'!AP14 -> 0 | AQ14: ='Prix des produits et services '!$G$14*'Objectifs de ventes (quantité)'!AQ14 -> 0 | AR14: ='Prix des produits et services '!$G$14*'Objectifs de ventes (quantité)'!AR14 -> 0 | AS14: ='Prix des produits et services '!$G$14*'Objectifs de ventes (quantité)'!AS14 -> 0 | AT14: ='Prix des produits et services '!$G$14*'Objectifs de ventes (quantité)'!AT14 -> 0 | AU14: ='Prix des produits et services '!$G$14*'Objectifs de ventes (quantité)'!AU14 -> 0 | AV14: ='Prix des produits et services '!$G$14*'Objectifs de ventes (quantité)'!AV14 -> 0 | AW14: ='Prix des produits et services '!$G$14*'Objectifs de ventes (quantité)'!AW14 -> 0 | ... BA14: ='Prix des produits et services '!$G$14*'Objectifs de ventes (quantité)'!BA14 -> 0 | BB14: =SUM(AP14:BA14) -> 0 | BC14: ='Prix des produits et services '!$H$14*'Objectifs de ventes (quantité)'!BC14 -> 0 | BD14: ='Prix des produits et services '!$H$14*'Objectifs de ventes (quantité)'!BD14 -> 0 | BE14: ='Prix des produits et services '!$H$14*'Objectifs de ventes (quantité)'!BE14 -> 0 | BF14: ='Prix des produits et services '!$H$14*'Objectifs de ventes (quantité)'!BF14 -> 0 | BG14: ='Prix des produits et services '!$H$14*'Objectifs de ventes (quantité)'!BG14 -> 0 | BH14: ='Prix des produits et services '!$H$14*'Objectifs de ventes (quantité)'!BH14 -> 0 | BI14: ='Prix des produits et services '!$H$14*'Objectifs de ventes (quantité)'!BI14 -> 0 | BJ14: ='Prix des produits et services '!$H$14*'Objectifs de ventes (quantité)'!BJ14 -> 0 | ... BN14: ='Prix des produits et services '!$H$14*'Objectifs de ventes (quantité)'!BN14 -> 0 | BO14: =SUM(BC14:BN14) -> 0
A15: ='Prix des produits et services '!B15 -> Produit ou Service 14 | B15: ='Prix des produits et services '!C15 -> 0 | C15: ='Prix des produits et services '!$D$15*'Objectifs de ventes (quantité)'!C15 -> 0 | D15: ='Prix des produits et services '!$D$15*'Objectifs de ventes (quantité)'!D15 -> 0 | E15: ='Prix des produits et services '!$D$15*'Objectifs de ventes (quantité)'!E15 -> 0 | F15: ='Prix des produits et services '!$D$15*'Objectifs de ventes (quantité)'!F15 -> 0 | G15: ='Prix des produits et services '!$D$15*'Objectifs de ventes (quantité)'!G15 -> 0 | H15: ='Prix des produits et services '!$D$15*'Objectifs de ventes (quantité)'!H15 -> 0 | I15: ='Prix des produits et services '!$D$15*'Objectifs de ventes (quantité)'!I15 -> 0 | J15: ='Prix des produits et services '!$D$15*'Objectifs de ventes (quantité)'!J15 -> 0 | ... N15: ='Prix des produits et services '!$D$15*'Objectifs de ventes (quantité)'!N15 -> 0 | O15: =SUM(C15:N15) -> 0 | P15: ='Prix des produits et services '!$E$15*'Objectifs de ventes (quantité)'!P15 -> 0 | Q15: ='Prix des produits et services '!$E$15*'Objectifs de ventes (quantité)'!Q15 -> 0 | R15: ='Prix des produits et services '!$E$15*'Objectifs de ventes (quantité)'!R15 -> 0 | S15: ='Prix des produits et services '!$E$15*'Objectifs de ventes (quantité)'!S15 -> 0 | T15: ='Prix des produits et services '!$E$15*'Objectifs de ventes (quantité)'!T15 -> 0 | U15: ='Prix des produits et services '!$E$15*'Objectifs de ventes (quantité)'!U15 -> 0 | V15: ='Prix des produits et services '!$E$15*'Objectifs de ventes (quantité)'!V15 -> 0 | W15: ='Prix des produits et services '!$E$15*'Objectifs de ventes (quantité)'!W15 -> 0 | ... AA15: ='Prix des produits et services '!$E$15*'Objectifs de ventes (quantité)'!AA15 -> 0 | AB15: =SUM(P15:AA15) -> 0 | AC15: ='Prix des produits et services '!$F$15*'Objectifs de ventes (quantité)'!AC15 -> 0 | AD15: ='Prix des produits et services '!$F$15*'Objectifs de ventes (quantité)'!AD15 -> 0 | AE15: ='Prix des produits et services '!$F$15*'Objectifs de ventes (quantité)'!AE15 -> 0 | AF15: ='Prix des produits et services '!$F$15*'Objectifs de ventes (quantité)'!AF15 -> 0 | AG15: ='Prix des produits et services '!$F$15*'Objectifs de ventes (quantité)'!AG15 -> 0 | AH15: ='Prix des produits et services '!$F$15*'Objectifs de ventes (quantité)'!AH15 -> 0 | AI15: ='Prix des produits et services '!$F$15*'Objectifs de ventes (quantité)'!AI15 -> 0 | AJ15: ='Prix des produits et services '!$F$15*'Objectifs de ventes (quantité)'!AJ15 -> 0 | ... AN15: ='Prix des produits et services '!$F$15*'Objectifs de ventes (quantité)'!AN15 -> 0 | AO15: =SUM(AC15:AN15) -> 0 | AP15: ='Prix des produits et services '!$G$15*'Objectifs de ventes (quantité)'!AP15 -> 0 | AQ15: ='Prix des produits et services '!$G$15*'Objectifs de ventes (quantité)'!AQ15 -> 0 | AR15: ='Prix des produits et services '!$G$15*'Objectifs de ventes (quantité)'!AR15 -> 0 | AS15: ='Prix des produits et services '!$G$15*'Objectifs de ventes (quantité)'!AS15 -> 0 | AT15: ='Prix des produits et services '!$G$15*'Objectifs de ventes (quantité)'!AT15 -> 0 | AU15: ='Prix des produits et services '!$G$15*'Objectifs de ventes (quantité)'!AU15 -> 0 | AV15: ='Prix des produits et services '!$G$15*'Objectifs de ventes (quantité)'!AV15 -> 0 | AW15: ='Prix des produits et services '!$G$15*'Objectifs de ventes (quantité)'!AW15 -> 0 | ... BA15: ='Prix des produits et services '!$G$15*'Objectifs de ventes (quantité)'!BA15 -> 0 | BB15: =SUM(AP15:BA15) -> 0 | BC15: ='Prix des produits et services '!$H$15*'Objectifs de ventes (quantité)'!BC15 -> 0 | BD15: ='Prix des produits et services '!$H$15*'Objectifs de ventes (quantité)'!BD15 -> 0 | BE15: ='Prix des produits et services '!$H$15*'Objectifs de ventes (quantité)'!BE15 -> 0 | BF15: ='Prix des produits et services '!$H$15*'Objectifs de ventes (quantité)'!BF15 -> 0 | BG15: ='Prix des produits et services '!$H$15*'Objectifs de ventes (quantité)'!BG15 -> 0 | BH15: ='Prix des produits et services '!$H$15*'Objectifs de ventes (quantité)'!BH15 -> 0 | BI15: ='Prix des produits et services '!$H$15*'Objectifs de ventes (quantité)'!BI15 -> 0 | BJ15: ='Prix des produits et services '!$H$15*'Objectifs de ventes (quantité)'!BJ15 -> 0 | ... BN15: ='Prix des produits et services '!$H$15*'Objectifs de ventes (quantité)'!BN15 -> 0 | BO15: =SUM(BC15:BN15) -> 0
A16: ='Prix des produits et services '!B16 -> Produit ou Service 15 | B16: ='Prix des produits et services '!C16 -> 0 | C16: ='Prix des produits et services '!$D$16*'Objectifs de ventes (quantité)'!C16 -> 0 | D16: ='Prix des produits et services '!$D$16*'Objectifs de ventes (quantité)'!D16 -> 0 | E16: ='Prix des produits et services '!$D$16*'Objectifs de ventes (quantité)'!E16 -> 0 | F16: ='Prix des produits et services '!$D$16*'Objectifs de ventes (quantité)'!F16 -> 0 | G16: ='Prix des produits et services '!$D$16*'Objectifs de ventes (quantité)'!G16 -> 0 | H16: ='Prix des produits et services '!$D$16*'Objectifs de ventes (quantité)'!H16 -> 0 | I16: ='Prix des produits et services '!$D$16*'Objectifs de ventes (quantité)'!I16 -> 0 | J16: ='Prix des produits et services '!$D$16*'Objectifs de ventes (quantité)'!J16 -> 0 | ... N16: ='Prix des produits et services '!$D$16*'Objectifs de ventes (quantité)'!N16 -> 0 | O16: =SUM(C16:N16) -> 0 | P16: ='Prix des produits et services '!$E$16*'Objectifs de ventes (quantité)'!P16 -> 0 | Q16: ='Prix des produits et services '!$E$16*'Objectifs de ventes (quantité)'!Q16 -> 0 | R16: ='Prix des produits et services '!$E$16*'Objectifs de ventes (quantité)'!R16 -> 0 | S16: ='Prix des produits et services '!$E$16*'Objectifs de ventes (quantité)'!S16 -> 0 | T16: ='Prix des produits et services '!$E$16*'Objectifs de ventes (quantité)'!T16 -> 0 | U16: ='Prix des produits et services '!$E$16*'Objectifs de ventes (quantité)'!U16 -> 0 | V16: ='Prix des produits et services '!$E$16*'Objectifs de ventes (quantité)'!V16 -> 0 | W16: ='Prix des produits et services '!$E$16*'Objectifs de ventes (quantité)'!W16 -> 0 | ... AA16: ='Prix des produits et services '!$E$16*'Objectifs de ventes (quantité)'!AA16 -> 0 | AB16: =SUM(P16:AA16) -> 0 | AC16: ='Prix des produits et services '!$F$16*'Objectifs de ventes (quantité)'!AC16 -> 0 | AD16: ='Prix des produits et services '!$F$16*'Objectifs de ventes (quantité)'!AD16 -> 0 | AE16: ='Prix des produits et services '!$F$16*'Objectifs de ventes (quantité)'!AE16 -> 0 | AF16: ='Prix des produits et services '!$F$16*'Objectifs de ventes (quantité)'!AF16 -> 0 | AG16: ='Prix des produits et services '!$F$16*'Objectifs de ventes (quantité)'!AG16 -> 0 | AH16: ='Prix des produits et services '!$F$16*'Objectifs de ventes (quantité)'!AH16 -> 0 | AI16: ='Prix des produits et services '!$F$16*'Objectifs de ventes (quantité)'!AI16 -> 0 | AJ16: ='Prix des produits et services '!$F$16*'Objectifs de ventes (quantité)'!AJ16 -> 0 | ... AN16: ='Prix des produits et services '!$F$16*'Objectifs de ventes (quantité)'!AN16 -> 0 | AO16: =SUM(AC16:AN16) -> 0 | AP16: ='Prix des produits et services '!$G$16*'Objectifs de ventes (quantité)'!AP16 -> 0 | AQ16: ='Prix des produits et services '!$G$16*'Objectifs de ventes (quantité)'!AQ16 -> 0 | AR16: ='Prix des produits et services '!$G$16*'Objectifs de ventes (quantité)'!AR16 -> 0 | AS16: ='Prix des produits et services '!$G$16*'Objectifs de ventes (quantité)'!AS16 -> 0 | AT16: ='Prix des produits et services '!$G$16*'Objectifs de ventes (quantité)'!AT16 -> 0 | AU16: ='Prix des produits et services '!$G$16*'Objectifs de ventes (quantité)'!AU16 -> 0 | AV16: ='Prix des produits et services '!$G$16*'Objectifs de ventes (quantité)'!AV16 -> 0 | AW16: ='Prix des produits et services '!$G$16*'Objectifs de ventes (quantité)'!AW16 -> 0 | ... BA16: ='Prix des produits et services '!$G$16*'Objectifs de ventes (quantité)'!BA16 -> 0 | BB16: =SUM(AP16:BA16) -> 0 | BC16: ='Prix des produits et services '!$H$16*'Objectifs de ventes (quantité)'!BC16 -> 0 | BD16: ='Prix des produits et services '!$H$16*'Objectifs de ventes (quantité)'!BD16 -> 0 | BE16: ='Prix des produits et services '!$H$16*'Objectifs de ventes (quantité)'!BE16 -> 0 | BF16: ='Prix des produits et services '!$H$16*'Objectifs de ventes (quantité)'!BF16 -> 0 | BG16: ='Prix des produits et services '!$H$16*'Objectifs de ventes (quantité)'!BG16 -> 0 | BH16: ='Prix des produits et services '!$H$16*'Objectifs de ventes (quantité)'!BH16 -> 0 | BI16: ='Prix des produits et services '!$H$16*'Objectifs de ventes (quantité)'!BI16 -> 0 | BJ16: ='Prix des produits et services '!$H$16*'Objectifs de ventes (quantité)'!BJ16 -> 0 | ... BN16: ='Prix des produits et services '!$H$16*'Objectifs de ventes (quantité)'!BN16 -> 0 | BO16: =SUM(BC16:BN16) -> 0
A17: ='Prix des produits et services '!B17 -> Produit ou Service 16 | B17: ='Prix des produits et services '!C17 -> 0 | C17: ='Prix des produits et services '!$D$17*'Objectifs de ventes (quantité)'!C17 -> 0 | D17: ='Prix des produits et services '!$D$17*'Objectifs de ventes (quantité)'!D17 -> 0 | E17: ='Prix des produits et services '!$D$17*'Objectifs de ventes (quantité)'!E17 -> 0 | F17: ='Prix des produits et services '!$D$17*'Objectifs de ventes (quantité)'!F17 -> 0 | G17: ='Prix des produits et services '!$D$17*'Objectifs de ventes (quantité)'!G17 -> 0 | H17: ='Prix des produits et services '!$D$17*'Objectifs de ventes (quantité)'!H17 -> 0 | I17: ='Prix des produits et services '!$D$17*'Objectifs de ventes (quantité)'!I17 -> 0 | J17: ='Prix des produits et services '!$D$17*'Objectifs de ventes (quantité)'!J17 -> 0 | ... N17: ='Prix des produits et services '!$D$17*'Objectifs de ventes (quantité)'!N17 -> 0 | O17: =SUM(C17:N17) -> 0 | P17: ='Prix des produits et services '!$E$17*'Objectifs de ventes (quantité)'!P17 -> 0 | Q17: ='Prix des produits et services '!$E$17*'Objectifs de ventes (quantité)'!Q17 -> 0 | R17: ='Prix des produits et services '!$E$17*'Objectifs de ventes (quantité)'!R17 -> 0 | S17: ='Prix des produits et services '!$E$17*'Objectifs de ventes (quantité)'!S17 -> 0 | T17: ='Prix des produits et services '!$E$17*'Objectifs de ventes (quantité)'!T17 -> 0 | U17: ='Prix des produits et services '!$E$17*'Objectifs de ventes (quantité)'!U17 -> 0 | V17: ='Prix des produits et services '!$E$17*'Objectifs de ventes (quantité)'!V17 -> 0 | W17: ='Prix des produits et services '!$E$17*'Objectifs de ventes (quantité)'!W17 -> 0 | ... AA17: ='Prix des produits et services '!$E$17*'Objectifs de ventes (quantité)'!AA17 -> 0 | AB17: =SUM(P17:AA17) -> 0 | AC17: ='Prix des produits et services '!$F$17*'Objectifs de ventes (quantité)'!AC17 -> 0 | AD17: ='Prix des produits et services '!$F$17*'Objectifs de ventes (quantité)'!AD17 -> 0 | AE17: ='Prix des produits et services '!$F$17*'Objectifs de ventes (quantité)'!AE17 -> 0 | AF17: ='Prix des produits et services '!$F$17*'Objectifs de ventes (quantité)'!AF17 -> 0 | AG17: ='Prix des produits et services '!$F$17*'Objectifs de ventes (quantité)'!AG17 -> 0 | AH17: ='Prix des produits et services '!$F$17*'Objectifs de ventes (quantité)'!AH17 -> 0 | AI17: ='Prix des produits et services '!$F$17*'Objectifs de ventes (quantité)'!AI17 -> 0 | AJ17: ='Prix des produits et services '!$F$17*'Objectifs de ventes (quantité)'!AJ17 -> 0 | ... AN17: ='Prix des produits et services '!$F$17*'Objectifs de ventes (quantité)'!AN17 -> 0 | AO17: =SUM(AC17:AN17) -> 0 | AP17: ='Prix des produits et services '!$G$17*'Objectifs de ventes (quantité)'!AP17 -> 0 | AQ17: ='Prix des produits et services '!$G$17*'Objectifs de ventes (quantité)'!AQ17 -> 0 | AR17: ='Prix des produits et services '!$G$17*'Objectifs de ventes (quantité)'!AR17 -> 0 | AS17: ='Prix des produits et services '!$G$17*'Objectifs de ventes (quantité)'!AS17 -> 0 | AT17: ='Prix des produits et services '!$G$17*'Objectifs de ventes (quantité)'!AT17 -> 0 | AU17: ='Prix des produits et services '!$G$17*'Objectifs de ventes (quantité)'!AU17 -> 0 | AV17: ='Prix des produits et services '!$G$17*'Objectifs de ventes (quantité)'!AV17 -> 0 | AW17: ='Prix des produits et services '!$G$17*'Objectifs de ventes (quantité)'!AW17 -> 0 | ... BA17: ='Prix des produits et services '!$G$17*'Objectifs de ventes (quantité)'!BA17 -> 0 | BB17: =SUM(AP17:BA17) -> 0 | BC17: ='Prix des produits et services '!$H$17*'Objectifs de ventes (quantité)'!BC17 -> 0 | BD17: ='Prix des produits et services '!$H$17*'Objectifs de ventes (quantité)'!BD17 -> 0 | BE17: ='Prix des produits et services '!$H$17*'Objectifs de ventes (quantité)'!BE17 -> 0 | BF17: ='Prix des produits et services '!$H$17*'Objectifs de ventes (quantité)'!BF17 -> 0 | BG17: ='Prix des produits et services '!$H$17*'Objectifs de ventes (quantité)'!BG17 -> 0 | BH17: ='Prix des produits et services '!$H$17*'Objectifs de ventes (quantité)'!BH17 -> 0 | BI17: ='Prix des produits et services '!$H$17*'Objectifs de ventes (quantité)'!BI17 -> 0 | BJ17: ='Prix des produits et services '!$H$17*'Objectifs de ventes (quantité)'!BJ17 -> 0 | ... BN17: ='Prix des produits et services '!$H$17*'Objectifs de ventes (quantité)'!BN17 -> 0 | BO17: =SUM(BC17:BN17) -> 0
A18: ='Prix des produits et services '!B18 -> Produit ou Service 17 | B18: ='Prix des produits et services '!C18 -> 0 | C18: ='Prix des produits et services '!$D$18*'Objectifs de ventes (quantité)'!C18 -> 0 | D18: ='Prix des produits et services '!$D$18*'Objectifs de ventes (quantité)'!D18 -> 0 | E18: ='Prix des produits et services '!$D$18*'Objectifs de ventes (quantité)'!E18 -> 0 | F18: ='Prix des produits et services '!$D$18*'Objectifs de ventes (quantité)'!F18 -> 0 | G18: ='Prix des produits et services '!$D$18*'Objectifs de ventes (quantité)'!G18 -> 0 | H18: ='Prix des produits et services '!$D$18*'Objectifs de ventes (quantité)'!H18 -> 0 | I18: ='Prix des produits et services '!$D$18*'Objectifs de ventes (quantité)'!I18 -> 0 | J18: ='Prix des produits et services '!$D$18*'Objectifs de ventes (quantité)'!J18 -> 0 | ... N18: ='Prix des produits et services '!$D$18*'Objectifs de ventes (quantité)'!N18 -> 0 | O18: =SUM(C18:N18) -> 0 | P18: ='Prix des produits et services '!$E$18*'Objectifs de ventes (quantité)'!P18 -> 0 | Q18: ='Prix des produits et services '!$E$18*'Objectifs de ventes (quantité)'!Q18 -> 0 | R18: ='Prix des produits et services '!$E$18*'Objectifs de ventes (quantité)'!R18 -> 0 | S18: ='Prix des produits et services '!$E$18*'Objectifs de ventes (quantité)'!S18 -> 0 | T18: ='Prix des produits et services '!$E$18*'Objectifs de ventes (quantité)'!T18 -> 0 | U18: ='Prix des produits et services '!$E$18*'Objectifs de ventes (quantité)'!U18 -> 0 | V18: ='Prix des produits et services '!$E$18*'Objectifs de ventes (quantité)'!V18 -> 0 | W18: ='Prix des produits et services '!$E$18*'Objectifs de ventes (quantité)'!W18 -> 0 | ... AA18: ='Prix des produits et services '!$E$18*'Objectifs de ventes (quantité)'!AA18 -> 0 | AB18: =SUM(P18:AA18) -> 0 | AC18: ='Prix des produits et services '!$F$18*'Objectifs de ventes (quantité)'!AC18 -> 0 | AD18: ='Prix des produits et services '!$F$18*'Objectifs de ventes (quantité)'!AD18 -> 0 | AE18: ='Prix des produits et services '!$F$18*'Objectifs de ventes (quantité)'!AE18 -> 0 | AF18: ='Prix des produits et services '!$F$18*'Objectifs de ventes (quantité)'!AF18 -> 0 | AG18: ='Prix des produits et services '!$F$18*'Objectifs de ventes (quantité)'!AG18 -> 0 | AH18: ='Prix des produits et services '!$F$18*'Objectifs de ventes (quantité)'!AH18 -> 0 | AI18: ='Prix des produits et services '!$F$18*'Objectifs de ventes (quantité)'!AI18 -> 0 | AJ18: ='Prix des produits et services '!$F$18*'Objectifs de ventes (quantité)'!AJ18 -> 0 | ... AN18: ='Prix des produits et services '!$F$18*'Objectifs de ventes (quantité)'!AN18 -> 0 | AO18: =SUM(AC18:AN18) -> 0 | AP18: ='Prix des produits et services '!$G$18*'Objectifs de ventes (quantité)'!AP18 -> 0 | AQ18: ='Prix des produits et services '!$G$18*'Objectifs de ventes (quantité)'!AQ18 -> 0 | AR18: ='Prix des produits et services '!$G$18*'Objectifs de ventes (quantité)'!AR18 -> 0 | AS18: ='Prix des produits et services '!$G$18*'Objectifs de ventes (quantité)'!AS18 -> 0 | AT18: ='Prix des produits et services '!$G$18*'Objectifs de ventes (quantité)'!AT18 -> 0 | AU18: ='Prix des produits et services '!$G$18*'Objectifs de ventes (quantité)'!AU18 -> 0 | AV18: ='Prix des produits et services '!$G$18*'Objectifs de ventes (quantité)'!AV18 -> 0 | AW18: ='Prix des produits et services '!$G$18*'Objectifs de ventes (quantité)'!AW18 -> 0 | ... BA18: ='Prix des produits et services '!$G$18*'Objectifs de ventes (quantité)'!BA18 -> 0 | BB18: =SUM(AP18:BA18) -> 0 | BC18: ='Prix des produits et services '!$H$18*'Objectifs de ventes (quantité)'!BC18 -> 0 | BD18: ='Prix des produits et services '!$H$18*'Objectifs de ventes (quantité)'!BD18 -> 0 | BE18: ='Prix des produits et services '!$H$18*'Objectifs de ventes (quantité)'!BE18 -> 0 | BF18: ='Prix des produits et services '!$H$18*'Objectifs de ventes (quantité)'!BF18 -> 0 | BG18: ='Prix des produits et services '!$H$18*'Objectifs de ventes (quantité)'!BG18 -> 0 | BH18: ='Prix des produits et services '!$H$18*'Objectifs de ventes (quantité)'!BH18 -> 0 | BI18: ='Prix des produits et services '!$H$18*'Objectifs de ventes (quantité)'!BI18 -> 0 | BJ18: ='Prix des produits et services '!$H$18*'Objectifs de ventes (quantité)'!BJ18 -> 0 | ... BN18: ='Prix des produits et services '!$H$18*'Objectifs de ventes (quantité)'!BN18 -> 0 | BO18: =SUM(BC18:BN18) -> 0
A19: ='Prix des produits et services '!B19 -> Produit ou Service 18 | B19: ='Prix des produits et services '!C19 -> 0 | C19: ='Prix des produits et services '!$D$19*'Objectifs de ventes (quantité)'!C19 -> 0 | D19: ='Prix des produits et services '!$D$19*'Objectifs de ventes (quantité)'!D19 -> 0 | E19: ='Prix des produits et services '!$D$19*'Objectifs de ventes (quantité)'!E19 -> 0 | F19: ='Prix des produits et services '!$D$19*'Objectifs de ventes (quantité)'!F19 -> 0 | G19: ='Prix des produits et services '!$D$19*'Objectifs de ventes (quantité)'!G19 -> 0 | H19: ='Prix des produits et services '!$D$19*'Objectifs de ventes (quantité)'!H19 -> 0 | I19: ='Prix des produits et services '!$D$19*'Objectifs de ventes (quantité)'!I19 -> 0 | J19: ='Prix des produits et services '!$D$19*'Objectifs de ventes (quantité)'!J19 -> 0 | ... N19: ='Prix des produits et services '!$D$19*'Objectifs de ventes (quantité)'!N19 -> 0 | O19: =SUM(C19:N19) -> 0 | P19: ='Prix des produits et services '!$E$19*'Objectifs de ventes (quantité)'!P19 -> 0 | Q19: ='Prix des produits et services '!$E$19*'Objectifs de ventes (quantité)'!Q19 -> 0 | R19: ='Prix des produits et services '!$E$19*'Objectifs de ventes (quantité)'!R19 -> 0 | S19: ='Prix des produits et services '!$E$19*'Objectifs de ventes (quantité)'!S19 -> 0 | T19: ='Prix des produits et services '!$E$19*'Objectifs de ventes (quantité)'!T19 -> 0 | U19: ='Prix des produits et services '!$E$19*'Objectifs de ventes (quantité)'!U19 -> 0 | V19: ='Prix des produits et services '!$E$19*'Objectifs de ventes (quantité)'!V19 -> 0 | W19: ='Prix des produits et services '!$E$19*'Objectifs de ventes (quantité)'!W19 -> 0 | ... AA19: ='Prix des produits et services '!$E$19*'Objectifs de ventes (quantité)'!AA19 -> 0 | AB19: =SUM(P19:AA19) -> 0 | AC19: ='Prix des produits et services '!$F$19*'Objectifs de ventes (quantité)'!AC19 -> 0 | AD19: ='Prix des produits et services '!$F$19*'Objectifs de ventes (quantité)'!AD19 -> 0 | AE19: ='Prix des produits et services '!$F$19*'Objectifs de ventes (quantité)'!AE19 -> 0 | AF19: ='Prix des produits et services '!$F$19*'Objectifs de ventes (quantité)'!AF19 -> 0 | AG19: ='Prix des produits et services '!$F$19*'Objectifs de ventes (quantité)'!AG19 -> 0 | AH19: ='Prix des produits et services '!$F$19*'Objectifs de ventes (quantité)'!AH19 -> 0 | AI19: ='Prix des produits et services '!$F$19*'Objectifs de ventes (quantité)'!AI19 -> 0 | AJ19: ='Prix des produits et services '!$F$19*'Objectifs de ventes (quantité)'!AJ19 -> 0 | ... AN19: ='Prix des produits et services '!$F$19*'Objectifs de ventes (quantité)'!AN19 -> 0 | AO19: =SUM(AC19:AN19) -> 0 | AP19: ='Prix des produits et services '!$G$19*'Objectifs de ventes (quantité)'!AP19 -> 0 | AQ19: ='Prix des produits et services '!$G$19*'Objectifs de ventes (quantité)'!AQ19 -> 0 | AR19: ='Prix des produits et services '!$G$19*'Objectifs de ventes (quantité)'!AR19 -> 0 | AS19: ='Prix des produits et services '!$G$19*'Objectifs de ventes (quantité)'!AS19 -> 0 | AT19: ='Prix des produits et services '!$G$19*'Objectifs de ventes (quantité)'!AT19 -> 0 | AU19: ='Prix des produits et services '!$G$19*'Objectifs de ventes (quantité)'!AU19 -> 0 | AV19: ='Prix des produits et services '!$G$19*'Objectifs de ventes (quantité)'!AV19 -> 0 | AW19: ='Prix des produits et services '!$G$19*'Objectifs de ventes (quantité)'!AW19 -> 0 | ... BA19: ='Prix des produits et services '!$G$19*'Objectifs de ventes (quantité)'!BA19 -> 0 | BB19: =SUM(AP19:BA19) -> 0 | BC19: ='Prix des produits et services '!$H$19*'Objectifs de ventes (quantité)'!BC19 -> 0 | BD19: ='Prix des produits et services '!$H$19*'Objectifs de ventes (quantité)'!BD19 -> 0 | BE19: ='Prix des produits et services '!$H$19*'Objectifs de ventes (quantité)'!BE19 -> 0 | BF19: ='Prix des produits et services '!$H$19*'Objectifs de ventes (quantité)'!BF19 -> 0 | BG19: ='Prix des produits et services '!$H$19*'Objectifs de ventes (quantité)'!BG19 -> 0 | BH19: ='Prix des produits et services '!$H$19*'Objectifs de ventes (quantité)'!BH19 -> 0 | BI19: ='Prix des produits et services '!$H$19*'Objectifs de ventes (quantité)'!BI19 -> 0 | BJ19: ='Prix des produits et services '!$H$19*'Objectifs de ventes (quantité)'!BJ19 -> 0 | ... BN19: ='Prix des produits et services '!$H$19*'Objectifs de ventes (quantité)'!BN19 -> 0 | BO19: =SUM(BC19:BN19) -> 0
A20: ='Prix des produits et services '!B20 -> Produit ou Service 19 | B20: ='Prix des produits et services '!C20 -> 0 | C20: ='Prix des produits et services '!$D$20*'Objectifs de ventes (quantité)'!C20 -> 0 | D20: ='Prix des produits et services '!$D$20*'Objectifs de ventes (quantité)'!D20 -> 0 | E20: ='Prix des produits et services '!$D$20*'Objectifs de ventes (quantité)'!E20 -> 0 | F20: ='Prix des produits et services '!$D$20*'Objectifs de ventes (quantité)'!F20 -> 0 | G20: ='Prix des produits et services '!$D$20*'Objectifs de ventes (quantité)'!G20 -> 0 | H20: ='Prix des produits et services '!$D$20*'Objectifs de ventes (quantité)'!H20 -> 0 | I20: ='Prix des produits et services '!$D$20*'Objectifs de ventes (quantité)'!I20 -> 0 | J20: ='Prix des produits et services '!$D$20*'Objectifs de ventes (quantité)'!J20 -> 0 | ... N20: ='Prix des produits et services '!$D$20*'Objectifs de ventes (quantité)'!N20 -> 0 | O20: =SUM(C20:N20) -> 0 | P20: ='Prix des produits et services '!$E$20*'Objectifs de ventes (quantité)'!P20 -> 0 | Q20: ='Prix des produits et services '!$E$20*'Objectifs de ventes (quantité)'!Q20 -> 0 | R20: ='Prix des produits et services '!$E$20*'Objectifs de ventes (quantité)'!R20 -> 0 | S20: ='Prix des produits et services '!$E$20*'Objectifs de ventes (quantité)'!S20 -> 0 | T20: ='Prix des produits et services '!$E$20*'Objectifs de ventes (quantité)'!T20 -> 0 | U20: ='Prix des produits et services '!$E$20*'Objectifs de ventes (quantité)'!U20 -> 0 | V20: ='Prix des produits et services '!$E$20*'Objectifs de ventes (quantité)'!V20 -> 0 | W20: ='Prix des produits et services '!$E$20*'Objectifs de ventes (quantité)'!W20 -> 0 | ... AA20: ='Prix des produits et services '!$E$20*'Objectifs de ventes (quantité)'!AA20 -> 0 | AB20: =SUM(P20:AA20) -> 0 | AC20: ='Prix des produits et services '!F20*'Objectifs de ventes (quantité)'!AC20 -> 0 | AD20: ='Prix des produits et services '!G20*'Objectifs de ventes (quantité)'!AD20 -> 0 | AE20: ='Prix des produits et services '!H20*'Objectifs de ventes (quantité)'!AE20 -> 0 | AF20: ='Prix des produits et services '!I20*'Objectifs de ventes (quantité)'!AF20 -> 0 | AG20: ='Prix des produits et services '!J20*'Objectifs de ventes (quantité)'!AG20 -> 0 | AH20: ='Prix des produits et services '!K20*'Objectifs de ventes (quantité)'!AH20 -> 0 | AI20: ='Prix des produits et services '!L20*'Objectifs de ventes (quantité)'!AI20 -> 0 | AJ20: ='Prix des produits et services '!M20*'Objectifs de ventes (quantité)'!AJ20 -> 0 | ... AN20: ='Prix des produits et services '!Q20*'Objectifs de ventes (quantité)'!AN20 -> 0 | AO20: =SUM(AC20:AN20) -> 0 | AP20: ='Prix des produits et services '!$G$20*'Objectifs de ventes (quantité)'!AP20 -> 0 | AQ20: ='Prix des produits et services '!$G$20*'Objectifs de ventes (quantité)'!AQ20 -> 0 | AR20: ='Prix des produits et services '!$G$20*'Objectifs de ventes (quantité)'!AR20 -> 0 | AS20: ='Prix des produits et services '!$G$20*'Objectifs de ventes (quantité)'!AS20 -> 0 | AT20: ='Prix des produits et services '!$G$20*'Objectifs de ventes (quantité)'!AT20 -> 0 | AU20: ='Prix des produits et services '!$G$20*'Objectifs de ventes (quantité)'!AU20 -> 0 | AV20: ='Prix des produits et services '!$G$20*'Objectifs de ventes (quantité)'!AV20 -> 0 | AW20: ='Prix des produits et services '!$G$20*'Objectifs de ventes (quantité)'!AW20 -> 0 | ... BA20: ='Prix des produits et services '!$G$20*'Objectifs de ventes (quantité)'!BA20 -> 0 | BB20: =SUM(AP20:BA20) -> 0 | BC20: ='Prix des produits et services '!$H$20*'Objectifs de ventes (quantité)'!BC20 -> 0 | BD20: ='Prix des produits et services '!$H$20*'Objectifs de ventes (quantité)'!BD20 -> 0 | BE20: ='Prix des produits et services '!$H$20*'Objectifs de ventes (quantité)'!BE20 -> 0 | BF20: ='Prix des produits et services '!$H$20*'Objectifs de ventes (quantité)'!BF20 -> 0 | BG20: ='Prix des produits et services '!$H$20*'Objectifs de ventes (quantité)'!BG20 -> 0 | BH20: ='Prix des produits et services '!$H$20*'Objectifs de ventes (quantité)'!BH20 -> 0 | BI20: ='Prix des produits et services '!$H$20*'Objectifs de ventes (quantité)'!BI20 -> 0 | BJ20: ='Prix des produits et services '!$H$20*'Objectifs de ventes (quantité)'!BJ20 -> 0 | ... BN20: ='Prix des produits et services '!$H$20*'Objectifs de ventes (quantité)'!BN20 -> 0 | BO20: =SUM(BC20:BN20) -> 0
A21: ='Prix des produits et services '!B21 -> Produit ou Service 20 | B21: ='Prix des produits et services '!C21 -> 0 | C21: ='Prix des produits et services '!$D$21*'Objectifs de ventes (quantité)'!C21 -> 0 | D21: ='Prix des produits et services '!$D$21*'Objectifs de ventes (quantité)'!D21 -> 0 | E21: ='Prix des produits et services '!$D$21*'Objectifs de ventes (quantité)'!E21 -> 0 | F21: ='Prix des produits et services '!$D$21*'Objectifs de ventes (quantité)'!F21 -> 0 | G21: ='Prix des produits et services '!$D$21*'Objectifs de ventes (quantité)'!G21 -> 0 | H21: ='Prix des produits et services '!$D$21*'Objectifs de ventes (quantité)'!H21 -> 0 | I21: ='Prix des produits et services '!$D$21*'Objectifs de ventes (quantité)'!I21 -> 0 | J21: ='Prix des produits et services '!$D$21*'Objectifs de ventes (quantité)'!J21 -> 0 | ... N21: ='Prix des produits et services '!$D$21*'Objectifs de ventes (quantité)'!N21 -> 0 | O21: =SUM(C21:N21) -> 0 | P21: ='Prix des produits et services '!$E$21*'Objectifs de ventes (quantité)'!P21 -> 0 | Q21: ='Prix des produits et services '!$E$21*'Objectifs de ventes (quantité)'!Q21 -> 0 | R21: ='Prix des produits et services '!$E$21*'Objectifs de ventes (quantité)'!R21 -> 0 | S21: ='Prix des produits et services '!$E$21*'Objectifs de ventes (quantité)'!S21 -> 0 | T21: ='Prix des produits et services '!$E$21*'Objectifs de ventes (quantité)'!T21 -> 0 | U21: ='Prix des produits et services '!$E$21*'Objectifs de ventes (quantité)'!U21 -> 0 | V21: ='Prix des produits et services '!$E$21*'Objectifs de ventes (quantité)'!V21 -> 0 | W21: ='Prix des produits et services '!$E$21*'Objectifs de ventes (quantité)'!W21 -> 0 | ... AA21: ='Prix des produits et services '!$E$21*'Objectifs de ventes (quantité)'!AA21 -> 0 | AB21: =SUM(P21:AA21) -> 0 | AC21: ='Prix des produits et services '!$F$21*'Objectifs de ventes (quantité)'!AC21 -> 0 | AD21: ='Prix des produits et services '!$F$21*'Objectifs de ventes (quantité)'!AD21 -> 0 | AE21: ='Prix des produits et services '!$F$21*'Objectifs de ventes (quantité)'!AE21 -> 0 | AF21: ='Prix des produits et services '!$F$21*'Objectifs de ventes (quantité)'!AF21 -> 0 | AG21: ='Prix des produits et services '!$F$21*'Objectifs de ventes (quantité)'!AG21 -> 0 | AH21: ='Prix des produits et services '!$F$21*'Objectifs de ventes (quantité)'!AH21 -> 0 | AI21: ='Prix des produits et services '!$F$21*'Objectifs de ventes (quantité)'!AI21 -> 0 | AJ21: ='Prix des produits et services '!$F$21*'Objectifs de ventes (quantité)'!AJ21 -> 0 | ... AN21: ='Prix des produits et services '!$F$21*'Objectifs de ventes (quantité)'!AN21 -> 0 | AO21: =SUM(AC21:AN21) -> 0 | AP21: ='Prix des produits et services '!$G$21*'Objectifs de ventes (quantité)'!AP21 -> 0 | AQ21: ='Prix des produits et services '!$G$21*'Objectifs de ventes (quantité)'!AQ21 -> 0 | AR21: ='Prix des produits et services '!$G$21*'Objectifs de ventes (quantité)'!AR21 -> 0 | AS21: ='Prix des produits et services '!$G$21*'Objectifs de ventes (quantité)'!AS21 -> 0 | AT21: ='Prix des produits et services '!$G$21*'Objectifs de ventes (quantité)'!AT21 -> 0 | AU21: ='Prix des produits et services '!$G$21*'Objectifs de ventes (quantité)'!AU21 -> 0 | AV21: ='Prix des produits et services '!$G$21*'Objectifs de ventes (quantité)'!AV21 -> 0 | AW21: ='Prix des produits et services '!$G$21*'Objectifs de ventes (quantité)'!AW21 -> 0 | ... BA21: ='Prix des produits et services '!$G$21*'Objectifs de ventes (quantité)'!BA21 -> 0 | BB21: =SUM(AP21:BA21) -> 0 | BC21: ='Prix des produits et services '!$H$21*'Objectifs de ventes (quantité)'!BC21 -> 0 | BD21: ='Prix des produits et services '!$H$21*'Objectifs de ventes (quantité)'!BD21 -> 0 | BE21: ='Prix des produits et services '!$H$21*'Objectifs de ventes (quantité)'!BE21 -> 0 | BF21: ='Prix des produits et services '!$H$21*'Objectifs de ventes (quantité)'!BF21 -> 0 | BG21: ='Prix des produits et services '!$H$21*'Objectifs de ventes (quantité)'!BG21 -> 0 | BH21: ='Prix des produits et services '!$H$21*'Objectifs de ventes (quantité)'!BH21 -> 0 | BI21: ='Prix des produits et services '!$H$21*'Objectifs de ventes (quantité)'!BI21 -> 0 | BJ21: ='Prix des produits et services '!$H$21*'Objectifs de ventes (quantité)'!BJ21 -> 0 | ... BN21: ='Prix des produits et services '!$H$21*'Objectifs de ventes (quantité)'!BN21 -> 0 | BO21: =SUM(BC21:BN21) -> 0
A22: TOTAL DU CHIFFRE D'AFFAIRES | C22: =+SUM(C2:C21) -> 175000 | D22: =+SUM(D2:D21) -> 350000 | E22: =+SUM(E2:E21) -> 525000 | F22: =+SUM(F2:F21) -> 700000 | G22: =+SUM(G2:G21) -> 875000 | H22: =+SUM(H2:H21) -> 1050000 | I22: =+SUM(I2:I21) -> 1400000 | J22: =+SUM(J2:J21) -> 1575000 | ... BO22: =+SUM(BO2:BO21) -> 0
A25: Objectif des créances clients en pourcentage du Chiffre d'affaires | B25: 0.2

Sheet Impots et taxes
C2: Patentes
C4: année 1 | F4: année 2 | I4: année 3 | L4: année 4 | O4: année 5
B5: Taux de contribution de la patente | C5: ='Chiffre d''affaires prévisionnel'!O22 -> 12950000 | F5: ='Chiffre d''affaires prévisionnel'!AB22 -> 32725000 | I5: ='Chiffre d''affaires prévisionnel'!AO22 -> 65949016 | L5: ='Chiffre d''affaires prévisionnel'!BB22 -> 0 | O5: ='Chiffre d''affaires prévisionnel'!BO22 -> 0
C6: Part min du CA | D6: Plafonds du CA | E6: Montant de la patente à payer | F6: Part min du CA | G6: Plafonds du CA | H6: Montant de la patente à payer | I6: Part min du CA | J6: Plafonds du CA | K6: Montant de la patente à payer | L6: Part min du CA | M6: Plafonds du CA | N6: Montant de la patente à payer | O6: Part min du CA | P6: Plafonds du CA | Q6: Montant de la patente à payer
A7: Inférieur à 1 000 000 | B7: 10000 | C7: 0 | D7: 1000000 | E7: 10000 | F7: 0 | G7: 1000000 | H7: 10000 | I7: 0 | J7: 1000000 | K7: 10000 | L7: 0 | M7: 1000000 | N7: 10000 | O7: 0 | P7: 1000000 | Q7: 10000
A8: Entre 1 000 000 et 20 000 000 | B8: 0.0075 | C8: 1000000 | D8: 4597500 | E8: =(D8-C8)*$B$8 -> 26981.25 | F8: 1000000 | G8: 3514647 | H8: =(G8-F8)*$B$8 -> 18859.853 | I8: 1000000 | J8: 6977730 | K8: =(J8-I8)*$B$8 -> 44832.975 | L8: 1000000 | M8: 20000000 | N8: =(M8-L8)*$B$8 -> 142500 | O8: 1000000 | P8: 20000000 | Q8: =(P8-O8)*$B$8 -> 142500
A9: Entre 20 000 001 et 40 000 000 | B9: 0.0065 | E9: =(D9-C9)*$B$9 -> 0 | H9: =(G9-F9)*$B$9 -> 0 | K9: =(J9-I9)*$B$9 -> 0 | L9: 20000000 | M9: 40000000 | N9: =(M9-L9)*$B$9 -> 130000 | O9: 20000000 | P9: 40000000 | Q9: =(P9-O9)*$B$9 -> 130000
A10: Entre 40 000 001 et 100 000 000 | B10: 0.0045 | E10: =(D10-C10)*$B$10 -> 0 | H10: =(G10-F10)*$B$10 -> 0 | K10: =(J10-I10)*$B$10 -> 0 | L10: 40000000 | M10: 57834009 | N10: =(M10-L10)*$B$10 -> 80253.04 | O10: 40000000 | P10: 100000000 | Q10: =(P10-O10)*$B$10 -> 270000
A11: Entre 100 000 001 et 300 000 000 | B11: 0.002 | E11: =(D11-C11)*$B$11 -> 0 | H11: =(G11-F11)*$B$11 -> 0 | K11: =(J11-I11)*$B$11 -> 0 | N11: =(M11-L11)*$B$11 -> 0 | O11: 100000000 | P11: 300000000 | Q11: =(P11-O11)*$B$11 -> 400000
A12: Entre 300 000 001 et 500 000 000 | B12: 0.0015 | E12: =(D12-C12)*$B$12 -> 0 | H12: =(G12-F12)*$B$12 -> 0 | K12: =(J12-I12)*$B$12 -> 0 | N12: =(M12-L12)*$B$12 -> 0 | O12: 300000000 | P12: 500000000 | Q12: =(P12-O12)*$B$12 -> 300000
A13: Entre 500 000 001 et 1 000 000 000 | B13: 0.0014 | E13: =(D13-C13)*$B$13 -> 0 | H13: =(G13-F13)*$B$13 -> 0 | K13: =(J13-I13)*$B$13 -> 0 | N13: =(M13-L13)*$B$13 -> 0 | O13: 500000000 | P13: 506017477 | Q13: =(P13-O13)*$B$13 -> 8424.4678
A14: Entre 1000 000 001 et 3 000 000 000 | B14: 0.00135 | E14: =(D14-C14)*$B$14 -> 0 | H14: =(G14-F14)*$B$14 -> 0 | K14: =(J14-I14)*$B$14 -> 0 | N14: =(M14-L14)*$B$14 -> 0 | Q14: =(P14-O14)*$B$14 -> 0
A15: Entre 300 000 001 et 20 000 000 000 | B15: 0.00125 | E15: =(D15-C15)*$B$15 -> 0 | H15: =(G15-F15)*$B$15 -> 0 | K15: =(J15-I15)*$B$15 -> 0 | N15: =(M15-L15)*$B$15 -> 0 | Q15: =(P15-O15)*$B$15 -> 0
A16: Plus de 20 000 000 000 | B16: 0.00045 | E16: =(C16*$B$16) -> 0 | H16: =(F16*$B$16) -> 0 | K16: =(I16*$B$16) -> 0 | N16: =(L16*$B$16) -> 0 | Q16: =(O16*$B$16) -> 0
E17: =SUM(E7:E16) -> 36981.25 | H17: =SUM(H7:H16) -> 28859.853 | K17: =SUM(K7:K16) -> 54832.975 | N17: =SUM(N7:N16) -> 362753.04 | Q17: =SUM(Q7:Q16) -> 1260924.5
A19: Impôts forfaitaire Global | B19: Taux
A20: Taux sur le chiffre d'affaires | B20: 0.075
A21: Taux sur la marge | B21: 0.1
A24: Impots sur les sociétés | B24: Taux
A25: IS | B25: 0.3
C27: Année 1 | E27: Année 2 | G27: Année 3 | I27: Année 4 | K27: Année 5 | M27: Année 6 | O27: Année 7 | Q27: Année 8
A28: Impots fonciers | B28: Taux | C28: Montant du droit fixe forfaitaire | D28: Impot à payer | E28: Montant du droit fixe forfaitaire | F28: Impot à payer | G28: Montant du droit fixe forfaitaire | H28: Impot à payer | I28: Montant du droit fixe forfaitaire | J28: Impot à payer | K28: Montant du droit fixe forfaitaire | L28: Impot à payer | M28: Montant du droit fixe forfaitaire | N28: Impot à payer | O28: Montant du droit fixe forfaitaire | P28: Impot à payer | Q28: Montant du droit fixe forfaitaire
A29: Droits d'enregistrements | B29: 0.5 | D29: =$B$29*C29 -> 0 | F29: =$B$29*E29 -> 0 | H29: =$B$29*G29 -> 0 | J29: =$B$29*I29 -> 0 | L29: =$B$29*K29 -> 0 | N29: =$B$29*M29 -> 0 | P29: =$B$29*O29 -> 0
A30: Centimes additionnels au droit d'enregistrement | B30: 0.025 | D30: =$B$30*C30 -> 0 | F30: =$B$30*E30 -> 0 | H30: =$B$30*G30 -> 0 | J30: =$B$30*I30 -> 0 | L30: =$B$30*K30 -> 0 | N30: =$B$30*M30 -> 0 | P30: =$B$30*O30 -> 0
A31: Frais de publicité foncière | B31: 0.25 | D31: =$B$31*C31 -> 0 | F31: =$B$31*E31 -> 0 | H31: =$B$31*G31 -> 0 | J31: =$B$31*I31 -> 0 | L31: =$B$31*K31 -> 0 | N31: =$B$31*M31 -> 0 | P31: =$B$31*O31 -> 0
A32: Frais de travaux cadastraux et topographiques | B32: 0.225 | D32: =$B$32*C32 -> 0 | F32: =$B$32*E32 -> 0 | H32: =$B$32*G32 -> 0 | J32: =$B$32*I32 -> 0 | L32: =$B$32*K32 -> 0 | N32: =$B$32*M32 -> 0 | P32: =$B$32*O32 -> 0
B35: Taxe d'occupation des locaux
A36: Petites entreprises | B36: 60000
A37: Moyennes entreprises | B37: 120000
A38: Grande entreprise | B38: 500000
A41: Taxe unique sur les salaires | B41: Taux
A42: TUS | B42: 0.075

Sheet Calcul intermédiaires Charges V

Sheet Charges variables
B1: Mois 1 | C1: Mois 2 | D1: Mois 3 | E1: Mois 4 | F1: Mois 5 | G1: Mois 6 | H1: Mois 7 | I1: Mois 8 | J1: Mois 9 | K1: Mois 10 | L1: Mois 11 | M1: Mois 12 | N1: Année 1 | O1: Mois 13 | P1: Mois 14 | Q1: Mois 15 | R1: Mois 16 | S1: Mois 17 | T1: Mois 18 | U1: Mois 19 | V1: Mois 20 | W1: Mois 21 | X1: Mois 22 | Y1: Mois 23 | Z1: Mois 24 | AA1: Année 2 | AB1: Mois 25 | AC1: Mois 26 | AD1: Mois 27 | AE1: Mois 28 | AF1: Mois 29 | AG1: Mois 30 | AH1: Mois 31 | AI1: Mois 32 | AJ1: Mois 33 | AK1: Mois 34 | AL1: Mois 35 | AM1: Mois 36 | AN1: Année 3 | AO1: Mois 37 | AP1: Mois 38 | AQ1: Mois 39 | AR1: Mois 40 | AS1: Mois 41 | AT1: Mois 42 | AU1: Mois 43 | AV1: Mois 44 | AW1: Mois 45 | AX1: Mois 46 | AY1: Mois 47 | AZ1: Mois 48 | BA1: Année 4 | BB1: Mois 49 | BC1: Mois 50 | BD1: Mois 51 | BE1: Mois 52 | BF1: Mois 53 | BG1: Mois 54 | BH1: Mois 55 | BI1: Mois 56 | BJ1: Mois 57 | BK1: Mois 58 | BL1: Mois 59 | BM1: Mois 60 | BN1: Année 5
A2: Achats de marchandises | N2: =SUM(B2:M2) -> 0 | O2: =('Prix des produits et services '!$E$24*'Objectifs de ventes (quantité)'!P2)+('Prix des produits et services '!$E$25*'Objectifs de ventes (quantité)'!P3)+('Prix des produits et services '!$E$26*'Objectifs de ventes (quantité)'!P4) -> 75000 | P2: =('Prix des produits et services '!$E$24*'Objectifs de ventes (quantité)'!Q2)+('Prix des produits et services '!$E$25*'Objectifs de ventes (quantité)'!Q3)+('Prix des produits et services '!$E$26*'Objectifs de ventes (quantité)'!Q4) -> 82500 | Q2: =('Prix des produits et services '!$E$24*'Objectifs de ventes (quantité)'!R2)+('Prix des produits et services '!$E$25*'Objectifs de ventes (quantité)'!R3)+('Prix des produits et services '!$E$26*'Objectifs de ventes (quantité)'!R4) -> 90000 | R2: =('Prix des produits et services '!$E$24*'Objectifs de ventes (quantité)'!S2)+('Prix des produits et services '!$E$25*'Objectifs de ventes (quantité)'!S3)+('Prix des produits et services '!$E$26*'Objectifs de ventes (quantité)'!S4) -> 97500 | S2: =('Prix des produits et services '!$E$24*'Objectifs de ventes (quantité)'!T2)+('Prix des produits et services '!$E$25*'Objectifs de ventes (quantité)'!T3)+('Prix des produits et services '!$E$26*'Objectifs de ventes (quantité)'!T4) -> 105000 | T2: =('Prix des produits et services '!$E$24*'Objectifs de ventes (quantité)'!U2)+('Prix des produits et services '!$E$25*'Objectifs de ventes (quantité)'!U3)+('Prix des produits et services '!$E$26*'Objectifs de ventes (quantité)'!U4) -> 112500 | U2: =('Prix des produits et services '!$E$24*'Objectifs de ventes (quantité)'!V2)+('Prix des produits et services '!$E$25*'Objectifs de ventes (quantité)'!V3)+('Prix des produits et services '!$E$26*'Objectifs de ventes (quantité)'!V4) -> 120000 | V2: =('Prix des produits et services '!$E$24*'Objectifs de ventes (quantité)'!W2)+('Prix des produits et services '!$E$25*'Objectifs de ventes (quantité)'!W3)+('Prix des produits et services '!$E$26*'Objectifs de ventes (quantité)'!W4) -> 127500 | ... Z2: =('Prix des produits et services '!$E$24*'Objectifs de ventes (quantité)'!AA2)+('Prix des produits et services '!$E$25*'Objectifs de ventes (quantité)'!AA3)+('Prix des produits et services '!$E$26*'Objectifs de ventes (quantité)'!AA4) -> 165000 | AA2: =SUM(O2:Z2) -> 1402500 | AB2: =('Prix des produits et services '!$F$24*'Objectifs de ventes (quantité)'!AC2)+('Prix des produits et services '!$F$25*'Objectifs de ventes (quantité)'!AC3)+('Prix des produits et services '!$F$26*'Objectifs de ventes (quantité)'!AC4) -> 260000 | AC2: =('Prix des produits et services '!$F$24*'Objectifs de ventes (quantité)'!AD2)+('Prix des produits et services '!$F$25*'Objectifs de ventes (quantité)'!AD3)+('Prix des produits et services '!$F$26*'Objectifs de ventes (quantité)'!AD4) -> 262600 | AD2: =('Prix des produits et services '!$F$24*'Objectifs de ventes (quantité)'!AE2)+('Prix des produits et services '!$F$25*'Objectifs de ventes (quantité)'!AE3)+('Prix des produits et services '!$F$26*'Objectifs de ventes (quantité)'!AE4) -> 265226 | AE2: =('Prix des produits et services '!$F$24*'Objectifs de ventes (quantité)'!AF2)+('Prix des produits et services '!$F$25*'Objectifs de ventes (quantité)'!AF3)+('Prix des produits et services '!$F$26*'Objectifs de ventes (quantité)'!AF4) -> 267878.26 | AF2: =('Prix des produits et services '!$F$24*'Objectifs de ventes (quantité)'!AG2)+('Prix des produits et services '!$F$25*'Objectifs de ventes (quantité)'!AG3)+('Prix des produits et services '!$F$26*'Objectifs de ventes (quantité)'!AG4) -> 270557.04 | AG2: =('Prix des produits et services '!$F$24*'Objectifs de ventes (quantité)'!AH2)+('Prix des produits et services '!$F$25*'Objectifs de ventes (quantité)'!AH3)+('Prix des produits et services '!$F$26*'Objectifs de ventes (quantité)'!AH4) -> 273262.61 | AH2: =('Prix des produits et services '!$F$24*'Objectifs de ventes (quantité)'!AI2)+('Prix des produits et services '!$F$25*'Objectifs de ventes (quantité)'!AI3)+('Prix des produits et services '!$F$26*'Objectifs de ventes (quantité)'!AI4) -> 275995.24 | AI2: =('Prix des produits et services '!$F$24*'Objectifs de ventes (quantité)'!AJ2)+('Prix des produits et services '!$F$25*'Objectifs de ventes (quantité)'!AJ3)+('Prix des produits et services '!$F$26*'Objectifs de ventes (quantité)'!AJ4) -> 278755.19 | ... AM2: =('Prix des produits et services '!$F$24*'Objectifs de ventes (quantité)'!AN2)+('Prix des produits et services '!$F$25*'Objectifs de ventes (quantité)'!AN3)+('Prix des produits et services '!$F$26*'Objectifs de ventes (quantité)'!AN4) -> 290073.77 | AN2: =SUM(AB2:AM2) -> 3297450.8 | BA2: =SUM(AO2:AZ2) -> 0 | BN2: =SUM(BB2:BM2) -> 0
A3: Achats de matières premières | N3: =SUM(B3:M3) -> 0 | AA3: =SUM(O3:Z3) -> 0 | AN3: =SUM(AB3:AM3) -> 0 | BA3: =SUM(AO3:AZ3) -> 0 | BN3: =SUM(BB3:BM3) -> 0
A4: Variation de stock des marchandises | C4: =C2-B2 -> 0 | D4: =D2-C2 -> 0 | E4: =E2-D2 -> 0 | F4: =F2-E2 -> 0 | G4: =G2-F2 -> 0 | H4: =H2-G2 -> 0 | I4: =I2-H2 -> 0 | J4: =J2-I2 -> 0 | ... M4: =M2-L2 -> 0 | N4: =SUM(B4:M4) -> 0 | P4: =P2-O2 -> 7500 | Q4: =Q2-P2 -> 7500 | R4: =R2-Q2 -> 7500 | S4: =S2-R2 -> 7500 | T4: =T2-S2 -> 7500 | U4: =U2-T2 -> 7500 | V4: =V2-U2 -> 7500 | W4: =W2-V2 -> 7500 | ... Z4: =Z2-Y2 -> 15000 | AA4: =SUM(O4:Z4) -> 90000 | AC4: =AC2-AB2 -> 2600 | AD4: =AD2-AC2 -> 2626 | AE4: =AE2-AD2 -> 2652.26 | AF4: =AF2-AE2 -> 2678.7826 | AG4: =AG2-AF2 -> 2705.5704 | AH4: =AH2-AG2 -> 2732.6261 | AI4: =AI2-AH2 -> 2759.9524 | AJ4: =AJ2-AI2 -> 2787.5519 | ... AM4: =AM2-AL2 -> 2872.0175 | AN4: =SUM(AB4:AM4) -> 30073.77 | AP4: =AP2-AO2 -> 0 | AQ4: =AQ2-AP2 -> 0 | AR4: =AR2-AQ2 -> 0 | AS4: =AS2-AR2 -> 0 | AT4: =AT2-AS2 -> 0 | AU4: =AU2-AT2 -> 0 | AV4: =AV2-AU2 -> 0 | AW4: =AW2-AV2 -> 0 | ... AZ4: =AZ2-AY2 -> 0 | BA4: =SUM(AO4:AZ4) -> 0 | BC4: =BC2-BB2 -> 0 | BD4: =BD2-BC2 -> 0 | BE4: =BE2-BD2 -> 0 | BF4: =BF2-BE2 -> 0 | BG4: =BG2-BF2 -> 0 | BH4: =BH2-BG2 -> 0 | BI4: =BI2-BH2 -> 0 | BJ4: =BJ2-BI2 -> 0 | ... BM4: =BM2-BL2 -> 0 | BN4: =SUM(BB4:BM4) -> 0
A5: Variation de stock des matières premières | C5: =C3-B3 -> 0 | D5: =D3-C3 -> 0 | E5: =E3-D3 -> 0 | F5: =F3-E3 -> 0 | G5: =G3-F3 -> 0 | H5: =H3-G3 -> 0 | I5: =I3-H3 -> 0 | J5: =J3-I3 -> 0 | ... M5: =M3-L3 -> 0 | N5: =SUM(B5:M5) -> 0 | P5: =P3-O3 -> 0 | Q5: =Q3-P3 -> 0 | R5: =R3-Q3 -> 0 | S5: =S3-R3 -> 0 | T5: =T3-S3 -> 0 | U5: =U3-T3 -> 0 | V5: =V3-U3 -> 0 | W5: =W3-V3 -> 0 | ... Z5: =Z3-Y3 -> 0 | AA5: =SUM(O5:Z5) -> 0 | AC5: =AC3-AB3 -> 0 | AD5: =AD3-AC3 -> 0 | AE5: =AE3-AD3 -> 0 | AF5: =AF3-AE3 -> 0 | AG5: =AG3-AF3 -> 0 | AH5: =AH3-AG3 -> 0 | AI5: =AI3-AH3 -> 0 | AJ5: =AJ3-AI3 -> 0 | ... AM5: =AM3-AL3 -> 0 | AN5: =SUM(AB5:AM5) -> 0 | AP5: =AP3-AO3 -> 0 | AQ5: =AQ3-AP3 -> 0 | AR5: =AR3-AQ3 -> 0 | AS5: =AS3-AR3 -> 0 | AT5: =AT3-AS3 -> 0 | AU5: =AU3-AT3 -> 0 | AV5: =AV3-AU3 -> 0 | AW5: =AW3-AV3 -> 0 | ... AZ5: =AZ3-AY3 -> 0 | BA5: =SUM(AO5:AZ5) -> 0 | BC5: =BC3-BB3 -> 0 | BD5: =BD3-BC3 -> 0 | BE5: =BE3-BD3 -> 0 | BF5: =BF3-BE3 -> 0 | BG5: =BG3-BF3 -> 0 | BH5: =BH3-BG3 -> 0 | BI5: =BI3-BH3 -> 0 | BJ5: =BJ3-BI3 -> 0 | ... BM5: =BM3-BL3 -> 0 | BN5: =SUM(BB5:BM5) -> 0
A6: Achats stockés de matières et fournitures consommables | N6: =SUM(B6:M6) -> 0 | AA6: =SUM(O6:Z6) -> 0 | AN6: =SUM(AB6:AM6) -> 0 | BA6: =SUM(AO6:AZ6) -> 0 | BN6: =SUM(BB6:BM6) -> 0
A7: Autres achats (achats d'études et prestation de services) | N7: =SUM(B7:M7) -> 0 | AA7: =SUM(O7:Z7) -> 0 | AN7: =SUM(AB7:AM7) -> 0 | BA7: =SUM(AO7:AZ7) -> 0 | BN7: =SUM(BB7:BM7) -> 0
A8: Achats d'emballages | N8: =SUM(B8:M8) -> 0 | O8: =0.05*O2 -> 3750 | P8: =0.05*P2 -> 4125 | Q8: =0.05*Q2 -> 4500 | R8: =0.05*R2 -> 4875 | S8: =0.05*S2 -> 5250 | T8: =0.05*T2 -> 5625 | U8: =0.05*U2 -> 6000 | V8: =0.05*V2 -> 6375 | ... Z8: =0.05*Z2 -> 8250 | AA8: =SUM(O8:Z8) -> 70125 | AB8: =0.05*AB2 -> 13000 | AC8: =0.05*AC2 -> 13130 | AD8: =0.05*AD2 -> 13261.3 | AE8: =0.05*AE2 -> 13393.913 | AF8: =0.05*AF2 -> 13527.852 | AG8: =0.05*AG2 -> 13663.131 | AH8: =0.05*AH2 -> 13799.762 | AI8: =0.05*AI2 -> 13937.76 | ... AM8: =0.05*AM2 -> 14503.689 | AN8: =SUM(AB8:AM8) -> 164872.54 | BA8: =SUM(AO8:AZ8) -> 0 | BN8: =SUM(BB8:BM8) -> 0
A9: Transport sur achats | N9: =SUM(B9:M9) -> 0 | O9: =0.1*O2 -> 7500 | P9: =0.1*P2 -> 8250 | Q9: =0.1*Q2 -> 9000 | R9: =0.1*R2 -> 9750 | S9: =0.1*S2 -> 10500 | T9: =0.1*T2 -> 11250 | U9: =0.1*U2 -> 12000 | V9: =0.1*V2 -> 12750 | ... Z9: =0.1*Z2 -> 16500 | AA9: =SUM(O9:Z9) -> 140250 | AB9: =0.1*AB2 -> 26000 | AC9: =0.1*AC2 -> 26260 | AD9: =0.1*AD2 -> 26522.6 | AE9: =0.1*AE2 -> 26787.826 | AF9: =0.1*AF2 -> 27055.704 | AG9: =0.1*AG2 -> 27326.261 | AH9: =0.1*AH2 -> 27599.524 | AI9: =0.1*AI2 -> 27875.519 | ... AM9: =0.1*AM2 -> 29007.377 | AN9: =SUM(AB9:AM9) -> 329745.08 | BA9: =SUM(AO9:AZ9) -> 0 | BN9: =SUM(BB9:BM9) -> 0
A10: Transports sur ventes | N10: =SUM(B10:M10) -> 0 | O10: =O2*0.1 -> 7500 | P10: =P2*0.1 -> 8250 | Q10: =Q2*0.1 -> 9000 | R10: =R2*0.1 -> 9750 | S10: =S2*0.1 -> 10500 | T10: =T2*0.1 -> 11250 | U10: =U2*0.1 -> 12000 | V10: =V2*0.1 -> 12750 | ... Z10: =Z2*0.1 -> 16500 | AA10: =SUM(O10:Z10) -> 140250 | AB10: =AB2*0.1 -> 26000 | AC10: =AC2*0.1 -> 26260 | AD10: =AD2*0.1 -> 26522.6 | AE10: =AE2*0.1 -> 26787.826 | AF10: =AF2*0.1 -> 27055.704 | AG10: =AG2*0.1 -> 27326.261 | AH10: =AH2*0.1 -> 27599.524 | AI10: =AI2*0.1 -> 27875.519 | ... AM10: =AM2*0.1 -> 29007.377 | AN10: =SUM(AB10:AM10) -> 329745.08 | BA10: =SUM(AO10:AZ10) -> 0 | BN10: =SUM(BB10:BM10) -> 0
A11: Transport pour le compte de tiers | N11: =SUM(B11:M11) -> 0 | AA11: =SUM(O11:Z11) -> 0 | AN11: =SUM(AB11:AM11) -> 0 | BA11: =SUM(AO11:AZ11) -> 0 | BN11: =SUM(BB11:BM11) -> 0
A12: Transport de plis | N12: =SUM(B12:M12) -> 0 | AA12: =SUM(O12:Z12) -> 0 | AN12: =SUM(AB12:AM12) -> 0 | BA12: =SUM(AO12:AZ12) -> 0 | BN12: =SUM(BB12:BM12) -> 0
A13: Autres frais de transport (Voyage, déplacement) | B13: =150000 -> 150000 | C13: =150000 -> 150000 | D13: =150000 -> 150000 | E13: =150000 -> 150000 | F13: =150000 -> 150000 | G13: =150000 -> 150000 | H13: =150000 -> 150000 | I13: =150000 -> 150000 | ... M13: =150000 -> 150000 | N13: =SUM(B13:M13) -> 1800000 | O13: =150000 -> 150000 | P13: =150000 -> 150000 | Q13: =150000 -> 150000 | R13: =150000 -> 150000 | S13: =150000 -> 150000 | T13: =150000 -> 150000 | U13: =150000 -> 150000 | V13: =150000 -> 150000 | ... Z13: =150000 -> 150000 | AA13: =SUM(O13:Z13) -> 1800000 | AB13: =150000 -> 150000 | AC13: =150000 -> 150000 | AD13: =150000 -> 150000 | AE13: =150000 -> 150000 | AF13: =150000 -> 150000 | AG13: =150000 -> 150000 | AH13: =150000 -> 150000 | AI13: =150000 -> 150000 | ... AM13: =150000 -> 150000 | AN13: =SUM(AB13:AM13) -> 1800000 | BA13: =SUM(AO13:AZ13) -> 0 | BN13: =SUM(BB13:BM13) -> 0
A14: Sous traitance générale | N14: =SUM(B14:M14) -> 0 | AA14: =SUM(O14:Z14) -> 0 | AN14: =SUM(AB14:AM14) -> 0 | BA14: =SUM(AO14:AZ14) -> 0 | BN14: =SUM(BB14:BM14) -> 0
A15: Publicité, publications, relations publiques | B15: =0.05*'Chiffre d''affaires prévisionnel'!C22 -> 8750 | C15: =0.05*'Chiffre d''affaires prévisionnel'!D22 -> 17500 | D15: =0.05*'Chiffre d''affaires prévisionnel'!E22 -> 26250 | E15: =0.05*'Chiffre d''affaires prévisionnel'!F22 -> 35000 | F15: =0.05*'Chiffre d''affaires prévisionnel'!G22 -> 43750 | G15: =0.05*'Chiffre d''affaires prévisionnel'!H22 -> 52500 | H15: =0.05*'Chiffre d''affaires prévisionnel'!I22 -> 70000 | I15: =0.05*'Chiffre d''affaires prévisionnel'!J22 -> 78750 | ... M15: =0.05*'Chiffre d''affaires prévisionnel'!N22 -> 78750 | N15: =SUM(B15:M15) -> 647500 | O15: =0.05*'Chiffre d''affaires prévisionnel'!P22 -> 87500 | P15: =0.05*'Chiffre d''affaires prévisionnel'!Q22 -> 96250 | Q15: =0.05*'Chiffre d''affaires prévisionnel'!R22 -> 105000 | R15: =0.05*'Chiffre d''affaires prévisionnel'!S22 -> 113750 | S15: =0.05*'Chiffre d''affaires prévisionnel'!T22 -> 122500 | T15: =0.05*'Chiffre d''affaires prévisionnel'!U22 -> 131250 | U15: =0.05*'Chiffre d''affaires prévisionnel'!V22 -> 140000 | V15: =0.05*'Chiffre d''affaires prévisionnel'!W22 -> 148750 | ... Z15: =0.05*'Chiffre d''affaires prévisionnel'!AA22 -> 192500 | AA15: =SUM(O15:Z15) -> 1636250 | AB15: =0.05*'Chiffre d''affaires prévisionnel'!AC22 -> 260000 | AC15: =0.05*'Chiffre d''affaires prévisionnel'!AD22 -> 262600 | AD15: =0.05*'Chiffre d''affaires prévisionnel'!AE22 -> 265226 | AE15: =0.05*'Chiffre d''affaires prévisionnel'!AF22 -> 267878.26 | AF15: =0.05*'Chiffre d''affaires prévisionnel'!AG22 -> 270557.04 | AG15: =0.05*'Chiffre d''affaires prévisionnel'!AH22 -> 273262.61 | AH15: =0.05*'Chiffre d''affaires prévisionnel'!AI22 -> 275995.24 | AI15: =0.05*'Chiffre d''affaires prévisionnel'!AJ22 -> 278755.19 | ... AM15: =0.05*'Chiffre d''affaires prévisionnel'!AN22 -> 290073.77 | AN15: =SUM(AB15:AM15) -> 3297450.8 | BA15: =SUM(AO15:AZ15) -> 0 | BN15: =SUM(BB15:BM15) -> 0
A16: Frais de télécommunications | B16: 50000 | C16: 50000 | D16: 50000 | E16: 50000 | F16: 50000 | G16: 50000 | H16: 50000 | I16: 50000 | J16: 50000 | K16: 50000 | L16: 50000 | M16: 50000 | N16: =SUM(B16:M16) -> 600000 | O16: 50000 | P16: 50000 | Q16: 50000 | R16: 50000 | S16: 50000 | T16: 50000 | U16: 50000 | V16: 50000 | W16: 50000 | X16: 50000 | Y16: 50000 | Z16: 50000 | AA16: =SUM(O16:Z16) -> 600000 | AB16: 50000 | AC16: 50000 | AD16: 50000 | AE16: 50000 | AF16: 50000 | AG16: 50000 | AH16: 50000 | AI16: 50000 | AJ16: 50000 | AK16: 50000 | AL16: 50000 | AM16: 50000 | AN16: =SUM(AB16:AM16) -> 600000 | BA16: =SUM(AO16:AZ16) -> 0 | BN16: =SUM(BB16:BM16) -> 0
A17: Frais bancaires | B17: 5000 | C17: 5000 | D17: 5000 | E17: 5000 | F17: 5000 | G17: 5000 | H17: 5000 | I17: 5000 | J17: 5000 | K17: 5000 | L17: 5000 | M17: 5000 | N17: =SUM(B17:M17) -> 60000 | O17: 5000 | P17: 5000 | Q17: 5000 | R17: 5000 | S17: 5000 | T17: 5000 | U17: 5000 | V17: 5000 | W17: 5000 | X17: 5000 | Y17: 5000 | Z17: 5000 | AA17: =SUM(O17:Z17) -> 60000 | AB17: 5000 | AC17: 5000 | AD17: 5000 | AE17: 5000 | AF17: 5000 | AG17: 5000 | AH17: 5000 | AI17: 5000 | AJ17: 5000 | AK17: 5000 | AL17: 5000 | AM17: 5000 | AN17: =SUM(AB17:AM17) -> 60000 | BA17: =SUM(AO17:AZ17) -> 0 | BN17: =SUM(BB17:BM17) -> 0
A18: Rémunérations d’intermédiaires et de conseils | B18: =0.1*'Chiffre d''affaires prévisionnel'!C22 -> 17500 | C18: =0.1*'Chiffre d''affaires prévisionnel'!D22 -> 35000 | D18: =0.1*'Chiffre d''affaires prévisionnel'!E22 -> 52500 | E18: =0.1*'Chiffre d''affaires prévisionnel'!F22 -> 70000 | F18: =0.1*'Chiffre d''affaires prévisionnel'!G22 -> 87500 | G18: =0.1*'Chiffre d''affaires prévisionnel'!H22 -> 105000 | H18: =0.1*'Chiffre d''affaires prévisionnel'!I22 -> 140000 | I18: =0.1*'Chiffre d''affaires prévisionnel'!J22 -> 157500 | ... M18: =0.1*'Chiffre d''affaires prévisionnel'!N22 -> 157500 | N18: =SUM(B18:M18) -> 1295000 | O18: =0.1*'Chiffre d''affaires prévisionnel'!P22 -> 175000 | P18: =0.1*'Chiffre d''affaires prévisionnel'!Q22 -> 192500 | Q18: =0.1*'Chiffre d''affaires prévisionnel'!R22 -> 210000 | R18: =0.1*'Chiffre d''affaires prévisionnel'!S22 -> 227500 | S18: =0.1*'Chiffre d''affaires prévisionnel'!T22 -> 245000 | T18: =0.1*'Chiffre d''affaires prévisionnel'!U22 -> 262500 | U18: =0.1*'Chiffre d''affaires prévisionnel'!V22 -> 280000 | V18: =0.1*'Chiffre d''affaires prévisionnel'!W22 -> 297500 | ... Z18: =0.1*'Chiffre d''affaires prévisionnel'!AA22 -> 385000 | AA18: =SUM(O18:Z18) -> 3272500 | AB18: =0.1*'Chiffre d''affaires prévisionnel'!AC22 -> 520000 | AC18: =0.1*'Chiffre d''affaires prévisionnel'!AD22 -> 525200 | AD18: =0.1*'Chiffre d''affaires prévisionnel'!AE22 -> 530452 | AE18: =0.1*'Chiffre d''affaires prévisionnel'!AF22 -> 535756.52 | AF18: =0.1*'Chiffre d''affaires prévisionnel'!AG22 -> 541114.09 | AG18: =0.1*'Chiffre d''affaires prévisionnel'!AH22 -> 546525.23 | AH18: =0.1*'Chiffre d''affaires prévisionnel'!AI22 -> 551990.48 | AI18: =0.1*'Chiffre d''affaires prévisionnel'!AJ22 -> 557510.38 | ... AM18: =0.1*'Chiffre d''affaires prévisionnel'!AN22 -> 580147.54 | AN18: =SUM(AB18:AM18) -> 6594901.6 | BA18: =SUM(AO18:AZ18) -> 0 | BN18: =SUM(BB18:BM18) -> 0
A19: Frais de formation du personnel | G19: 100000 | H19: 100000 | I19: 100000 | J19: 100000 | K19: 100000 | L19: 100000 | M19: 100000 | N19: =SUM(B19:M19) -> 700000 | O19: 100000 | P19: 100000 | Q19: 100000 | R19: 100000 | S19: 100000 | T19: 100000 | U19: 100000 | V19: 100000 | W19: 100000 | X19: 100000 | Y19: 100000 | Z19: 100000 | AA19: =SUM(O19:Z19) -> 1200000 | AB19: 100000 | AC19: 100000 | AD19: 100000 | AE19: 100000 | AF19: 100000 | AG19: 100000 | AH19: 100000 | AI19: 100000 | AJ19: 100000 | AK19: 100000 | AL19: 100000 | AM19: 100000 | AN19: =SUM(AB19:AM19) -> 1200000 | BA19: =SUM(AO19:AZ19) -> 0 | BN19: =SUM(BB19:BM19) -> 0
A20: Redevances pour brevets, licences, logiciels et droits similaires | B20: ='Chiffre d''affaires prévisionnel'!C22*0.15 -> 26250 | C20: ='Chiffre d''affaires prévisionnel'!D22*0.15 -> 52500 | D20: ='Chiffre d''affaires prévisionnel'!E22*0.15 -> 78750 | E20: ='Chiffre d''affaires prévisionnel'!F22*0.15 -> 105000 | F20: ='Chiffre d''affaires prévisionnel'!G22*0.15 -> 131250 | G20: ='Chiffre d''affaires prévisionnel'!H22*0.15 -> 157500 | H20: ='Chiffre d''affaires prévisionnel'!I22*0.15 -> 210000 | I20: ='Chiffre d''affaires prévisionnel'!J22*0.15 -> 236250 | ... M20: ='Chiffre d''affaires prévisionnel'!N22*0.15 -> 236250 | N20: =SUM(B20:M20) -> 1942500 | O20: ='Chiffre d''affaires prévisionnel'!P22*0.15 -> 262500 | P20: ='Chiffre d''affaires prévisionnel'!Q22*0.15 -> 288750 | Q20: ='Chiffre d''affaires prévisionnel'!R22*0.15 -> 315000 | R20: ='Chiffre d''affaires prévisionnel'!S22*0.15 -> 341250 | S20: ='Chiffre d''affaires prévisionnel'!T22*0.15 -> 367500 | T20: ='Chiffre d''affaires prévisionnel'!U22*0.15 -> 393750 | U20: ='Chiffre d''affaires prévisionnel'!V22*0.15 -> 420000 | V20: ='Chiffre d''affaires prévisionnel'!W22*0.15 -> 446250 | ... Z20: ='Chiffre d''affaires prévisionnel'!AA22*0.15 -> 577500 | AA20: =SUM(O20:Z20) -> 4908750 | AB20: ='Chiffre d''affaires prévisionnel'!AC22*0.15 -> 780000 | AC20: ='Chiffre d''affaires prévisionnel'!AD22*0.15 -> 787800 | AD20: ='Chiffre d''affaires prévisionnel'!AE22*0.15 -> 795678 | AE20: ='Chiffre d''affaires prévisionnel'!AF22*0.15 -> 803634.78 | AF20: ='Chiffre d''affaires prévisionnel'!AG22*0.15 -> 811671.13 | AG20: ='Chiffre d''affaires prévisionnel'!AH22*0.15 -> 819787.84 | AH20: ='Chiffre d''affaires prévisionnel'!AI22*0.15 -> 827985.72 | AI20: ='Chiffre d''affaires prévisionnel'!AJ22*0.15 -> 836265.57 | ... AM20: ='Chiffre d''affaires prévisionnel'!AN22*0.15 -> 870221.31 | AN20: =SUM(AB20:AM20) -> 9892352.4 | BA20: =SUM(AO20:AZ20) -> 0 | BN20: =SUM(BB20:BM20) -> 0
A21: Rémunérations de personnel extérieur à l’entreprise | B21: 200000 | C21: 200000 | D21: 200000 | E21: 200000 | F21: 200000 | G21: 200000 | H21: 200000 | I21: 200000 | J21: 200000 | K21: 200000 | L21: 200000 | M21: 200000 | N21: =SUM(B21:M21) -> 2400000 | O21: 400000 | P21: 400000 | Q21: 400000 | R21: 400000 | S21: 400000 | T21: 400000 | U21: 400000 | V21: 400000 | W21: 400000 | X21: 400000 | Y21: 400000 | Z21: 400000 | AA21: =SUM(O21:Z21) -> 4800000 | AB21: 600000 | AC21: 600000 | AD21: 600000 | AE21: 600000 | AF21: 600000 | AG21: 600000 | AH21: 600000 | AI21: 600000 | AJ21: 600000 | AK21: 600000 | AL21: 600000 | AM21: 600000 | AN21: =SUM(AB21:AM21) -> 7200000
A22: Autres charges externes (Frais de recrutement, de déménagement)
A23: TOTAL DES CHARGES VARIABLES | B23: =SUM(B2:B22) -> 457500 | C23: =SUM(C2:C22) -> 510000 | D23: =SUM(D2:D22) -> 562500 | E23: =SUM(E2:E22) -> 615000 | F23: =SUM(F2:F22) -> 667500 | G23: =SUM(G2:G22) -> 820000 | H23: =SUM(H2:H22) -> 925000 | I23: =SUM(I2:I22) -> 977500 | ... M23: =SUM(M2:M22) -> 977500 | N23: =SUM(B23:M23) -> 9445000 | O23: =SUM(O2:O22) -> 1323750 | P23: =SUM(P2:P22) -> 1393125 | Q23: =SUM(Q2:Q22) -> 1455000 | R23: =SUM(R2:R22) -> 1516875 | S23: =SUM(S2:S22) -> 1578750 | T23: =SUM(T2:T22) -> 1640625 | U23: =SUM(U2:U22) -> 1702500 | V23: =SUM(V2:V22) -> 1764375 | ... Z23: =SUM(Z2:Z22) -> 2081250 | AA23: =SUM(O23:Z23) -> 20120625 | AB23: =SUM(AB2:AB22) -> 2790000 | AC23: =SUM(AC2:AC22) -> 2811450 | AD23: =SUM(AD2:AD22) -> 2830514.5 | AE23: =SUM(AE2:AE22) -> 2849769.6 | AF23: =SUM(AF2:AF22) -> 2869217.3 | AG23: =SUM(AG2:AG22) -> 2888859.5 | AH23: =SUM(AH2:AH22) -> 2908698.1 | AI23: =SUM(AI2:AI22) -> 2928735.1 | ... AM23: =SUM(AM2:AM22) -> 3010906.9 | AN23: =SUM(AB23:AM23) -> 34796592 | BA23: =SUM(AO23:AZ23) -> 0 | BN23: =SUM(BB23:BM23) -> 0
A26: Objectif de la dette fournisseur en pourcentage des charges variables | B26: =0.3 -> 0.3
A28: Stock de sécurité en pourcentage des matières premières et des marchandises | B28: =0.3 -> 0.3

Sheet Calcul intermédiaires CF
A1: Numéro de compte | B1: Liste des charges fixes | C1: Cout unitaire mensuel | D1: Quantité | E1: 45292 | F1: 45323 | G1: 45352 | H1: 45383 | I1: 45413 | J1: 45444 | K1: 45474 | L1: 45505 | M1: 45536 | N1: 45566 | O1: 45597 | P1: 45627 | Q1: Total 2024 | R1: 45658 | S1: 45689 | T1: 45717 | U1: 45748 | V1: 45778 | W1: 45809 | X1: 45839 | Y1: 45870 | Z1: 45901 | AA1: 45931 | AB1: 45962 | AC1: 45992 | AD1: Total 2025 | AE1: 46023 | AF1: 46054 | AG1: 46082 | AH1: 46113 | AI1: 46143 | AJ1: 46174 | AK1: 46204 | AL1: 46235 | AM1: 46266 | AN1: 46296 | AO1: 46327 | AP1: 46357 | AQ1: Total 2026 | AR1: 46388 | AS1: 46419 | AT1: 46447 | AU1: 46478 | AV1: 46508 | AW1: 46539 | AX1: 46569 | AY1: 46600 | AZ1: 46631 | BA1: 46661 | BB1: 46692 | BC1: 46722 | BD1: Total 2027 | BE1: 46753 | BF1: 46784 | BG1: 46813 | BH1: 46844 | BI1: 46874 | BJ1: 46905 | BK1: 46935 | BL1: 46966 | BM1: 46997 | BN1: 47027 | BO1: 47058 | BP1: 47088 | BQ1: Total 2028
B2: Frais de location des machines | Q2: =SUM(E2:P2) -> 0
B3: Redevances de crédit bail | Q3: =SUM(E3:P3) -> 0
B4: Entretiens, réparations et maintenance (60 % du montant des investissements amortis sur 48 mois) | Q4: =SUM(E4:P4) -> 0 | R4: =$C$4 -> 0 | S4: =$C$4 -> 0 | T4: =$C$4 -> 0 | U4: =$C$4 -> 0 | V4: =$C$4 -> 0 | W4: =$C$4 -> 0 | X4: =$C$4 -> 0 | Y4: =$C$4 -> 0 | ... AC4: =$C$4 -> 0 | AD4: =SUM(R4:AC4) -> 0 | AE4: =$C$4 -> 0 | AF4: =$C$4 -> 0 | AG4: =$C$4 -> 0 | AH4: =$C$4 -> 0 | AI4: =$C$4 -> 0 | AJ4: =$C$4 -> 0 | AK4: =$C$4 -> 0 | AL4: =$C$4 -> 0 | ... AP4: =$C$4 -> 0 | AQ4: =SUM(AE4:AP4) -> 0 | AR4: =$C$4 -> 0 | AS4: =$C$4 -> 0 | AT4: =$C$4 -> 0 | AU4: =$C$4 -> 0 | AV4: =$C$4 -> 0 | AW4: =$C$4 -> 0 | AX4: =$C$4 -> 0 | AY4: =$C$4 -> 0 | ... BC4: =$C$4 -> 0 | BD4: =SUM(AR4:BC4) -> 0 | BE4: =$C$4 -> 0 | BF4: =$C$4 -> 0 | BG4: =$C$4 -> 0 | BH4: =$C$4 -> 0 | BI4: =$C$4 -> 0 | BJ4: =$C$4 -> 0 | BK4: =$C$4 -> 0 | BL4: =$C$4 -> 0 | ... BP4: =$C$4 -> 0 | BQ4: =SUM(BE4:BP4) -> 0
B5: Prime d'assurances perte de production
B6: Prime d'assurances responsabilité civile
B7: Prime d'assurances Matériel de production
B8: Administrateurs (Forfait annuel) | Q8: =SUM(E8:P8) -> 0 | AD8: =SUM(R8:AC8) -> 0 | AQ8: =SUM(AE8:AP8) -> 0 | AR8: =$C$8*$D$8 -> 0 | AS8: =$C$8*$D$8 -> 0 | AT8: =$C$8*$D$8 -> 0 | AU8: =$C$8*$D$8 -> 0 | AV8: =$C$8*$D$8 -> 0 | AW8: =$C$8*$D$8 -> 0 | AX8: =$C$8*$D$8 -> 0 | AY8: =$C$8*$D$8 -> 0 | ... BC8: =$C$8*$D$8 -> 0 | BD8: =SUM(AR8:BC8) -> 0 | BE8: =$C$8*$D$8 -> 0 | BF8: =$C$8*$D$8 -> 0 | BG8: =$C$8*$D$8 -> 0 | BH8: =$C$8*$D$8 -> 0 | BI8: =$C$8*$D$8 -> 0 | BJ8: =$C$8*$D$8 -> 0 | BK8: =$C$8*$D$8 -> 0 | BL8: =$C$8*$D$8 -> 0 | ... BP8: =$C$8*$D$8 -> 0 | BQ8: =SUM(BE8:BP8) -> 0
B9: Salaire DG | Q9: =SUM(E9:P9) -> 0 | R9: =$C$9*$D$9 -> 0 | S9: =$C$9*$D$9 -> 0 | T9: =$C$9*$D$9 -> 0 | U9: =$C$9*$D$9 -> 0 | V9: =$C$9*$D$9 -> 0 | W9: =$C$9*$D$9 -> 0 | X9: =$C$9*$D$9 -> 0 | Y9: =$C$9*$D$9 -> 0 | ... AC9: =$C$9*$D$9 -> 0 | AD9: =SUM(R9:AC9) -> 0 | AE9: =$C$9*$D$9 -> 0 | AF9: =$C$9*$D$9 -> 0 | AG9: =$C$9*$D$9 -> 0 | AH9: =$C$9*$D$9 -> 0 | AI9: =$C$9*$D$9 -> 0 | AJ9: =$C$9*$D$9 -> 0 | AK9: =$C$9*$D$9 -> 0 | AL9: =$C$9*$D$9 -> 0 | ... AP9: =$C$9*$D$9 -> 0 | AQ9: =SUM(AE9:AP9) -> 0 | AR9: =$C$9*$D$9 -> 0 | AS9: =$C$9*$D$9 -> 0 | AT9: =$C$9*$D$9 -> 0 | AU9: =$C$9*$D$9 -> 0 | AV9: =$C$9*$D$9 -> 0 | AW9: =$C$9*$D$9 -> 0 | AX9: =$C$9*$D$9 -> 0 | AY9: =$C$9*$D$9 -> 0 | ... BC9: =$C$9*$D$9 -> 0 | BD9: =SUM(AR9:BC9) -> 0 | BE9: =$C$9*$D$9 -> 0 | BF9: =$C$9*$D$9 -> 0 | BG9: =$C$9*$D$9 -> 0 | BH9: =$C$9*$D$9 -> 0 | BI9: =$C$9*$D$9 -> 0 | BJ9: =$C$9*$D$9 -> 0 | BK9: =$C$9*$D$9 -> 0 | BL9: =$C$9*$D$9 -> 0 | ... BP9: =$C$9*$D$9 -> 0 | BQ9: =SUM(BE9:BP9) -> 0
B10: Salaire secretaire de direction | Q10: =SUM(E10:P10) -> 0 | R10: =$C$10*$D$10 -> 0 | S10: =$C$10*$D$10 -> 0 | T10: =$C$10*$D$10 -> 0 | U10: =$C$10*$D$10 -> 0 | V10: =$C$10*$D$10 -> 0 | W10: =$C$10*$D$10 -> 0 | X10: =$C$10*$D$10 -> 0 | Y10: =$C$10*$D$10 -> 0 | ... AC10: =$C$10*$D$10 -> 0 | AD10: =SUM(R10:AC10) -> 0 | AE10: =$C$10*$D$10 -> 0 | AF10: =$C$10*$D$10 -> 0 | AG10: =$C$10*$D$10 -> 0 | AH10: =$C$10*$D$10 -> 0 | AI10: =$C$10*$D$10 -> 0 | AJ10: =$C$10*$D$10 -> 0 | AK10: =$C$10*$D$10 -> 0 | AL10: =$C$10*$D$10 -> 0 | ... AP10: =$C$10*$D$10 -> 0 | AQ10: =SUM(AE10:AP10) -> 0 | AR10: =$C$10*$D$10 -> 0 | AS10: =$C$10*$D$10 -> 0 | AT10: =$C$10*$D$10 -> 0 | AU10: =$C$10*$D$10 -> 0 | AV10: =$C$10*$D$10 -> 0 | AW10: =$C$10*$D$10 -> 0 | AX10: =$C$10*$D$10 -> 0 | AY10: =$C$10*$D$10 -> 0 | ... BC10: =$C$10*$D$10 -> 0 | BD10: =SUM(AR10:BC10) -> 0 | BE10: =$C$10*$D$10 -> 0 | BF10: =$C$10*$D$10 -> 0 | BG10: =$C$10*$D$10 -> 0 | BH10: =$C$10*$D$10 -> 0 | BI10: =$C$10*$D$10 -> 0 | BJ10: =$C$10*$D$10 -> 0 | BK10: =$C$10*$D$10 -> 0 | BL10: =$C$10*$D$10 -> 0 | ... BP10: =$C$10*$D$10 -> 0 | BQ10: =SUM(BE10:BP10) -> 0
B11: Salaire Chef de département commercial | Q11: =SUM(E11:P11) -> 0 | R11: =$C$11*$D$11 -> 0 | S11: =$C$11*$D$11 -> 0 | T11: =$C$11*$D$11 -> 0 | U11: =$C$11*$D$11 -> 0 | V11: =$C$11*$D$11 -> 0 | W11: =$C$11*$D$11 -> 0 | X11: =$C$11*$D$11 -> 0 | Y11: =$C$11*$D$11 -> 0 | ... AC11: =$C$11*$D$11 -> 0 | AD11: =SUM(R11:AC11) -> 0 | AE11: =$C$11*$D$11 -> 0 | AF11: =$C$11*$D$11 -> 0 | AG11: =$C$11*$D$11 -> 0 | AH11: =$C$11*$D$11 -> 0 | AI11: =$C$11*$D$11 -> 0 | AJ11: =$C$11*$D$11 -> 0 | AK11: =$C$11*$D$11 -> 0 | AL11: =$C$11*$D$11 -> 0 | ... AP11: =$C$11*$D$11 -> 0 | AQ11: =SUM(AE11:AP11) -> 0 | AR11: =$C$11*$D$11 -> 0 | AS11: =$C$11*$D$11 -> 0 | AT11: =$C$11*$D$11 -> 0 | AU11: =$C$11*$D$11 -> 0 | AV11: =$C$11*$D$11 -> 0 | AW11: =$C$11*$D$11 -> 0 | AX11: =$C$11*$D$11 -> 0 | AY11: =$C$11*$D$11 -> 0 | ... BC11: =$C$11*$D$11 -> 0 | BD11: =SUM(AR11:BC11) -> 0 | BE11: =$C$11*$D$11 -> 0 | BF11: =$C$11*$D$11 -> 0 | BG11: =$C$11*$D$11 -> 0 | BH11: =$C$11*$D$11 -> 0 | BI11: =$C$11*$D$11 -> 0 | BJ11: =$C$11*$D$11 -> 0 | BK11: =$C$11*$D$11 -> 0 | BL11: =$C$11*$D$11 -> 0 | ... BP11: =$C$11*$D$11 -> 0 | BQ11: =SUM(BE11:BP11) -> 0
B12: Salaire service placement de la production | Q12: =SUM(E12:P12) -> 0 | R12: =$C$12*$D$12 -> 0 | S12: =$C$12*$D$12 -> 0 | T12: =$C$12*$D$12 -> 0 | U12: =$C$12*$D$12 -> 0 | V12: =$C$12*$D$12 -> 0 | W12: =$C$12*$D$12 -> 0 | X12: =$C$12*$D$12 -> 0 | Y12: =$C$12*$D$12 -> 0 | ... AC12: =$C$12*$D$12 -> 0 | AD12: =SUM(R12:AC12) -> 0 | AE12: =$C$12*$D$12 -> 0 | AF12: =$C$12*$D$12 -> 0 | AG12: =$C$12*$D$12 -> 0 | AH12: =$C$12*$D$12 -> 0 | AI12: =$C$12*$D$12 -> 0 | AJ12: =$C$12*$D$12 -> 0 | AK12: =$C$12*$D$12 -> 0 | AL12: =$C$12*$D$12 -> 0 | ... AP12: =$C$12*$D$12 -> 0 | AQ12: =SUM(AE12:AP12) -> 0 | AR12: =$C$12*$D$12 -> 0 | AS12: =$C$12*$D$12 -> 0 | AT12: =$C$12*$D$12 -> 0 | AU12: =$C$12*$D$12 -> 0 | AV12: =$C$12*$D$12 -> 0 | AW12: =$C$12*$D$12 -> 0 | AX12: =$C$12*$D$12 -> 0 | AY12: =$C$12*$D$12 -> 0 | ... BC12: =$C$12*$D$12 -> 0 | BD12: =SUM(AR12:BC12) -> 0 | BE12: =$C$12*$D$12 -> 0 | BF12: =$C$12*$D$12 -> 0 | BG12: =$C$12*$D$12 -> 0 | BH12: =$C$12*$D$12 -> 0 | BI12: =$C$12*$D$12 -> 0 | BJ12: =$C$12*$D$12 -> 0 | BK12: =$C$12*$D$12 -> 0 | BL12: =$C$12*$D$12 -> 0 | ... BP12: =$C$12*$D$12 -> 0 | BQ12: =SUM(BE12:BP12) -> 0
B13: Salaire service de l'approvisionnement | Q13: =SUM(E13:P13) -> 0 | R13: =$C$13*$D$13 -> 0 | S13: =$C$13*$D$13 -> 0 | T13: =$C$13*$D$13 -> 0 | U13: =$C$13*$D$13 -> 0 | V13: =$C$13*$D$13 -> 0 | W13: =$C$13*$D$13 -> 0 | X13: =$C$13*$D$13 -> 0 | Y13: =$C$13*$D$13 -> 0 | ... AC13: =$C$13*$D$13 -> 0 | AD13: =SUM(R13:AC13) -> 0 | AE13: =$C$13*$D$13 -> 0 | AF13: =$C$13*$D$13 -> 0 | AG13: =$C$13*$D$13 -> 0 | AH13: =$C$13*$D$13 -> 0 | AI13: =$C$13*$D$13 -> 0 | AJ13: =$C$13*$D$13 -> 0 | AK13: =$C$13*$D$13 -> 0 | AL13: =$C$13*$D$13 -> 0 | ... AP13: =$C$13*$D$13 -> 0 | AQ13: =SUM(AE13:AP13) -> 0 | AR13: =$C$13*$D$13 -> 0 | AS13: =$C$13*$D$13 -> 0 | AT13: =$C$13*$D$13 -> 0 | AU13: =$C$13*$D$13 -> 0 | AV13: =$C$13*$D$13 -> 0 | AW13: =$C$13*$D$13 -> 0 | AX13: =$C$13*$D$13 -> 0 | AY13: =$C$13*$D$13 -> 0 | ... BC13: =$C$13*$D$13 -> 0 | BD13: =SUM(AR13:BC13) -> 0 | BE13: =$C$13*$D$13 -> 0 | BF13: =$C$13*$D$13 -> 0 | BG13: =$C$13*$D$13 -> 0 | BH13: =$C$13*$D$13 -> 0 | BI13: =$C$13*$D$13 -> 0 | BJ13: =$C$13*$D$13 -> 0 | BK13: =$C$13*$D$13 -> 0 | BL13: =$C$13*$D$13 -> 0 | ... BP13: =$C$13*$D$13 -> 0 | BQ13: =SUM(BE13:BP13) -> 0
B14: Salaire Chef de département Sécurité du domaine | Q14: =SUM(E14:P14) -> 0 | R14: =$C$14*$D$14 -> 0 | S14: =$C$14*$D$14 -> 0 | T14: =$C$14*$D$14 -> 0 | U14: =$C$14*$D$14 -> 0 | V14: =$C$14*$D$14 -> 0 | W14: =$C$14*$D$14 -> 0 | X14: =$C$14*$D$14 -> 0 | Y14: =$C$14*$D$14 -> 0 | ... AC14: =$C$14*$D$14 -> 0 | AD14: =SUM(R14:AC14) -> 0 | AE14: =$C$14*$D$14 -> 0 | AF14: =$C$14*$D$14 -> 0 | AG14: =$C$14*$D$14 -> 0 | AH14: =$C$14*$D$14 -> 0 | AI14: =$C$14*$D$14 -> 0 | AJ14: =$C$14*$D$14 -> 0 | AK14: =$C$14*$D$14 -> 0 | AL14: =$C$14*$D$14 -> 0 | ... AP14: =$C$14*$D$14 -> 0 | AQ14: =SUM(AE14:AP14) -> 0 | AR14: =$C$14*$D$14 -> 0 | AS14: =$C$14*$D$14 -> 0 | AT14: =$C$14*$D$14 -> 0 | AU14: =$C$14*$D$14 -> 0 | AV14: =$C$14*$D$14 -> 0 | AW14: =$C$14*$D$14 -> 0 | AX14: =$C$14*$D$14 -> 0 | AY14: =$C$14*$D$14 -> 0 | ... BC14: =$C$14*$D$14 -> 0 | BD14: =SUM(AR14:BC14) -> 0 | BE14: =$C$14*$D$14 -> 0 | BF14: =$C$14*$D$14 -> 0 | BG14: =$C$14*$D$14 -> 0 | BH14: =$C$14*$D$14 -> 0 | BI14: =$C$14*$D$14 -> 0 | BJ14: =$C$14*$D$14 -> 0 | BK14: =$C$14*$D$14 -> 0 | BL14: =$C$14*$D$14 -> 0 | ... BP14: =$C$14*$D$14 -> 0 | BQ14: =SUM(BE14:BP14) -> 0
B15: Salaire Gardiens | Q15: =SUM(E15:P15) -> 0 | R15: =$C$15*$D$15 -> 0 | S15: =$C$15*$D$15 -> 0 | T15: =$C$15*$D$15 -> 0 | U15: =$C$15*$D$15 -> 0 | V15: =$C$15*$D$15 -> 0 | W15: =$C$15*$D$15 -> 0 | X15: =$C$15*$D$15 -> 0 | Y15: =$C$15*$D$15 -> 0 | ... AC15: =$C$15*$D$15 -> 0 | AD15: =SUM(R15:AC15) -> 0 | AE15: =$C$15*$D$15 -> 0 | AF15: =$C$15*$D$15 -> 0 | AG15: =$C$15*$D$15 -> 0 | AH15: =$C$15*$D$15 -> 0 | AI15: =$C$15*$D$15 -> 0 | AJ15: =$C$15*$D$15 -> 0 | AK15: =$C$15*$D$15 -> 0 | AL15: =$C$15*$D$15 -> 0 | ... AP15: =$C$15*$D$15 -> 0 | AQ15: =SUM(AE15:AP15) -> 0 | AR15: =$C$15*$D$15 -> 0 | AS15: =$C$15*$D$15 -> 0 | AT15: =$C$15*$D$15 -> 0 | AU15: =$C$15*$D$15 -> 0 | AV15: =$C$15*$D$15 -> 0 | AW15: =$C$15*$D$15 -> 0 | AX15: =$C$15*$D$15 -> 0 | AY15: =$C$15*$D$15 -> 0 | ... BC15: =$C$15*$D$15 -> 0 | BD15: =SUM(AR15:BC15) -> 0 | BE15: =$C$15*$D$15 -> 0 | BF15: =$C$15*$D$15 -> 0 | BG15: =$C$15*$D$15 -> 0 | BH15: =$C$15*$D$15 -> 0 | BI15: =$C$15*$D$15 -> 0 | BJ15: =$C$15*$D$15 -> 0 | BK15: =$C$15*$D$15 -> 0 | BL15: =$C$15*$D$15 -> 0 | ... BP15: =$C$15*$D$15 -> 0 | BQ15: =SUM(BE15:BP15) -> 0
B16: Salaire Chef de la division technique | Q16: =SUM(E16:P16) -> 0 | R16: =$C$16*$D$16 -> 0 | S16: =$C$16*$D$16 -> 0 | T16: =$C$16*$D$16 -> 0 | U16: =$C$16*$D$16 -> 0 | V16: =$C$16*$D$16 -> 0 | W16: =$C$16*$D$16 -> 0 | X16: =$C$16*$D$16 -> 0 | Y16: =$C$16*$D$16 -> 0 | ... AC16: =$C$16*$D$16 -> 0 | AD16: =SUM(R16:AC16) -> 0 | AE16: =$C$16*$D$16 -> 0 | AF16: =$C$16*$D$16 -> 0 | AG16: =$C$16*$D$16 -> 0 | AH16: =$C$16*$D$16 -> 0 | AI16: =$C$16*$D$16 -> 0 | AJ16: =$C$16*$D$16 -> 0 | AK16: =$C$16*$D$16 -> 0 | AL16: =$C$16*$D$16 -> 0 | ... AP16: =$C$16*$D$16 -> 0 | AQ16: =SUM(AE16:AP16) -> 0 | AR16: =$C$16*$D$16 -> 0 | AS16: =$C$16*$D$16 -> 0 | AT16: =$C$16*$D$16 -> 0 | AU16: =$C$16*$D$16 -> 0 | AV16: =$C$16*$D$16 -> 0 | AW16: =$C$16*$D$16 -> 0 | AX16: =$C$16*$D$16 -> 0 | AY16: =$C$16*$D$16 -> 0 | ... BC16: =$C$16*$D$16 -> 0 | BD16: =SUM(AR16:BC16) -> 0 | BE16: =$C$16*$D$16 -> 0 | BF16: =$C$16*$D$16 -> 0 | BG16: =$C$16*$D$16 -> 0 | BH16: =$C$16*$D$16 -> 0 | BI16: =$C$16*$D$16 -> 0 | BJ16: =$C$16*$D$16 -> 0 | BK16: =$C$16*$D$16 -> 0 | BL16: =$C$16*$D$16 -> 0 | ... BP16: =$C$16*$D$16 -> 0 | BQ16: =SUM(BE16:BP16) -> 0
B17: Salaire Secrétaire du chef de division | Q17: =SUM(E17:P17) -> 0 | R17: =$C$17*$D$17 -> 0 | S17: =$C$17*$D$17 -> 0 | T17: =$C$17*$D$17 -> 0 | U17: =$C$17*$D$17 -> 0 | V17: =$C$17*$D$17 -> 0 | W17: =$C$17*$D$17 -> 0 | X17: =$C$17*$D$17 -> 0 | Y17: =$C$17*$D$17 -> 0 | ... AC17: =$C$17*$D$17 -> 0 | AD17: =SUM(R17:AC17) -> 0 | AE17: =$C$17*$D$17 -> 0 | AF17: =$C$17*$D$17 -> 0 | AG17: =$C$17*$D$17 -> 0 | AH17: =$C$17*$D$17 -> 0 | AI17: =$C$17*$D$17 -> 0 | AJ17: =$C$17*$D$17 -> 0 | AK17: =$C$17*$D$17 -> 0 | AL17: =$C$17*$D$17 -> 0 | ... AP17: =$C$17*$D$17 -> 0 | AQ17: =SUM(AE17:AP17) -> 0 | AR17: =$C$17*$D$17 -> 0 | AS17: =$C$17*$D$17 -> 0 | AT17: =$C$17*$D$17 -> 0 | AU17: =$C$17*$D$17 -> 0 | AV17: =$C$17*$D$17 -> 0 | AW17: =$C$17*$D$17 -> 0 | AX17: =$C$17*$D$17 -> 0 | AY17: =$C$17*$D$17 -> 0 | ... BC17: =$C$17*$D$17 -> 0 | BD17: =SUM(AR17:BC17) -> 0 | BE17: =$C$17*$D$17 -> 0 | BF17: =$C$17*$D$17 -> 0 | BG17: =$C$17*$D$17 -> 0 | BH17: =$C$17*$D$17 -> 0 | BI17: =$C$17*$D$17 -> 0 | BJ17: =$C$17*$D$17 -> 0 | BK17: =$C$17*$D$17 -> 0 | BL17: =$C$17*$D$17 -> 0 | ... BP17: =$C$17*$D$17 -> 0 | BQ17: =SUM(BE17:BP17) -> 0
B18: Salaire Chef de département des installations et équipements de production | Q18: =SUM(E18:P18) -> 0 | R18: =$C$18*$D$18 -> 0 | S18: =$C$18*$D$18 -> 0 | T18: =$C$18*$D$18 -> 0 | U18: =$C$18*$D$18 -> 0 | V18: =$C$18*$D$18 -> 0 | W18: =$C$18*$D$18 -> 0 | X18: =$C$18*$D$18 -> 0 | Y18: =$C$18*$D$18 -> 0 | ... AC18: =$C$18*$D$18 -> 0 | AD18: =SUM(R18:AC18) -> 0 | AE18: =$C$18*$D$18 -> 0 | AF18: =$C$18*$D$18 -> 0 | AG18: =$C$18*$D$18 -> 0 | AH18: =$C$18*$D$18 -> 0 | AI18: =$C$18*$D$18 -> 0 | AJ18: =$C$18*$D$18 -> 0 | AK18: =$C$18*$D$18 -> 0 | AL18: =$C$18*$D$18 -> 0 | ... AP18: =$C$18*$D$18 -> 0 | AQ18: =SUM(AE18:AP18) -> 0 | AR18: =$C$18*$D$18 -> 0 | AS18: =$C$18*$D$18 -> 0 | AT18: =$C$18*$D$18 -> 0 | AU18: =$C$18*$D$18 -> 0 | AV18: =$C$18*$D$18 -> 0 | AW18: =$C$18*$D$18 -> 0 | AX18: =$C$18*$D$18 -> 0 | AY18: =$C$18*$D$18 -> 0 | ... BC18: =$C$18*$D$18 -> 0 | BD18: =SUM(AR18:BC18) -> 0 | BE18: =$C$18*$D$18 -> 0 | BF18: =$C$18*$D$18 -> 0 | BG18: =$C$18*$D$18 -> 0 | BH18: =$C$18*$D$18 -> 0 | BI18: =$C$18*$D$18 -> 0 | BJ18: =$C$18*$D$18 -> 0 | BK18: =$C$18*$D$18 -> 0 | BL18: =$C$18*$D$18 -> 0 | ... BP18: =$C$18*$D$18 -> 0 | BQ18: =SUM(BE18:BP18) -> 0
B19: Salaire service maintenance des installations et de production | Q19: =SUM(E19:P19) -> 0 | R19: =$C$19*$D$19 -> 0 | S19: =$C$19*$D$19 -> 0 | T19: =$C$19*$D$19 -> 0 | U19: =$C$19*$D$19 -> 0 | V19: =$C$19*$D$19 -> 0 | W19: =$C$19*$D$19 -> 0 | X19: =$C$19*$D$19 -> 0 | Y19: =$C$19*$D$19 -> 0 | ... AC19: =$C$19*$D$19 -> 0 | AD19: =SUM(R19:AC19) -> 0 | AE19: =$C$19*$D$19 -> 0 | AF19: =$C$19*$D$19 -> 0 | AG19: =$C$19*$D$19 -> 0 | AH19: =$C$19*$D$19 -> 0 | AI19: =$C$19*$D$19 -> 0 | AJ19: =$C$19*$D$19 -> 0 | AK19: =$C$19*$D$19 -> 0 | AL19: =$C$19*$D$19 -> 0 | ... AP19: =$C$19*$D$19 -> 0 | AQ19: =SUM(AE19:AP19) -> 0 | AR19: =$C$19*$D$19 -> 0 | AS19: =$C$19*$D$19 -> 0 | AT19: =$C$19*$D$19 -> 0 | AU19: =$C$19*$D$19 -> 0 | AV19: =$C$19*$D$19 -> 0 | AW19: =$C$19*$D$19 -> 0 | AX19: =$C$19*$D$19 -> 0 | AY19: =$C$19*$D$19 -> 0 | ... BC19: =$C$19*$D$19 -> 0 | BD19: =SUM(AR19:BC19) -> 0 | BE19: =$C$19*$D$19 -> 0 | BF19: =$C$19*$D$19 -> 0 | BG19: =$C$19*$D$19 -> 0 | BH19: =$C$19*$D$19 -> 0 | BI19: =$C$19*$D$19 -> 0 | BJ19: =$C$19*$D$19 -> 0 | BK19: =$C$19*$D$19 -> 0 | BL19: =$C$19*$D$19 -> 0 | ... BP19: =$C$19*$D$19 -> 0 | BQ19: =SUM(BE19:BP19) -> 0
B20: Salaire service d'exploitation des moyens roulants | Q20: =SUM(E20:P20) -> 0 | R20: =$C$20*$D$20 -> 0 | S20: =$C$20*$D$20 -> 0 | T20: =$C$20*$D$20 -> 0 | U20: =$C$20*$D$20 -> 0 | V20: =$C$20*$D$20 -> 0 | W20: =$C$20*$D$20 -> 0 | X20: =$C$20*$D$20 -> 0 | Y20: =$C$20*$D$20 -> 0 | ... AC20: =$C$20*$D$20 -> 0 | AD20: =SUM(R20:AC20) -> 0 | AE20: =$C$20*$D$20 -> 0 | AF20: =$C$20*$D$20 -> 0 | AG20: =$C$20*$D$20 -> 0 | AH20: =$C$20*$D$20 -> 0 | AI20: =$C$20*$D$20 -> 0 | AJ20: =$C$20*$D$20 -> 0 | AK20: =$C$20*$D$20 -> 0 | AL20: =$C$20*$D$20 -> 0 | ... AP20: =$C$20*$D$20 -> 0 | AQ20: =SUM(AE20:AP20) -> 0 | AR20: =$C$20*$D$20 -> 0 | AS20: =$C$20*$D$20 -> 0 | AT20: =$C$20*$D$20 -> 0 | AU20: =$C$20*$D$20 -> 0 | AV20: =$C$20*$D$20 -> 0 | AW20: =$C$20*$D$20 -> 0 | AX20: =$C$20*$D$20 -> 0 | AY20: =$C$20*$D$20 -> 0 | ... BC20: =$C$20*$D$20 -> 0 | BD20: =SUM(AR20:BC20) -> 0 | BE20: =$C$20*$D$20 -> 0 | BF20: =$C$20*$D$20 -> 0 | BG20: =$C$20*$D$20 -> 0 | BH20: =$C$20*$D$20 -> 0 | BI20: =$C$20*$D$20 -> 0 | BJ20: =$C$20*$D$20 -> 0 | BK20: =$C$20*$D$20 -> 0 | BL20: =$C$20*$D$20 -> 0 | ... BP20: =$C$20*$D$20 -> 0 | BQ20: =SUM(BE20:BP20) -> 0
B21: Salaire service d'exploitation des installations de stockage et de transformation | Q21: =SUM(E21:P21) -> 0 | R21: =$C$21*$D$21 -> 0 | S21: =$C$21*$D$21 -> 0 | T21: =$C$21*$D$21 -> 0 | U21: =$C$21*$D$21 -> 0 | V21: =$C$21*$D$21 -> 0 | W21: =$C$21*$D$21 -> 0 | X21: =$C$21*$D$21 -> 0 | Y21: =$C$21*$D$21 -> 0 | ... AC21: =$C$21*$D$21 -> 0 | AD21: =SUM(R21:AC21) -> 0 | AE21: =$C$21*$D$21 -> 0 | AF21: =$C$21*$D$21 -> 0 | AG21: =$C$21*$D$21 -> 0 | AH21: =$C$21*$D$21 -> 0 | AI21: =$C$21*$D$21 -> 0 | AJ21: =$C$21*$D$21 -> 0 | AK21: =$C$21*$D$21 -> 0 | AL21: =$C$21*$D$21 -> 0 | ... AP21: =$C$21*$D$21 -> 0 | AQ21: =SUM(AE21:AP21) -> 0 | AR21: =$C$21*$D$21 -> 0 | AS21: =$C$21*$D$21 -> 0 | AT21: =$C$21*$D$21 -> 0 | AU21: =$C$21*$D$21 -> 0 | AV21: =$C$21*$D$21 -> 0 | AW21: =$C$21*$D$21 -> 0 | AX21: =$C$21*$D$21 -> 0 | AY21: =$C$21*$D$21 -> 0 | ... BC21: =$C$21*$D$21 -> 0 | BD21: =SUM(AR21:BC21) -> 0 | BE21: =$C$21*$D$21 -> 0 | BF21: =$C$21*$D$21 -> 0 | BG21: =$C$21*$D$21 -> 0 | BH21: =$C$21*$D$21 -> 0 | BI21: =$C$21*$D$21 -> 0 | BJ21: =$C$21*$D$21 -> 0 | BK21: =$C$21*$D$21 -> 0 | BL21: =$C$21*$D$21 -> 0 | ... BP21: =$C$21*$D$21 -> 0 | BQ21: =SUM(BE21:BP21) -> 0
B22: Salaire chef de département de la production | Q22: =SUM(E22:P22) -> 0 | R22: =$C$22*$D$22 -> 0 | S22: =$C$22*$D$22 -> 0 | T22: =$C$22*$D$22 -> 0 | U22: =$C$22*$D$22 -> 0 | V22: =$C$22*$D$22 -> 0 | W22: =$C$22*$D$22 -> 0 | X22: =$C$22*$D$22 -> 0 | Y22: =$C$22*$D$22 -> 0 | ... AC22: =$C$22*$D$22 -> 0 | AD22: =SUM(R22:AC22) -> 0 | AE22: =$C$22*$D$22 -> 0 | AF22: =$C$22*$D$22 -> 0 | AG22: =$C$22*$D$22 -> 0 | AH22: =$C$22*$D$22 -> 0 | AI22: =$C$22*$D$22 -> 0 | AJ22: =$C$22*$D$22 -> 0 | AK22: =$C$22*$D$22 -> 0 | AL22: =$C$22*$D$22 -> 0 | ... AP22: =$C$22*$D$22 -> 0 | AQ22: =SUM(AE22:AP22) -> 0 | AR22: =$C$22*$D$22 -> 0 | AS22: =$C$22*$D$22 -> 0 | AT22: =$C$22*$D$22 -> 0 | AU22: =$C$22*$D$22 -> 0 | AV22: =$C$22*$D$22 -> 0 | AW22: =$C$22*$D$22 -> 0 | AX22: =$C$22*$D$22 -> 0 | AY22: =$C$22*$D$22 -> 0 | ... BC22: =$C$22*$D$22 -> 0 | BD22: =SUM(AR22:BC22) -> 0 | BE22: =$C$22*$D$22 -> 0 | BF22: =$C$22*$D$22 -> 0 | BG22: =$C$22*$D$22 -> 0 | BH22: =$C$22*$D$22 -> 0 | BI22: =$C$22*$D$22 -> 0 | BJ22: =$C$22*$D$22 -> 0 | BK22: =$C$22*$D$22 -> 0 | BL22: =$C$22*$D$22 -> 0 | ... BP22: =$C$22*$D$22 -> 0 | BQ22: =SUM(BE22:BP22) -> 0
B23: Salaire service culture, stockage et transformation du Mais | Q23: =SUM(E23:P23) -> 0 | R23: =$C$23*$D$23 -> 0 | S23: =$C$23*$D$23 -> 0 | T23: =$C$23*$D$23 -> 0 | U23: =$C$23*$D$23 -> 0 | V23: =$C$23*$D$23 -> 0 | W23: =$C$23*$D$23 -> 0 | X23: =$C$23*$D$23 -> 0 | Y23: =$C$23*$D$23 -> 0 | ... AC23: =$C$23*$D$23 -> 0 | AD23: =SUM(R23:AC23) -> 0 | AE23: =$C$23*$D$23 -> 0 | AF23: =$C$23*$D$23 -> 0 | AG23: =$C$23*$D$23 -> 0 | AH23: =$C$23*$D$23 -> 0 | AI23: =$C$23*$D$23 -> 0 | AJ23: =$C$23*$D$23 -> 0 | AK23: =$C$23*$D$23 -> 0 | AL23: =$C$23*$D$23 -> 0 | ... AP23: =$C$23*$D$23 -> 0 | AQ23: =SUM(AE23:AP23) -> 0 | AR23: =$C$23*$D$23 -> 0 | AS23: =$C$23*$D$23 -> 0 | AT23: =$C$23*$D$23 -> 0 | AU23: =$C$23*$D$23 -> 0 | AV23: =$C$23*$D$23 -> 0 | AW23: =$C$23*$D$23 -> 0 | AX23: =$C$23*$D$23 -> 0 | AY23: =$C$23*$D$23 -> 0 | ... BC23: =$C$23*$D$23 -> 0 | BD23: =SUM(AR23:BC23) -> 0 | BE23: =$C$23*$D$23 -> 0 | BF23: =$C$23*$D$23 -> 0 | BG23: =$C$23*$D$23 -> 0 | BH23: =$C$23*$D$23 -> 0 | BI23: =$C$23*$D$23 -> 0 | BJ23: =$C$23*$D$23 -> 0 | BK23: =$C$23*$D$23 -> 0 | BL23: =$C$23*$D$23 -> 0 | ... BP23: =$C$23*$D$23 -> 0 | BQ23: =SUM(BE23:BP23) -> 0
B24: Salaire service culture, stockage et transformation du Soja | Q24: =SUM(E24:P24) -> 0 | R24: =$C$24*$D$24 -> 0 | S24: =$C$24*$D$24 -> 0 | T24: =$C$24*$D$24 -> 0 | U24: =$C$24*$D$24 -> 0 | V24: =$C$24*$D$24 -> 0 | W24: =$C$24*$D$24 -> 0 | X24: =$C$24*$D$24 -> 0 | Y24: =$C$24*$D$24 -> 0 | ... AC24: =$C$24*$D$24 -> 0 | AD24: =SUM(R24:AC24) -> 0 | AE24: =$C$24*$D$24 -> 0 | AF24: =$C$24*$D$24 -> 0 | AG24: =$C$24*$D$24 -> 0 | AH24: =$C$24*$D$24 -> 0 | AI24: =$C$24*$D$24 -> 0 | AJ24: =$C$24*$D$24 -> 0 | AK24: =$C$24*$D$24 -> 0 | AL24: =$C$24*$D$24 -> 0 | ... AP24: =$C$24*$D$24 -> 0 | AQ24: =SUM(AE24:AP24) -> 0 | AR24: =$C$24*$D$24 -> 0 | AS24: =$C$24*$D$24 -> 0 | AT24: =$C$24*$D$24 -> 0 | AU24: =$C$24*$D$24 -> 0 | AV24: =$C$24*$D$24 -> 0 | AW24: =$C$24*$D$24 -> 0 | AX24: =$C$24*$D$24 -> 0 | AY24: =$C$24*$D$24 -> 0 | ... BC24: =$C$24*$D$24 -> 0 | BD24: =SUM(AR24:BC24) -> 0 | BE24: =$C$24*$D$24 -> 0 | BF24: =$C$24*$D$24 -> 0 | BG24: =$C$24*$D$24 -> 0 | BH24: =$C$24*$D$24 -> 0 | BI24: =$C$24*$D$24 -> 0 | BJ24: =$C$24*$D$24 -> 0 | BK24: =$C$24*$D$24 -> 0 | BL24: =$C$24*$D$24 -> 0 | ... BP24: =$C$24*$D$24 -> 0 | BQ24: =SUM(BE24:BP24) -> 0
B25: Salaire service culture, stockage et transformation du Ricin | Q25: =SUM(E25:P25) -> 0 | R25: =$C$25*$D$25 -> 0 | S25: =$C$25*$D$25 -> 0 | T25: =$C$25*$D$25 -> 0 | U25: =$C$25*$D$25 -> 0 | V25: =$C$25*$D$25 -> 0 | W25: =$C$25*$D$25 -> 0 | X25: =$C$25*$D$25 -> 0 | Y25: =$C$25*$D$25 -> 0 | ... AC25: =$C$25*$D$25 -> 0 | AD25: =SUM(R25:AC25) -> 0 | AE25: =$C$25*$D$25 -> 0 | AF25: =$C$25*$D$25 -> 0 | AG25: =$C$25*$D$25 -> 0 | AH25: =$C$25*$D$25 -> 0 | AI25: =$C$25*$D$25 -> 0 | AJ25: =$C$25*$D$25 -> 0 | AK25: =$C$25*$D$25 -> 0 | AL25: =$C$25*$D$25 -> 0 | ... AP25: =$C$25*$D$25 -> 0 | AQ25: =SUM(AE25:AP25) -> 0 | AR25: =$C$25*$D$25 -> 0 | AS25: =$C$25*$D$25 -> 0 | AT25: =$C$25*$D$25 -> 0 | AU25: =$C$25*$D$25 -> 0 | AV25: =$C$25*$D$25 -> 0 | AW25: =$C$25*$D$25 -> 0 | AX25: =$C$25*$D$25 -> 0 | AY25: =$C$25*$D$25 -> 0 | ... BC25: =$C$25*$D$25 -> 0 | BD25: =SUM(AR25:BC25) -> 0 | BE25: =$C$25*$D$25 -> 0 | BF25: =$C$25*$D$25 -> 0 | BG25: =$C$25*$D$25 -> 0 | BH25: =$C$25*$D$25 -> 0 | BI25: =$C$25*$D$25 -> 0 | BJ25: =$C$25*$D$25 -> 0 | BK25: =$C$25*$D$25 -> 0 | BL25: =$C$25*$D$25 -> 0 | ... BP25: =$C$25*$D$25 -> 0 | BQ25: =SUM(BE25:BP25) -> 0
B26: Salaire Chef de division administration, comptabilité et finance | Q26: =SUM(E26:P26) -> 0 | R26: =$C$26*$D$26 -> 0 | S26: =$C$26*$D$26 -> 0 | T26: =$C$26*$D$26 -> 0 | U26: =$C$26*$D$26 -> 0 | V26: =$C$26*$D$26 -> 0 | W26: =$C$26*$D$26 -> 0 | X26: =$C$26*$D$26 -> 0 | Y26: =$C$26*$D$26 -> 0 | ... AC26: =$C$26*$D$26 -> 0 | AD26: =SUM(R26:AC26) -> 0 | AE26: =$C$26*$D$26 -> 0 | AF26: =$C$26*$D$26 -> 0 | AG26: =$C$26*$D$26 -> 0 | AH26: =$C$26*$D$26 -> 0 | AI26: =$C$26*$D$26 -> 0 | AJ26: =$C$26*$D$26 -> 0 | AK26: =$C$26*$D$26 -> 0 | AL26: =$C$26*$D$26 -> 0 | ... AP26: =$C$26*$D$26 -> 0 | AQ26: =SUM(AE26:AP26) -> 0 | AR26: =$C$26*$D$26 -> 0 | AS26: =$C$26*$D$26 -> 0 | AT26: =$C$26*$D$26 -> 0 | AU26: =$C$26*$D$26 -> 0 | AV26: =$C$26*$D$26 -> 0 | AW26: =$C$26*$D$26 -> 0 | AX26: =$C$26*$D$26 -> 0 | AY26: =$C$26*$D$26 -> 0 | ... BC26: =$C$26*$D$26 -> 0 | BD26: =SUM(AR26:BC26) -> 0 | BE26: =$C$26*$D$26 -> 0 | BF26: =$C$26*$D$26 -> 0 | BG26: =$C$26*$D$26 -> 0 | BH26: =$C$26*$D$26 -> 0 | BI26: =$C$26*$D$26 -> 0 | BJ26: =$C$26*$D$26 -> 0 | BK26: =$C$26*$D$26 -> 0 | BL26: =$C$26*$D$26 -> 0 | ... BP26: =$C$26*$D$26 -> 0 | BQ26: =SUM(BE26:BP26) -> 0
B27: Salaire Secrétaire du chef de division | Q27: =SUM(E27:P27) -> 0 | R27: =$C$27*$D$27 -> 0 | S27: =$C$27*$D$27 -> 0 | T27: =$C$27*$D$27 -> 0 | U27: =$C$27*$D$27 -> 0 | V27: =$C$27*$D$27 -> 0 | W27: =$C$27*$D$27 -> 0 | X27: =$C$27*$D$27 -> 0 | Y27: =$C$27*$D$27 -> 0 | ... AC27: =$C$27*$D$27 -> 0 | AD27: =SUM(R27:AC27) -> 0 | AE27: =$C$27*$D$27 -> 0 | AF27: =$C$27*$D$27 -> 0 | AG27: =$C$27*$D$27 -> 0 | AH27: =$C$27*$D$27 -> 0 | AI27: =$C$27*$D$27 -> 0 | AJ27: =$C$27*$D$27 -> 0 | AK27: =$C$27*$D$27 -> 0 | AL27: =$C$27*$D$27 -> 0 | ... AP27: =$C$27*$D$27 -> 0 | AQ27: =SUM(AE27:AP27) -> 0 | AR27: =$C$27*$D$27 -> 0 | AS27: =$C$27*$D$27 -> 0 | AT27: =$C$27*$D$27 -> 0 | AU27: =$C$27*$D$27 -> 0 | AV27: =$C$27*$D$27 -> 0 | AW27: =$C$27*$D$27 -> 0 | AX27: =$C$27*$D$27 -> 0 | AY27: =$C$27*$D$27 -> 0 | ... BC27: =$C$27*$D$27 -> 0 | BD27: =SUM(AR27:BC27) -> 0 | BE27: =$C$27*$D$27 -> 0 | BF27: =$C$27*$D$27 -> 0 | BG27: =$C$27*$D$27 -> 0 | BH27: =$C$27*$D$27 -> 0 | BI27: =$C$27*$D$27 -> 0 | BJ27: =$C$27*$D$27 -> 0 | BK27: =$C$27*$D$27 -> 0 | BL27: =$C$27*$D$27 -> 0 | ... BP27: =$C$27*$D$27 -> 0 | BQ27: =SUM(BE27:BP27) -> 0
B28: Salaire chef de département administration et affaires juridiques | Q28: =SUM(E28:P28) -> 0 | R28: =$C$28*$D$28 -> 0 | S28: =$C$28*$D$28 -> 0 | T28: =$C$28*$D$28 -> 0 | U28: =$C$28*$D$28 -> 0 | V28: =$C$28*$D$28 -> 0 | W28: =$C$28*$D$28 -> 0 | X28: =$C$28*$D$28 -> 0 | Y28: =$C$28*$D$28 -> 0 | ... AC28: =$C$28*$D$28 -> 0 | AD28: =SUM(R28:AC28) -> 0 | AE28: =$C$28*$D$28 -> 0 | AF28: =$C$28*$D$28 -> 0 | AG28: =$C$28*$D$28 -> 0 | AH28: =$C$28*$D$28 -> 0 | AI28: =$C$28*$D$28 -> 0 | AJ28: =$C$28*$D$28 -> 0 | AK28: =$C$28*$D$28 -> 0 | AL28: =$C$28*$D$28 -> 0 | ... AP28: =$C$28*$D$28 -> 0 | AQ28: =SUM(AE28:AP28) -> 0 | AR28: =$C$28*$D$28 -> 0 | AS28: =$C$28*$D$28 -> 0 | AT28: =$C$28*$D$28 -> 0 | AU28: =$C$28*$D$28 -> 0 | AV28: =$C$28*$D$28 -> 0 | AW28: =$C$28*$D$28 -> 0 | AX28: =$C$28*$D$28 -> 0 | AY28: =$C$28*$D$28 -> 0 | ... BC28: =$C$28*$D$28 -> 0 | BD28: =SUM(AR28:BC28) -> 0 | BE28: =$C$28*$D$28 -> 0 | BF28: =$C$28*$D$28 -> 0 | BG28: =$C$28*$D$28 -> 0 | BH28: =$C$28*$D$28 -> 0 | BI28: =$C$28*$D$28 -> 0 | BJ28: =$C$28*$D$28 -> 0 | BK28: =$C$28*$D$28 -> 0 | BL28: =$C$28*$D$28 -> 0 | ... BP28: =$C$28*$D$28 -> 0 | BQ28: =SUM(BE28:BP28) -> 0
B29: Salaire service administration | Q29: =SUM(E29:P29) -> 0 | R29: =$C$29*$D$29 -> 0 | S29: =$C$29*$D$29 -> 0 | T29: =$C$29*$D$29 -> 0 | U29: =$C$29*$D$29 -> 0 | V29: =$C$29*$D$29 -> 0 | W29: =$C$29*$D$29 -> 0 | X29: =$C$29*$D$29 -> 0 | Y29: =$C$29*$D$29 -> 0 | ... AC29: =$C$29*$D$29 -> 0 | AD29: =SUM(R29:AC29) -> 0 | AE29: =$C$29*$D$29 -> 0 | AF29: =$C$29*$D$29 -> 0 | AG29: =$C$29*$D$29 -> 0 | AH29: =$C$29*$D$29 -> 0 | AI29: =$C$29*$D$29 -> 0 | AJ29: =$C$29*$D$29 -> 0 | AK29: =$C$29*$D$29 -> 0 | AL29: =$C$29*$D$29 -> 0 | ... AP29: =$C$29*$D$29 -> 0 | AQ29: =SUM(AE29:AP29) -> 0 | AR29: =$C$29*$D$29 -> 0 | AS29: =$C$29*$D$29 -> 0 | AT29: =$C$29*$D$29 -> 0 | AU29: =$C$29*$D$29 -> 0 | AV29: =$C$29*$D$29 -> 0 | AW29: =$C$29*$D$29 -> 0 | AX29: =$C$29*$D$29 -> 0 | AY29: =$C$29*$D$29 -> 0 | ... BC29: =$C$29*$D$29 -> 0 | BD29: =SUM(AR29:BC29) -> 0 | BE29: =$C$29*$D$29 -> 0 | BF29: =$C$29*$D$29 -> 0 | BG29: =$C$29*$D$29 -> 0 | BH29: =$C$29*$D$29 -> 0 | BI29: =$C$29*$D$29 -> 0 | BJ29: =$C$29*$D$29 -> 0 | BK29: =$C$29*$D$29 -> 0 | BL29: =$C$29*$D$29 -> 0 | ... BP29: =$C$29*$D$29 -> 0 | BQ29: =SUM(BE29:BP29) -> 0
B30: Salaire service affaires juridiques | Q30: =SUM(E30:P30) -> 0 | R30: =$C$30*$D$30 -> 0 | S30: =$C$30*$D$30 -> 0 | T30: =$C$30*$D$30 -> 0 | U30: =$C$30*$D$30 -> 0 | V30: =$C$30*$D$30 -> 0 | W30: =$C$30*$D$30 -> 0 | X30: =$C$30*$D$30 -> 0 | Y30: =$C$30*$D$30 -> 0 | ... AC30: =$C$30*$D$30 -> 0 | AD30: =SUM(R30:AC30) -> 0 | AE30: =$C$30*$D$30 -> 0 | AF30: =$C$30*$D$30 -> 0 | AG30: =$C$30*$D$30 -> 0 | AH30: =$C$30*$D$30 -> 0 | AI30: =$C$30*$D$30 -> 0 | AJ30: =$C$30*$D$30 -> 0 | AK30: =$C$30*$D$30 -> 0 | AL30: =$C$30*$D$30 -> 0 | ... AP30: =$C$30*$D$30 -> 0 | AQ30: =SUM(AE30:AP30) -> 0 | AR30: =$C$30*$D$30 -> 0 | AS30: =$C$30*$D$30 -> 0 | AT30: =$C$30*$D$30 -> 0 | AU30: =$C$30*$D$30 -> 0 | AV30: =$C$30*$D$30 -> 0 | AW30: =$C$30*$D$30 -> 0 | AX30: =$C$30*$D$30 -> 0 | AY30: =$C$30*$D$30 -> 0 | ... BC30: =$C$30*$D$30 -> 0 | BD30: =SUM(AR30:BC30) -> 0 | BE30: =$C$30*$D$30 -> 0 | BF30: =$C$30*$D$30 -> 0 | BG30: =$C$30*$D$30 -> 0 | BH30: =$C$30*$D$30 -> 0 | BI30: =$C$30*$D$30 -> 0 | BJ30: =$C$30*$D$30 -> 0 | BK30: =$C$30*$D$30 -> 0 | BL30: =$C$30*$D$30 -> 0 | ... BP30: =$C$30*$D$30 -> 0 | BQ30: =SUM(BE30:BP30) -> 0
B31: Chef de département Comptabilité et Finances | Q31: =SUM(E31:P31) -> 0 | R31: =$C$31*$D$31 -> 0 | S31: =$C$31*$D$31 -> 0 | T31: =$C$31*$D$31 -> 0 | U31: =$C$31*$D$31 -> 0 | V31: =$C$31*$D$31 -> 0 | W31: =$C$31*$D$31 -> 0 | X31: =$C$31*$D$31 -> 0 | Y31: =$C$31*$D$31 -> 0 | ... AC31: =$C$31*$D$31 -> 0 | AD31: =SUM(R31:AC31) -> 0 | AE31: =$C$31*$D$31 -> 0 | AF31: =$C$31*$D$31 -> 0 | AG31: =$C$31*$D$31 -> 0 | AH31: =$C$31*$D$31 -> 0 | AI31: =$C$31*$D$31 -> 0 | AJ31: =$C$31*$D$31 -> 0 | AK31: =$C$31*$D$31 -> 0 | AL31: =$C$31*$D$31 -> 0 | ... AP31: =$C$31*$D$31 -> 0 | AQ31: =SUM(AE31:AP31) -> 0 | AR31: =$C$31*$D$31 -> 0 | AS31: =$C$31*$D$31 -> 0 | AT31: =$C$31*$D$31 -> 0 | AU31: =$C$31*$D$31 -> 0 | AV31: =$C$31*$D$31 -> 0 | AW31: =$C$31*$D$31 -> 0 | AX31: =$C$31*$D$31 -> 0 | AY31: =$C$31*$D$31 -> 0 | ... BC31: =$C$31*$D$31 -> 0 | BD31: =SUM(AR31:BC31) -> 0 | BE31: =$C$31*$D$31 -> 0 | BF31: =$C$31*$D$31 -> 0 | BG31: =$C$31*$D$31 -> 0 | BH31: =$C$31*$D$31 -> 0 | BI31: =$C$31*$D$31 -> 0 | BJ31: =$C$31*$D$31 -> 0 | BK31: =$C$31*$D$31 -> 0 | BL31: =$C$31*$D$31 -> 0 | ... BP31: =$C$31*$D$31 -> 0 | BQ31: =SUM(BE31:BP31) -> 0
B32: Salaire service comptabilité | Q32: =SUM(E32:P32) -> 0 | R32: =$C$32*$D$32 -> 0 | S32: =$C$32*$D$32 -> 0 | T32: =$C$32*$D$32 -> 0 | U32: =$C$32*$D$32 -> 0 | V32: =$C$32*$D$32 -> 0 | W32: =$C$32*$D$32 -> 0 | X32: =$C$32*$D$32 -> 0 | Y32: =$C$32*$D$32 -> 0 | ... AC32: =$C$32*$D$32 -> 0 | AD32: =SUM(R32:AC32) -> 0 | AE32: =$C$32*$D$32 -> 0 | AF32: =$C$32*$D$32 -> 0 | AG32: =$C$32*$D$32 -> 0 | AH32: =$C$32*$D$32 -> 0 | AI32: =$C$32*$D$32 -> 0 | AJ32: =$C$32*$D$32 -> 0 | AK32: =$C$32*$D$32 -> 0 | AL32: =$C$32*$D$32 -> 0 | ... AP32: =$C$32*$D$32 -> 0 | AQ32: =SUM(AE32:AP32) -> 0 | AR32: =$C$32*$D$32 -> 0 | AS32: =$C$32*$D$32 -> 0 | AT32: =$C$32*$D$32 -> 0 | AU32: =$C$32*$D$32 -> 0 | AV32: =$C$32*$D$32 -> 0 | AW32: =$C$32*$D$32 -> 0 | AX32: =$C$32*$D$32 -> 0 | AY32: =$C$32*$D$32 -> 0 | ... BC32: =$C$32*$D$32 -> 0 | BD32: =SUM(AR32:BC32) -> 0 | BE32: =$C$32*$D$32 -> 0 | BF32: =$C$32*$D$32 -> 0 | BG32: =$C$32*$D$32 -> 0 | BH32: =$C$32*$D$32 -> 0 | BI32: =$C$32*$D$32 -> 0 | BJ32: =$C$32*$D$32 -> 0 | BK32: =$C$32*$D$32 -> 0 | BL32: =$C$32*$D$32 -> 0 | ... BP32: =$C$32*$D$32 -> 0 | BQ32: =SUM(BE32:BP32) -> 0
B33: Salaire service des finances | Q33: =SUM(E33:P33) -> 0 | R33: =$C$33*$D$33 -> 0 | S33: =$C$33*$D$33 -> 0 | T33: =$C$33*$D$33 -> 0 | U33: =$C$33*$D$33 -> 0 | V33: =$C$33*$D$33 -> 0 | W33: =$C$33*$D$33 -> 0 | X33: =$C$33*$D$33 -> 0 | Y33: =$C$33*$D$33 -> 0 | ... AC33: =$C$33*$D$33 -> 0 | AD33: =SUM(R33:AC33) -> 0 | AE33: =$C$33*$D$33 -> 0 | AF33: =$C$33*$D$33 -> 0 | AG33: =$C$33*$D$33 -> 0 | AH33: =$C$33*$D$33 -> 0 | AI33: =$C$33*$D$33 -> 0 | AJ33: =$C$33*$D$33 -> 0 | AK33: =$C$33*$D$33 -> 0 | AL33: =$C$33*$D$33 -> 0 | ... AP33: =$C$33*$D$33 -> 0 | AQ33: =SUM(AE33:AP33) -> 0 | AR33: =$C$33*$D$33 -> 0 | AS33: =$C$33*$D$33 -> 0 | AT33: =$C$33*$D$33 -> 0 | AU33: =$C$33*$D$33 -> 0 | AV33: =$C$33*$D$33 -> 0 | AW33: =$C$33*$D$33 -> 0 | AX33: =$C$33*$D$33 -> 0 | AY33: =$C$33*$D$33 -> 0 | ... BC33: =$C$33*$D$33 -> 0 | BD33: =SUM(AR33:BC33) -> 0 | BE33: =$C$33*$D$33 -> 0 | BF33: =$C$33*$D$33 -> 0 | BG33: =$C$33*$D$33 -> 0 | BH33: =$C$33*$D$33 -> 0 | BI33: =$C$33*$D$33 -> 0 | BJ33: =$C$33*$D$33 -> 0 | BK33: =$C$33*$D$33 -> 0 | BL33: =$C$33*$D$33 -> 0 | ... BP33: =$C$33*$D$33 -> 0 | BQ33: =SUM(BE33:BP33) -> 0
B34: Mission d'assistance de la direction générale par OBAC CAPITAL | Q34: =SUM(E34:P34) -> 0 | R34: =$C$34*$D$34 -> 0 | S34: =$C$34*$D$34 -> 0 | T34: =$C$34*$D$34 -> 0 | U34: =$C$34*$D$34 -> 0 | V34: =$C$34*$D$34 -> 0 | W34: =$C$34*$D$34 -> 0 | X34: =$C$34*$D$34 -> 0 | Y34: =$C$34*$D$34 -> 0 | ... AC34: =$C$34*$D$34 -> 0 | AD34: =SUM(R34:AC34) -> 0 | AE34: =$C$34*$D$34 -> 0 | AF34: =$C$34*$D$34 -> 0 | AG34: =$C$34*$D$34 -> 0 | AH34: =$C$34*$D$34 -> 0 | AI34: =$C$34*$D$34 -> 0 | AJ34: =$C$34*$D$34 -> 0 | AK34: =$C$34*$D$34 -> 0 | AL34: =$C$34*$D$34 -> 0 | ... AP34: =$C$34*$D$34 -> 0 | AQ34: =SUM(AE34:AP34) -> 0 | AR34: =$C$34*$D$34 -> 0 | AS34: =$C$34*$D$34 -> 0 | AT34: =$C$34*$D$34 -> 0 | AU34: =$C$34*$D$34 -> 0 | AV34: =$C$34*$D$34 -> 0 | AW34: =$C$34*$D$34 -> 0 | AX34: =$C$34*$D$34 -> 0 | AY34: =$C$34*$D$34 -> 0 | ... BC34: =$C$34*$D$34 -> 0 | BD34: =SUM(AR34:BC34) -> 0 | BE34: =$C$34*$D$34 -> 0 | BF34: =$C$34*$D$34 -> 0 | BG34: =$C$34*$D$34 -> 0 | BH34: =$C$34*$D$34 -> 0 | BI34: =$C$34*$D$34 -> 0 | BJ34: =$C$34*$D$34 -> 0 | BK34: =$C$34*$D$34 -> 0 | BL34: =$C$34*$D$34 -> 0 | ... BP34: =$C$34*$D$34 -> 0 | BQ34: =SUM(BE34:BP34) -> 0
Q35: =SUM(E35:P35) -> 0 | AD35: =SUM(R35:AC35) -> 0 | AQ35: =SUM(AE35:AP35) -> 0 | BD35: =SUM(AR35:BC35) -> 0 | BQ35: =SUM(BE35:BP35) -> 0
Q36: =SUM(E36:P36) -> 0 | AD36: =SUM(R36:AC36) -> 0 | AQ36: =SUM(AE36:AP36) -> 0 | BD36: =SUM(AR36:BC36) -> 0 | BQ36: =SUM(BE36:BP36) -> 0
Q37: =SUM(E37:P37) -> 0 | AD37: =SUM(R37:AC37) -> 0 | AQ37: =SUM(AE37:AP37) -> 0 | BD37: =SUM(AR37:BC37) -> 0 | BQ37: =SUM(BE37:BP37) -> 0
Q38: =SUM(E38:P38) -> 0 | AD38: =SUM(R38:AC38) -> 0 | AQ38: =SUM(AE38:AP38) -> 0 | BD38: =SUM(AR38:BC38) -> 0 | BQ38: =SUM(BE38:BP38) -> 0
Q39: =SUM(E39:P39) -> 0 | AD39: =SUM(R39:AC39) -> 0 | AQ39: =SUM(AE39:AP39) -> 0 | BD39: =SUM(AR39:BC39) -> 0 | BQ39: =SUM(BE39:BP39) -> 0
Q40: =SUM(E40:P40) -> 0 | AD40: =SUM(R40:AC40) -> 0 | AQ40: =SUM(AE40:AP40) -> 0 | BD40: =SUM(AR40:BC40) -> 0 | BQ40: =SUM(BE40:BP40) -> 0
Q41: =SUM(E41:P41) -> 0 | AD41: =SUM(R41:AC41) -> 0 | AQ41: =SUM(AE41:AP41) -> 0 | BD41: =SUM(AR41:BC41) -> 0 | BQ41: =SUM(BE41:BP41) -> 0
Q42: =SUM(E42:P42) -> 0 | AD42: =SUM(R42:AC42) -> 0 | AQ42: =SUM(AE42:AP42) -> 0 | BD42: =SUM(AR42:BC42) -> 0 | BQ42: =SUM(BE42:BP42) -> 0
Q43: =SUM(E43:P43) -> 0 | AD43: =SUM(R43:AC43) -> 0 | AQ43: =SUM(AE43:AP43) -> 0 | BD43: =SUM(AR43:BC43) -> 0 | BQ43: =SUM(BE43:BP43) -> 0
Q44: =SUM(E44:P44) -> 0 | AD44: =SUM(R44:AC44) -> 0 | AQ44: =SUM(AE44:AP44) -> 0 | BD44: =SUM(AR44:BC44) -> 0 | BQ44: =SUM(BE44:BP44) -> 0
Q45: =SUM(E45:P45) -> 0 | AD45: =SUM(R45:AC45) -> 0 | AQ45: =SUM(AE45:AP45) -> 0 | BD45: =SUM(AR45:BC45) -> 0 | BQ45: =SUM(BE45:BP45) -> 0
Q46: =SUM(E46:P46) -> 0 | AD46: =SUM(R46:AC46) -> 0 | AQ46: =SUM(AE46:AP46) -> 0 | BD46: =SUM(AR46:BC46) -> 0 | BQ46: =SUM(BE46:BP46) -> 0
... Q64: =SUM(E64:P64) -> 0 | AD64: =SUM(R64:AC64) -> 0 | AQ64: =SUM(AE64:AP64) -> 0 | BD64: =SUM(AR64:BC64) -> 0 | BQ64: =SUM(BE64:BP64) -> 0
E65: =$C$65*$D$65 -> 0 | Q65: =SUM(E65:P65) -> 0 | AD65: =SUM(R65:AC65) -> 0 | AQ65: =SUM(AE65:AP65) -> 0 | BD65: =SUM(AR65:BC65) -> 0 | BQ65: =SUM(BE65:BP65) -> 0
E66: =$C$66*$D$66 -> 0 | Q66: =SUM(E66:P66) -> 0 | AD66: =SUM(R66:AC66) -> 0 | AQ66: =SUM(AE66:AP66) -> 0 | BD66: =SUM(AR66:BC66) -> 0 | BQ66: =SUM(BE66:BP66) -> 0
E67: =C67*D67 -> 0 | Q67: =SUM(E67:P67) -> 0 | AD67: =SUM(R67:AC67) -> 0 | AQ67: =SUM(AE67:AP67) -> 0 | BD67: =SUM(AR67:BC67) -> 0 | BQ67: =SUM(BE67:BP67) -> 0
E68: =C68*D68 -> 0 | Q68: =SUM(E68:P68) -> 0 | AD68: =SUM(R68:AC68) -> 0 | AQ68: =SUM(AE68:AP68) -> 0 | BD68: =SUM(AR68:BC68) -> 0 | BQ68: =SUM(BE68:BP68) -> 0
E69: =C69*D69 -> 0 | Q69: =SUM(E69:P69) -> 0 | AD69: =SUM(R69:AC69) -> 0 | AQ69: =SUM(AE69:AP69) -> 0 | BD69: =SUM(AR69:BC69) -> 0 | BQ69: =SUM(BE69:BP69) -> 0
E70: =C70*D70 -> 0 | Q70: =SUM(E70:P70) -> 0 | AD70: =SUM(R70:AC70) -> 0 | AQ70: =SUM(AE70:AP70) -> 0 | BD70: =SUM(AR70:BC70) -> 0 | BQ70: =SUM(BE70:BP70) -> 0
E71: =C71*D71 -> 0 | Q71: =SUM(E71:P71) -> 0 | AD71: =SUM(R71:AC71) -> 0 | AQ71: =SUM(AE71:AP71) -> 0 | BD71: =SUM(AR71:BC71) -> 0 | BQ71: =SUM(BE71:BP71) -> 0
E72: =C72*D72 -> 0 | Q72: =SUM(E72:P72) -> 0 | AD72: =SUM(R72:AC72) -> 0 | AQ72: =SUM(AE72:AP72) -> 0 | BD72: =SUM(AR72:BC72) -> 0 | BQ72: =SUM(BE72:BP72) -> 0
E73: =C73*D73 -> 0 | Q73: =SUM(E73:P73) -> 0 | AD73: =SUM(R73:AC73) -> 0 | AQ73: =SUM(AE73:AP73) -> 0 | BD73: =SUM(AR73:BC73) -> 0 | BQ73: =SUM(BE73:BP73) -> 0
E74: =C74*D74 -> 0 | Q74: =SUM(E74:P74) -> 0 | AD74: =SUM(R74:AC74) -> 0 | AQ74: =SUM(AE74:AP74) -> 0 | BD74: =SUM(AR74:BC74) -> 0 | BQ74: =SUM(BE74:BP74) -> 0
E75: =C75*D75 -> 0 | Q75: =SUM(E75:P75) -> 0 | AD75: =SUM(R75:AC75) -> 0 | AQ75: =SUM(AE75:AP75) -> 0 | BD75: =SUM(AR75:BC75) -> 0 | BQ75: =SUM(BE75:BP75) -> 0
E76: =C76*D76 -> 0 | Q76: =SUM(E76:P76) -> 0 | AD76: =SUM(R76:AC76) -> 0 | AQ76: =SUM(AE76:AP76) -> 0 | BD76: =SUM(AR76:BC76) -> 0 | BQ76: =SUM(BE76:BP76) -> 0
E77: =C77*D77 -> 0 | Q77: =SUM(E77:P77) -> 0 | AD77: =SUM(R77:AC77) -> 0 | AQ77: =SUM(AE77:AP77) -> 0 | BD77: =SUM(AR77:BC77) -> 0 | BQ77: =SUM(BE77:BP77) -> 0
E78: =C78*D78 -> 0 | Q78: =SUM(E78:P78) -> 0 | AD78: =SUM(R78:AC78) -> 0 | AQ78: =SUM(AE78:AP78) -> 0 | BD78: =SUM(AR78:BC78) -> 0 | BQ78: =SUM(BE78:BP78) -> 0
... E157: =C157*D157 -> 0 | Q157: =SUM(E157:P157) -> 0 | AD157: =SUM(R157:AC157) -> 0 | AQ157: =SUM(AE157:AP157) -> 0 | BD157: =SUM(AR157:BC157) -> 0 | BQ157: =SUM(BE157:BP157) -> 0

Sheet Charges fixes
B1: Mois 1 | C1: Mois 2 | D1: Mois 3 | E1: Mois 4 | F1: Mois 5 | G1: Mois 6 | H1: Mois 7 | I1: Mois 8 | J1: Mois 9 | K1: Mois 10 | L1: Mois 11 | M1: Mois 12 | N1: Année 1 | O1: Mois 13 | P1: Mois 14 | Q1: Mois 15 | R1: Mois 16 | S1: Mois 17 | T1: Mois 18 | U1: Mois 19 | V1: Mois 20 | W1: Mois 21 | X1: Mois 22 | Y1: Mois 23 | Z1: Mois 24 | AA1: Année 2 | AB1: Mois 25 | AC1: Mois 26 | AD1: Mois 27 | AE1: Mois 28 | AF1: Mois 29 | AG1: Mois 30 | AH1: Mois 31 | AI1: Mois 32 | AJ1: Mois 33 | AK1: Mois 34 | AL1: Mois 35 | AM1: Mois 36 | AN1: Année 3 | AO1: Mois 37 | AP1: Mois 38 | AQ1: Mois 39 | AR1: Mois 40 | AS1: Mois 41 | AT1: Mois 42 | AU1: Mois 43 | AV1: Mois 44 | AW1: Mois 45 | AX1: Mois 46 | AY1: Mois 47 | AZ1: Mois 48 | BA1: Année 4 | BB1: Mois 49 | BC1: Mois 50 | BD1: Mois 51 | BE1: Mois 52 | BF1: Mois 53 | BG1: Mois 54 | BH1: Mois 55 | BI1: Mois 56 | BJ1: Mois 57 | BK1: Mois 58 | BL1: Mois 59 | BM1: Mois 60 | BN1: Année 5
A2: Locations et charges locatives | B2: 250000 | C2: 250000 | D2: 250000 | E2: 250000 | F2: 250000 | G2: 250000 | H2: 250000 | I2: 250000 | J2: 250000 | K2: 250000 | L2: 250000 | M2: 250000 | N2: =SUM(B2:M2) -> 3000000 | O2: 250000 | P2: 250000 | Q2: 250000 | R2: 250000 | S2: 250000 | T2: 250000 | U2: 250000 | V2: 250000 | W2: 250000 | X2: 250000 | Y2: 250000 | Z2: 250000 | AA2: =SUM(O2:Z2) -> 3000000 | AB2: 250000 | AC2: 250000 | AD2: 250000 | AE2: 250000 | AF2: 250000 | AG2: 250000 | AH2: 250000 | AI2: 250000 | AJ2: 250000 | AK2: 250000 | AL2: 250000 | AM2: 250000 | AN2: =SUM(AB2:AM2) -> 3000000 | BA2: =SUM(AO2:AZ2) -> 0 | BN2: =SUM(BB2:BM2) -> 0
A3: Redevances de crédit bail et contrats assimilés | N3: =SUM(B3:M3) -> 0 | AA3: =SUM(O3:Z3) -> 0 | AN3: =SUM(AB3:AM3) -> 0 | BA3: =SUM(AO3:AZ3) -> 0 | BN3: =SUM(BB3:BM3) -> 0
A4: Entretien, Réparation et Maintenance | D4: 150000 | G4: 150000 | J4: 150000 | M4: 150000 | N4: =SUM(B4:M4) -> 600000 | Q4: 150000 | T4: 150000 | W4: 150000 | Z4: 150000 | AA4: =SUM(O4:Z4) -> 600000 | AD4: 150000 | AG4: 150000 | AJ4: 150000 | AM4: 150000 | AN4: =SUM(AB4:AM4) -> 600000 | BA4: =SUM(AO4:AZ4) -> 0 | BN4: =SUM(BB4:BM4) -> 0
A5: Prime d'assurances | B5: 350000 | N5: =SUM(B5:M5) -> 350000 | O5: 350000 | AA5: =SUM(O5:Z5) -> 350000 | AB5: 350000 | AN5: =SUM(AB5:AM5) -> 350000 | BA5: =SUM(AO5:AZ5) -> 0 | BN5: =SUM(BB5:BM5) -> 0
A6: Etudes, recherche et documentation | N6: =SUM(B6:M6) -> 0 | AA6: =SUM(O6:Z6) -> 0 | AN6: =SUM(AB6:AM6) -> 0 | BA6: =SUM(AO6:AZ6) -> 0 | BN6: =SUM(BB6:BM6) -> 0
A7: Cotisations | N7: =SUM(B7:M7) -> 0 | AA7: =SUM(O7:Z7) -> 0 | AN7: =SUM(AB7:AM7) -> 0 | BA7: =SUM(AO7:AZ7) -> 0 | BN7: =SUM(BB7:BM7) -> 0
A8: Impots fonciers et taxes annexes | N8: =SUM(B8:M8) -> 0 | AA8: =SUM(O8:Z8) -> 0 | AN8: =SUM(AB8:AM8) -> 0 | BA8: =SUM(AO8:AZ8) -> 0 | BN8: =SUM(BB8:BM8) -> 0
A9: Patentes, licences et taxes annexes | N9: ='Impots et taxes'!E17 -> 36981.25 | AA9: ='Impots et taxes'!H17 -> 28859.853 | AN9: ='Impots et taxes'!K17 -> 54832.975 | BA9: ='Impots et taxes'!N17 -> 362753.04 | BN9: ='Impots et taxes'!Q17 -> 1260924.5
A10: Taxes sur appointements et salaires | N10: =N15*'Impots et taxes'!$B$42 -> 450000 | AA10: =AA15*'Impots et taxes'!$B$42 -> 450000 | AN10: =AN15*'Impots et taxes'!$B$42 -> 450000 | BA10: =BA15*'Impots et taxes'!$B$42 -> 0 | BN10: =BN15*'Impots et taxes'!$B$42 -> 0
A11: Taxes d'apprentissage | N11: =SUM(B11:M11) -> 0 | AA11: =SUM(O11:Z11) -> 0 | AN11: =SUM(AB11:AM11) -> 0 | BA11: =SUM(AO11:AZ11) -> 0 | BN11: =SUM(BB11:BM11) -> 0
A12: Formation professionnelle continue | N12: =SUM(B12:M12) -> 0 | AA12: =SUM(O12:Z12) -> 0 | AN12: =SUM(AB12:AM12) -> 0 | BA12: =SUM(AO12:AZ12) -> 0 | BN12: =SUM(BB12:BM12) -> 0
A13: Autres impôts et taxes directs | N13: ='Impots et taxes'!$B$37 -> 120000 | AA13: ='Impots et taxes'!$B$37 -> 120000 | AN13: ='Impots et taxes'!$B$37 -> 120000 | BA13: ='Impots et taxes'!$B$37 -> 120000 | BN13: ='Impots et taxes'!$B$37 -> 120000
A14: Droits d'enregistrements | N14: =SUM('Impots et taxes'!D29:D32) -> 0 | AA14: =SUM('Impots et taxes'!F29:F32) -> 0 | AN14: =SUM('Impots et taxes'!H29:H32) -> 0 | BA14: =SUM('Impots et taxes'!J29:J32) -> 0 | BN14: =SUM('Impots et taxes'!L29:L32) -> 0
A15: Rémunérations versées au personnel | B15: 500000 | C15: 500000 | D15: 500000 | E15: 500000 | F15: 500000 | G15: 500000 | H15: 500000 | I15: 500000 | J15: 500000 | K15: 500000 | L15: 500000 | M15: 500000 | N15: =SUM(B15:M15) -> 6000000 | O15: 500000 | P15: 500000 | Q15: 500000 | R15: 500000 | S15: 500000 | T15: 500000 | U15: 500000 | V15: 500000 | W15: 500000 | X15: 500000 | Y15: 500000 | Z15: 500000 | AA15: =SUM(O15:Z15) -> 6000000 | AB15: 500000 | AC15: 500000 | AD15: 500000 | AE15: 500000 | AF15: 500000 | AG15: 500000 | AH15: 500000 | AI15: 500000 | AJ15: 500000 | AK15: 500000 | AL15: 500000 | AM15: 500000 | AN15: =SUM(AB15:AM15) -> 6000000 | BA15: =SUM(AO15:AZ15) -> 0 | BN15: =SUM(BB15:BM15) -> 0
A16: Indemnité forfaitaire versée au personnel | N16: =SUM(B16:M16) -> 0 | AA16: =SUM(O16:Z16) -> 0 | AN16: =SUM(AB16:AM16) -> 0 | BA16: =SUM(AO16:AZ16) -> 0 | BN16: =SUM(BB16:BM16) -> 0
A17: Charges sociales | B17: =33.6%*B15 -> 168000 | C17: =33.6%*C15 -> 168000 | D17: =33.6%*D15 -> 168000 | E17: =33.6%*E15 -> 168000 | F17: =33.6%*F15 -> 168000 | G17: =33.6%*G15 -> 168000 | H17: =33.6%*H15 -> 168000 | I17: =33.6%*I15 -> 168000 | ... BN17: =33.6%*BN15 -> 0
A18: Intérêts sur emprunt | B18: =$N$18/12 -> 0 | C18: =$N$18/12 -> 0 | D18: =$N$18/12 -> 0 | E18: =$N$18/12 -> 0 | F18: =$N$18/12 -> 0 | G18: =$N$18/12 -> 0 | H18: =$N$18/12 -> 0 | I18: =$N$18/12 -> 0 | ... M18: =$N$18/12 -> 0 | N18: ='Calculs financiers'!D16+'Calculs financiers'!D34 -> 0 | O18: =$AA$18/12 -> 0 | P18: =$AA$18/12 -> 0 | Q18: =$AA$18/12 -> 0 | R18: =$AA$18/12 -> 0 | S18: =$AA$18/12 -> 0 | T18: =$AA$18/12 -> 0 | U18: =$AA$18/12 -> 0 | V18: =$AA$18/12 -> 0 | ... Z18: =$AA$18/12 -> 0 | AA18: ='Calculs financiers'!D17+'Calculs financiers'!D35 -> 0 | AB18: =$AN$18/12 -> 0 | AC18: =$AN$18/12 -> 0 | AD18: =$AN$18/12 -> 0 | AE18: =$AN$18/12 -> 0 | AF18: =$AN$18/12 -> 0 | AG18: =$AN$18/12 -> 0 | AH18: =$AN$18/12 -> 0 | AI18: =$AN$18/12 -> 0 | ... AM18: =$AN$18/12 -> 0 | AN18: ='Calculs financiers'!D18+'Calculs financiers'!D36 -> 0 | AO18: =$BA$18/12 -> 0 | AP18: =$BA$18/12 -> 0 | AQ18: =$BA$18/12 -> 0 | AR18: =$BA$18/12 -> 0 | AS18: =$BA$18/12 -> 0 | AT18: =$BA$18/12 -> 0 | AU18: =$BA$18/12 -> 0 | AV18: =$BA$18/12 -> 0 | ... AZ18: =$BA$18/12 -> 0 | BA18: ='Calculs financiers'!D19+'Calculs financiers'!D37 -> 0 | BB18: =$BN$18/12 -> 0 | BC18: =$BN$18/12 -> 0 | BD18: =$BN$18/12 -> 0 | BE18: =$BN$18/12 -> 0 | BF18: =$BN$18/12 -> 0 | BG18: =$BN$18/12 -> 0 | BH18: =$BN$18/12 -> 0 | BI18: =$BN$18/12 -> 0 | ... BM18: =$BN$18/12 -> 0 | BN18: ='Calculs financiers'!D20+'Calculs financiers'!D38 -> 0
A19: Intérêt dans loyer de crédit bail | B19: =$N$19/12 -> 0 | C19: =$N$19/12 -> 0 | D19: =$N$19/12 -> 0 | E19: =$N$19/12 -> 0 | F19: =$N$19/12 -> 0 | G19: =$N$19/12 -> 0 | H19: =$N$19/12 -> 0 | I19: =$N$19/12 -> 0 | ... M19: =$N$19/12 -> 0 | N19: ='Calculs financiers'!D60 -> 0 | O19: =$AA$19/12 -> 0 | P19: =$AA$19/12 -> 0 | Q19: =$AA$19/12 -> 0 | R19: =$AA$19/12 -> 0 | S19: =$AA$19/12 -> 0 | T19: =$AA$19/12 -> 0 | U19: =$AA$19/12 -> 0 | V19: =$AA$19/12 -> 0 | ... Z19: =$AA$19/12 -> 0 | AA19: ='Calculs financiers'!D61 -> 0 | AB19: =$AN$19/12 -> 0 | AC19: =$AN$19/12 -> 0 | AD19: =$AN$19/12 -> 0 | AE19: =$AN$19/12 -> 0 | AF19: =$AN$19/12 -> 0 | AG19: =$AN$19/12 -> 0 | AH19: =$AN$19/12 -> 0 | AI19: =$AN$19/12 -> 0 | ... AM19: =$AN$19/12 -> 0 | AN19: ='Calculs financiers'!D62 -> 0 | AO19: =$BA$19/12 -> 0 | AP19: =$BA$19/12 -> 0 | AQ19: =$BA$19/12 -> 0 | AR19: =$BA$19/12 -> 0 | AS19: =$BA$19/12 -> 0 | AT19: =$BA$19/12 -> 0 | AU19: =$BA$19/12 -> 0 | AV19: =$BA$19/12 -> 0 | ... AZ19: =$BA$19/12 -> 0 | BA19: ='Calculs financiers'!D63 -> 0 | BB19: =$BN$19/12 -> 0 | BC19: =$BN$19/12 -> 0 | BD19: =$BN$19/12 -> 0 | BE19: =$BN$19/12 -> 0 | BF19: =$BN$19/12 -> 0 | BG19: =$BN$19/12 -> 0 | BH19: =$BN$19/12 -> 0 | BI19: =$BN$19/12 -> 0 | ... BM19: =$BN$19/12 -> 0 | BN19: ='Calculs financiers'!D64 -> 0
A20: Escomptes accordés | N20: =SUM(B20:M20) -> 0
A21: Autres intérets | N21: =SUM(B21:M21) -> 0
A22: Perte de change | N22: =SUM(B22:M22) -> 0 | AA22: =SUM(O22:Z22) -> 0 | AN22: =SUM(AB22:AM22) -> 0 | BA22: =SUM(AO22:AZ22) -> 0 | BN22: =SUM(BB22:BM22) -> 0
N23: =SUM(B23:M23) -> 0 | AA23: =SUM(O23:Z23) -> 0 | AN23: =SUM(AB23:AM23) -> 0 | BA23: =SUM(AO23:AZ23) -> 0 | BN23: =SUM(BB23:BM23) -> 0
A24: TOTAL DES CHARGES FIXES | B24: =SUM(B2:B23) -> 1268000 | C24: =SUM(C2:C23) -> 918000 | D24: =SUM(D2:D23) -> 1068000 | E24: =SUM(E2:E23) -> 918000 | F24: =SUM(F2:F23) -> 918000 | G24: =SUM(G2:G23) -> 1068000 | H24: =SUM(H2:H23) -> 918000 | I24: =SUM(I2:I23) -> 918000 | ... BN24: =SUM(BN2:BN23) -> 1380924.5

Sheet Calcul intermédiaires Investiss
A3: Logiciel | B3: 50000000
A4: Ordinateurs | B4: 7000000
A5: Bureaux | B5: 5623482

Sheet Liste des investissements
A1: Nature de l'investissement | B1: Mois 1 | C1: Mois 2 | D1: Mois 3 | E1: Mois 4 | F1: Mois 5 | G1: Mois 6 | H1: Mois 7 | I1: Mois 8 | J1: Mois 9 | K1: Mois 10 | L1: Mois 11 | M1: Mois 12 | N1: Année 1 | O1: Mois 13 | P1: Mois 14 | Q1: Mois 15 | R1: Mois 16 | S1: Mois 17 | T1: Mois 18 | U1: Mois 19 | V1: Mois 20 | W1: Mois 21 | X1: Mois 22 | Y1: Mois 23 | Z1: Mois 24 | AA1: Année 2 | AB1: Mois 25 | AC1: Mois 26 | AD1: Mois 27 | AE1: Mois 28 | AF1: Mois 29 | AG1: Mois 30 | AH1: Mois 31 | AI1: Mois 32 | AJ1: Mois 33 | AK1: Mois 34 | AL1: Mois 35 | AM1: Mois 36 | AN1: Année 3 | AO1: Mois 37 | AP1: Mois 38 | AQ1: Mois 39 | AR1: Mois 40 | AS1: Mois 41 | AT1: Mois 42 | AU1: Mois 43 | AV1: Mois 44 | AW1: Mois 45 | AX1: Mois 46 | AY1: Mois 47 | AZ1: Mois 48 | BA1: Année 4 | BB1: Mois 49 | BC1: Mois 50 | BD1: Mois 51 | BE1: Mois 52 | BF1: Mois 53 | BG1: Mois 54 | BH1: Mois 55 | BI1: Mois 56 | BJ1: Mois 57 | BK1: Mois 58 | BL1: Mois 59 | BM1: Mois 60 | BN1: Année 5
A2: Frais de constitution | N2: =SUM(B2:M2) -> 0 | AA2: =SUM(O2:Z2) -> 0 | AN2: =SUM(AB2:AM2) -> 0 | BA2: =SUM(AO2:AZ2) -> 0 | BN2: =SUM(BB2:BM2) -> 0
A3: Frais de propection | N3: =SUM(B3:M3) -> 0 | AA3: =SUM(O3:Z3) -> 0 | AN3: =SUM(AB3:AM3) -> 0 | BA3: =SUM(AO3:AZ3) -> 0 | BN3: =SUM(BB3:BM3) -> 0
A4: Frais de publicité et de lancement | N4: =SUM(B4:M4) -> 0 | AA4: =SUM(O4:Z4) -> 0 | AN4: =SUM(AB4:AM4) -> 0 | BA4: =SUM(AO4:AZ4) -> 0 | BN4: =SUM(BB4:BM4) -> 0
A5: Frais de fonctionnement antérieur au démarrage | N5: =SUM(B5:M5) -> 0 | AA5: =SUM(O5:Z5) -> 0 | AN5: =SUM(AB5:AM5) -> 0 | BA5: =SUM(AO5:AZ5) -> 0 | BN5: =SUM(BB5:BM5) -> 0
A6: Frais de modification de capital | N6: =SUM(B6:M6) -> 0 | AA6: =SUM(O6:Z6) -> 0 | AN6: =SUM(AB6:AM6) -> 0 | BA6: =SUM(AO6:AZ6) -> 0 | BN6: =SUM(BB6:BM6) -> 0
A7: Frais d'entrée en bourse | N7: =SUM(B7:M7) -> 0 | AA7: =SUM(O7:Z7) -> 0 | AN7: =SUM(AB7:AM7) -> 0 | BA7: =SUM(AO7:AZ7) -> 0 | BN7: =SUM(BB7:BM7) -> 0
A8: Frais de restructuration | N8: =SUM(B8:M8) -> 0 | AA8: =SUM(O8:Z8) -> 0 | AN8: =SUM(AB8:AM8) -> 0 | BA8: =SUM(AO8:AZ8) -> 0 | BN8: =SUM(BB8:BM8) -> 0
A9: Frais divers d'établissement | N9: =SUM(B9:M9) -> 0 | AA9: =SUM(O9:Z9) -> 0 | AN9: =SUM(AB9:AM9) -> 0 | BA9: =SUM(AO9:AZ9) -> 0 | BN9: =SUM(BB9:BM9) -> 0
A10: Charges à répartir sur plusieurs exercices | N10: =SUM(B10:M10) -> 0 | AA10: =SUM(O10:Z10) -> 0 | AN10: =SUM(AB10:AM10) -> 0 | BA10: =SUM(AO10:AZ10) -> 0 | BN10: =SUM(BB10:BM10) -> 0
A11: Primes de remboursement des obligations | N11: =SUM(B11:M11) -> 0 | AA11: =SUM(O11:Z11) -> 0 | AN11: =SUM(AB11:AM11) -> 0 | BA11: =SUM(AO11:AZ11) -> 0 | BN11: =SUM(BB11:BM11) -> 0
A12: Frais de recherche et développement | N12: =SUM(B12:M12) -> 0 | AA12: =SUM(O12:Z12) -> 0 | AN12: =SUM(AB12:AM12) -> 0 | BA12: =SUM(AO12:AZ12) -> 0 | BN12: =SUM(BB12:BM12) -> 0
A13: Brevets, licences, concessions et droits similaires | N13: =SUM(B13:M13) -> 0 | AA13: =SUM(O13:Z13) -> 0 | AN13: =SUM(AB13:AM13) -> 0 | BA13: =SUM(AO13:AZ13) -> 0 | BN13: =SUM(BB13:BM13) -> 0
... A33: Installations techniques | N33: =SUM(B33:M33) -> 0 | AA33: =SUM(O33:Z33) -> 0 | AN33: =SUM(AB33:AM33) -> 0 | BA33: =SUM(AO33:AZ33) -> 0 | BN33: =SUM(BB33:BM33) -> 0
A34: Aménagement de bureaux | B34: 1000000 | N34: =SUM(B34:M34) -> 1000000 | AA34: =SUM(O34:Z34) -> 0 | AN34: =SUM(AB34:AM34) -> 0 | BA34: =SUM(AO34:AZ34) -> 0 | BN34: =SUM(BB34:BM34) -> 0
A35: Batiment mis en concession | N35: =SUM(B35:M35) -> 0 | AA35: =SUM(O35:Z35) -> 0 | AN35: =SUM(AB35:AM35) -> 0 | BA35: =SUM(AO35:AZ35) -> 0 | BN35: =SUM(BB35:BM35) -> 0
A36: Autres installations et agencements | N36: =SUM(B36:M36) -> 0 | AA36: =SUM(O36:Z36) -> 0 | AN36: =SUM(AB36:AM36) -> 0 | BA36: =SUM(AO36:AZ36) -> 0 | BN36: =SUM(BB36:BM36) -> 0
A37: Batiments et installations en cours | N37: =SUM(B37:M37) -> 0 | AA37: =SUM(O37:Z37) -> 0 | AN37: =SUM(AB37:AM37) -> 0 | BA37: =SUM(AO37:AZ37) -> 0 | BN37: =SUM(BB37:BM37) -> 0
A38: Matériel et outillage industriel | B38: 17000000 | N38: =SUM(B38:M38) -> 17000000 | AA38: =SUM(O38:Z38) -> 0 | AN38: =SUM(AB38:AM38) -> 0 | BA38: =SUM(AO38:AZ38) -> 0 | BN38: =SUM(BB38:BM38) -> 0
A39: Martériel et outillage agricole | N39: =SUM(B39:M39) -> 0 | AA39: =SUM(O39:Z39) -> 0 | AN39: =SUM(AB39:AM39) -> 0 | BA39: =SUM(AO39:AZ39) -> 0 | BN39: =SUM(BB39:BM39) -> 0
A40: Matériel d’emballage récupérable et identifiable | N40: =SUM(B40:M40) -> 0 | AA40: =SUM(O40:Z40) -> 0 | AN40: =SUM(AB40:AM40) -> 0 | BA40: =SUM(AO40:AZ40) -> 0 | BN40: =SUM(BB40:BM40) -> 0
A41: Matériel et mobilier | N41: =SUM(B41:M41) -> 0 | AA41: =SUM(O41:Z41) -> 0 | AN41: =SUM(AB41:AM41) -> 0 | BA41: =SUM(AO41:AZ41) -> 0 | BN41: =SUM(BB41:BM41) -> 0
A42: Matériel de transport | N42: =SUM(B42:M42) -> 0 | AA42: =SUM(O42:Z42) -> 0 | AN42: =SUM(AB42:AM42) -> 0 | BA42: =SUM(AO42:AZ42) -> 0 | BN42: =SUM(BB42:BM42) -> 0
A43: Cheptel, animaux de trait | N43: =SUM(B43:M43) -> 0 | AA43: =SUM(O43:Z43) -> 0 | AN43: =SUM(AB43:AM43) -> 0 | BA43: =SUM(AO43:AZ43) -> 0 | BN43: =SUM(BB43:BM43) -> 0
A44: Cheptel, animaux reproducteurs | N44: =SUM(B44:M44) -> 0 | AA44: =SUM(O44:Z44) -> 0 | AN44: =SUM(AB44:AM44) -> 0 | BA44: =SUM(AO44:AZ44) -> 0 | BN44: =SUM(BB44:BM44) -> 0
A45: Animaux de garde | N45: =SUM(B45:M45) -> 0 | AA45: =SUM(O45:Z45) -> 0 | AN45: =SUM(AB45:AM45) -> 0 | BA45: =SUM(AO45:AZ45) -> 0 | BN45: =SUM(BB45:BM45) -> 0
A46: Plantations agricoles | N46: =SUM(B46:M46) -> 0 | AA46: =SUM(O46:Z46) -> 0 | AN46: =SUM(AB46:AM46) -> 0 | BA46: =SUM(AO46:AZ46) -> 0 | BN46: =SUM(BB46:BM46) -> 0
A47: Agencements et aménagements du matériel | N47: =SUM(B47:M47) -> 0 | AA47: =SUM(O47:Z47) -> 0 | AN47: =SUM(AB47:AM47) -> 0 | BA47: =SUM(AO47:AZ47) -> 0 | BN47: =SUM(BB47:BM47) -> 0
A48: Autres matériels | N48: =SUM(B48:M48) -> 0 | AA48: =SUM(O48:Z48) -> 0 | AN48: =SUM(AB48:AM48) -> 0 | BA48: =SUM(AO48:AZ48) -> 0 | BN48: =SUM(BB48:BM48) -> 0
A49: Matériel en cours | N49: =SUM(B49:M49) -> 0 | AA49: =SUM(O49:Z49) -> 0 | AN49: =SUM(AB49:AM49) -> 0 | BA49: =SUM(AO49:AZ49) -> 0 | BN49: =SUM(BB49:BM49) -> 0
A50: Avances et acomptes versés sur immobilisations incorporelles | N50: =SUM(B50:M50) -> 0 | AA50: =SUM(O50:Z50) -> 0 | AN50: =SUM(AB50:AM50) -> 0 | BA50: =SUM(AO50:AZ50) -> 0 | BN50: =SUM(BB50:BM50) -> 0
... A60: Immobilisations financières diverses | N60: =SUM(B60:M60) -> 0 | AA60: =SUM(O60:Z60) -> 0 | AN60: =SUM(AB60:AM60) -> 0 | BA60: =SUM(AO60:AZ60) -> 0 | BN60: =SUM(BB60:BM60) -> 0
A61: TOTAL DES INVESTISSEMENTS | B61: =SUM(B2:B60) -> 18000000 | C61: =SUM(C2:C60) -> 0 | D61: =SUM(D2:D60) -> 0 | E61: =SUM(E2:E60) -> 0 | F61: =SUM(F2:F60) -> 0 | G61: =SUM(G2:G60) -> 0 | H61: =SUM(H2:H60) -> 0 | I61: =SUM(I2:I60) -> 0 | ... BN61: =SUM(BN2:BN60) -> 0

Sheet tableau des amortissements
B2: Amortissement des immobilisations incorporelles (5 ans) | I2: Amortissement des immobilisations corporelles (Mobilier : 10 ans)
B3: Année | C3: Base d'amortissement | D3: Taux | E3: Dotations / Annuités | F3: Cumul des Amortissements | G3: VNA | I3: Année | J3: Base d'amortissement | K3: Taux | L3: Dotations / Annuités | M3: Cumul des Amortissements | N3: VNA
B4: 1 | C4: =SUM('Liste des investissements'!$N$2:$N$20) -> 0 | D4: 0.2 | E4: =C4*D4 -> 0 | F4: =E4 -> 0 | G4: =C4-F4 -> 0 | I4: 1 | J4: ='Liste des investissements'!$N$41 -> 0 | K4: 0.05 | L4: =J4*K4 -> 0 | M4: =L4 -> 0 | N4: =J4-M4 -> 0
B5: 2 | C5: =SUM('Liste des investissements'!$N$2:$N$20) -> 0 | D5: 0.2 | E5: =C5*D5 -> 0 | F5: =F4+E5 -> 0 | G5: =C5-F5 -> 0 | I5: 2 | J5: ='Liste des investissements'!$N$41 -> 0 | K5: 0.05 | L5: =J5*K5 -> 0 | M5: =M4+L5 -> 0 | N5: =J5-M5 -> 0
B6: 3 | C6: =SUM('Liste des investissements'!$N$2:$N$20) -> 0 | D6: 0.2 | E6: =C6*D6 -> 0 | F6: =F5+E6 -> 0 | G6: =C6-F6 -> 0 | I6: 3 | J6: ='Liste des investissements'!$N$41 -> 0 | K6: 0.05 | L6: =J6*K6 -> 0 | M6: =M5+L6 -> 0 | N6: =J6-M6 -> 0
B7: 4 | C7: =SUM('Liste des investissements'!$N$2:$N$20) -> 0 | D7: 0.2 | E7: =C7*D7 -> 0 | F7: =F6+E7 -> 0 | G7: =C7-F7 -> 0 | I7: 4 | J7: ='Liste des investissements'!$N$41 -> 0 | K7: 0.05 | L7: =J7*K7 -> 0 | M7: =M6+L7 -> 0 | N7: =J7-M7 -> 0
B8: 5 | C8: =SUM('Liste des investissements'!$N$2:$N$20) -> 0 | D8: 0.2 | E8: =C8*D8 -> 0 | F8: =F7+E8 -> 0 | G8: =C8-F8 -> 0 | I8: 5 | J8: ='Liste des investissements'!$N$41 -> 0 | K8: 0.05 | L8: =J8*K8 -> 0 | M8: =M7+L8 -> 0 | N8: =J8-M8 -> 0
I9: 6 | J9: ='Liste des investissements'!$N$41 -> 0 | K9: 0.05 | L9: =J9*K9 -> 0 | M9: =M8+L9 -> 0 | N9: =J9-M9 -> 0
I10: 7 | J10: ='Liste des investissements'!$N$41 -> 0 | K10: 0.05 | L10: =J10*K10 -> 0 | M10: =M9+L10 -> 0 | N10: =J10-M10 -> 0
I11: 8 | J11: ='Liste des investissements'!$N$41 -> 0 | K11: 0.05 | L11: =J11*K11 -> 0 | M11: =M10+L11 -> 0 | N11: =J11-M11 -> 0
B12: Amortissement des immobilisations corporelles (Batiments : 20 ans) | I12: 9 | J12: ='Liste des investissements'!$N$41 -> 0 | K12: 0.05 | L12: =J12*K12 -> 0 | M12: =M11+L12 -> 0 | N12: =J12-M12 -> 0
B13: Année | C13: Base d'amortissement | D13: Taux | E13: Dotations / Annuités | F13: Cumul des Amortissements | G13: VNA | I13: 10 | J13: ='Liste des investissements'!$N$41 -> 0 | K13: 0.05 | L13: =J13*K13 -> 0 | M13: =M12+L13 -> 0 | N13: =J13-M13 -> 0
B14: 1 | C14: =SUM('Liste des investissements'!$N$30:$N$37) -> 1000000 | D14: 0.05 | E14: =C14*D14 -> 50000 | F14: =E14 -> 50000 | G14: =C14-F14 -> 950000
B15: 2 | C15: =SUM('Liste des investissements'!$N$30:$N$37) -> 1000000 | D15: 0.05 | E15: =C15*D15 -> 50000 | F15: =F14+E15 -> 100000 | G15: =C15-F15 -> 900000
B16: 3 | C16: =SUM('Liste des investissements'!$N$30:$N$37) -> 1000000 | D16: 0.05 | E16: =C16*D16 -> 50000 | F16: =F15+E16 -> 150000 | G16: =C16-F16 -> 850000 | I16: Amortissement des immobilisations corporelles (Matériel et outillage; animaux; cheptel;plantations agricoles: 5 ans)
B17: 4 | C17: =SUM('Liste des investissements'!$N$30:$N$37) -> 1000000 | D17: 0.05 | E17: =C17*D17 -> 50000 | F17: =F16+E17 -> 200000 | G17: =C17-F17 -> 800000 | I17: Année | J17: Base d'amortissement | K17: Taux | L17: Dotations / Annuités | M17: Cumul des Amortissements | N17: VNA
B18: 5 | C18: =SUM('Liste des investissements'!$N$30:$N$37) -> 1000000 | D18: 0.05 | E18: =C18*D18 -> 50000 | F18: =F17+E18 -> 250000 | G18: =C18-F18 -> 750000 | I18: 1 | J18: =SUM('Liste des investissements'!$N$38:$N$40)+SUM('Liste des investissements'!$N$42:$N$49) -> 17000000 | K18: 0.2 | L18: =J18*K18 -> 3400000 | M18: =L18 -> 3400000 | N18: =J18-M18 -> 13600000
B19: 6 | C19: =SUM('Liste des investissements'!$N$30:$N$37) -> 1000000 | D19: 0.05 | E19: =C19*D19 -> 50000 | F19: =F18+E19 -> 300000 | G19: =C19-F19 -> 700000 | I19: 2 | J19: =SUM('Liste des investissements'!$N$38:$N$40)+SUM('Liste des investissements'!$N$42:$N$49) -> 17000000 | K19: 0.2 | L19: =J19*K19 -> 3400000 | M19: =M18+L19 -> 6800000 | N19: =J19-M19 -> 10200000
B20: 7 | C20: =SUM('Liste des investissements'!$N$30:$N$37) -> 1000000 | D20: 0.05 | E20: =C20*D20 -> 50000 | F20: =F19+E20 -> 350000 | G20: =C20-F20 -> 650000 | I20: 3 | J20: =SUM('Liste des investissements'!$N$38:$N$40)+SUM('Liste des investissements'!$N$42:$N$49) -> 17000000 | K20: 0.2 | L20: =J20*K20 -> 3400000 | M20: =M19+L20 -> 10200000 | N20: =J20-M20 -> 6800000
B21: 8 | C21: =SUM('Liste des investissements'!$N$30:$N$37) -> 1000000 | D21: 0.05 | E21: =C21*D21 -> 50000 | F21: =F20+E21 -> 400000 | G21: =C21-F21 -> 600000 | I21: 4 | J21: =SUM('Liste des investissements'!$N$38:$N$40)+SUM('Liste des investissements'!$N$42:$N$49) -> 17000000 | K21: 0.2 | L21: =J21*K21 -> 3400000 | M21: =M20+L21 -> 13600000 | N21: =J21-M21 -> 3400000
B22: 9 | C22: =SUM('Liste des investissements'!$N$30:$N$37) -> 1000000 | D22: 0.05 | E22: =C22*D22 -> 50000 | F22: =F21+E22 -> 450000 | G22: =C22-F22 -> 550000 | I22: 5 | J22: =SUM('Liste des investissements'!$N$38:$N$40)+SUM('Liste des investissements'!$N$42:$N$49) -> 17000000 | K22: 0.2 | L22: =J22*K22 -> 3400000 | M22: =M21+L22 -> 17000000 | N22: =J22-M22 -> 0
B23: 10 | C23: =SUM('Liste des investissements'!$N$30:$N$37) -> 1000000 | D23: 0.05 | E23: =C23*D23 -> 50000 | F23: =F22+E23 -> 500000 | G23: =C23-F23 -> 500000
B24: 11 | C24: =SUM('Liste des investissements'!$N$30:$N$37) -> 1000000 | D24: 0.05 | E24: =C24*D24 -> 50000 | F24: =F23+E24 -> 550000 | G24: =C24-F24 -> 450000
B25: 12 | C25: =SUM('Liste des investissements'!$N$30:$N$37) -> 1000000 | D25: 0.05 | E25: =C25*D25 -> 50000 | F25: =F24+E25 -> 600000 | G25: =C25-F25 -> 400000
B26: 13 | C26: =SUM('Liste des investissements'!$N$30:$N$37) -> 1000000 | D26: 0.05 | E26: =C26*D26 -> 50000 | F26: =F25+E26 -> 650000 | G26: =C26-F26 -> 350000
B27: 14 | C27: =SUM('Liste des investissements'!$N$30:$N$37) -> 1000000 | D27: 0.05 | E27: =C27*D27 -> 50000 | F27: =F26+E27 -> 700000 | G27: =C27-F27 -> 300000
B28: 15 | C28: =SUM('Liste des investissements'!$N$30:$N$37) -> 1000000 | D28: 0.05 | E28: =C28*D28 -> 50000 | F28: =F27+E28 -> 750000 | G28: =C28-F28 -> 250000
B29: 16 | C29: =SUM('Liste des investissements'!$N$30:$N$37) -> 1000000 | D29: 0.05 | E29: =C29*D29 -> 50000 | F29: =F28+E29 -> 800000 | G29: =C29-F29 -> 200000
B30: 17 | C30: =SUM('Liste des investissements'!$N$30:$N$37) -> 1000000 | D30: 0.05 | E30: =C30*D30 -> 50000 | F30: =F29+E30 -> 850000 | G30: =C30-F30 -> 150000
B31: 18 | C31: =SUM('Liste des investissements'!$N$30:$N$37) -> 1000000 | D31: 0.05 | E31: =C31*D31 -> 50000 | F31: =F30+E31 -> 900000 | G31: =C31-F31 -> 100000
B32: 19 | C32: =SUM('Liste des investissements'!$N$30:$N$37) -> 1000000 | D32: 0.05 | E32: =C32*D32 -> 50000 | F32: =F31+E32 -> 950000 | G32: =C32-F32 -> 50000
B33: 20 | C33: =SUM('Liste des investissements'!$N$30:$N$37) -> 1000000 | D33: 0.05 | E33: =C33*D33 -> 50000 | F33: =F32+E33 -> 1000000 | G33: =C33-F33 -> 0

Sheet Fonds de roulement
B1: Mois 1 | C1: Mois 2 | D1: Mois 3 | E1: Mois 4 | F1: Mois 5 | G1: Mois 6 | H1: Mois 7 | I1: Mois 8 | J1: Mois 9 | K1: Mois 10 | L1: Mois 11 | M1: Mois 12 | N1: Année 1
A2: Achats de marchandises | B2: ='Charges variables'!B2 -> 0 | C2: ='Charges variables'!C2 -> 0 | D2: ='Charges variables'!D2 -> 0 | E2: ='Charges variables'!E2 -> 0 | F2: ='Charges variables'!F2 -> 0 | G2: ='Charges variables'!G2 -> 0 | H2: ='Charges variables'!H2 -> 0 | I2: ='Charges variables'!I2 -> 0 | ... M2: ='Charges variables'!M2 -> 0 | N2: =SUM(B2:M2) -> 0
A3: Achats de matières premières | B3: ='Charges variables'!B3 -> 0 | C3: ='Charges variables'!C3 -> 0 | D3: ='Charges variables'!D3 -> 0 | E3: ='Charges variables'!E3 -> 0 | F3: ='Charges variables'!F3 -> 0 | G3: ='Charges variables'!G3 -> 0 | H3: ='Charges variables'!H3 -> 0 | I3: ='Charges variables'!I3 -> 0 | ... M3: ='Charges variables'!M3 -> 0 | N3: =SUM(B3:M3) -> 0
A4: Achats stockés de matières et fournitures consommables | B4: ='Charges variables'!B4 -> 0 | C4: ='Charges variables'!C4 -> 0 | D4: ='Charges variables'!D4 -> 0 | E4: ='Charges variables'!E4 -> 0 | F4: ='Charges variables'!F4 -> 0 | G4: ='Charges variables'!G4 -> 0 | H4: ='Charges variables'!H4 -> 0 | I4: ='Charges variables'!I4 -> 0 | ... M4: ='Charges variables'!M4 -> 0 | N4: =SUM(B4:M4) -> 0
A5: TOTAL Marchandises / matières premières et fournitures | B5: =SUM(B2:B4) -> 0 | C5: =SUM(C2:C4) -> 0 | D5: =SUM(D2:D4) -> 0 | E5: =SUM(E2:E4) -> 0 | F5: =SUM(F2:F4) -> 0 | G5: =SUM(G2:G4) -> 0 | H5: =SUM(H2:H4) -> 0 | I5: =SUM(I2:I4) -> 0 | ... M5: =SUM(M2:M4) -> 0 | N5: =SUM(B5:M5) -> 0
A6: Autres achats (achats d'études et prestation de services) | B6: ='Charges variables'!B7 -> 0 | C6: ='Charges variables'!C7 -> 0 | D6: ='Charges variables'!D7 -> 0 | E6: ='Charges variables'!E7 -> 0 | F6: ='Charges variables'!F7 -> 0 | G6: ='Charges variables'!G7 -> 0 | H6: ='Charges variables'!H7 -> 0 | I6: ='Charges variables'!I7 -> 0 | ... M6: ='Charges variables'!M7 -> 0 | N6: =SUM(B6:M6) -> 0
A7: Achats d'emballages | B7: ='Charges variables'!B8 -> 0 | C7: ='Charges variables'!C8 -> 0 | D7: ='Charges variables'!D8 -> 0 | E7: ='Charges variables'!E8 -> 0 | F7: ='Charges variables'!F8 -> 0 | G7: ='Charges variables'!G8 -> 0 | H7: ='Charges variables'!H8 -> 0 | I7: ='Charges variables'!I8 -> 0 | ... M7: ='Charges variables'!M8 -> 0 | N7: =SUM(B7:M7) -> 0
A8: Transport sur achats | B8: ='Charges variables'!B9 -> 0 | C8: ='Charges variables'!C9 -> 0 | D8: ='Charges variables'!D9 -> 0 | E8: ='Charges variables'!E9 -> 0 | F8: ='Charges variables'!F9 -> 0 | G8: ='Charges variables'!G9 -> 0 | H8: ='Charges variables'!H9 -> 0 | I8: ='Charges variables'!I9 -> 0 | ... M8: ='Charges variables'!M9 -> 0 | N8: =SUM(B8:M8) -> 0
A9: Transports sur ventes | B9: ='Charges variables'!B10 -> 0 | C9: ='Charges variables'!C10 -> 0 | D9: ='Charges variables'!D10 -> 0 | E9: ='Charges variables'!E10 -> 0 | F9: ='Charges variables'!F10 -> 0 | G9: ='Charges variables'!G10 -> 0 | H9: ='Charges variables'!H10 -> 0 | I9: ='Charges variables'!I10 -> 0 | ... M9: ='Charges variables'!M10 -> 0 | N9: =SUM(B9:M9) -> 0
A10: Transport pour le compte de tiers | B10: ='Charges variables'!B11 -> 0 | C10: ='Charges variables'!C11 -> 0 | D10: ='Charges variables'!D11 -> 0 | E10: ='Charges variables'!E11 -> 0 | F10: ='Charges variables'!F11 -> 0 | G10: ='Charges variables'!G11 -> 0 | H10: ='Charges variables'!H11 -> 0 | I10: ='Charges variables'!I11 -> 0 | ... M10: ='Charges variables'!M11 -> 0 | N10: =SUM(B10:M10) -> 0
A11: Transport de plis | B11: ='Charges variables'!B12 -> 0 | C11: ='Charges variables'!C12 -> 0 | D11: ='Charges variables'!D12 -> 0 | E11: ='Charges variables'!E12 -> 0 | F11: ='Charges variables'!F12 -> 0 | G11: ='Charges variables'!G12 -> 0 | H11: ='Charges variables'!H12 -> 0 | I11: ='Charges variables'!I12 -> 0 | ... M11: ='Charges variables'!M12 -> 0 | N11: =SUM(B11:M11) -> 0
A12: Autres frais de transport (Voyage, déplacement) | B12: ='Charges variables'!B13 -> 150000 | C12: ='Charges variables'!C13 -> 150000 | D12: ='Charges variables'!D13 -> 150000 | E12: ='Charges variables'!E13 -> 150000 | F12: ='Charges variables'!F13 -> 150000 | G12: ='Charges variables'!G13 -> 150000 | H12: ='Charges variables'!H13 -> 150000 | I12: ='Charges variables'!I13 -> 150000 | ... M12: ='Charges variables'!M13 -> 150000 | N12: =SUM(B12:M12) -> 1800000
A13: Sous traitance générale | B13: ='Charges variables'!B14 -> 0 | C13: ='Charges variables'!C14 -> 0 | D13: ='Charges variables'!D14 -> 0 | E13: ='Charges variables'!E14 -> 0 | F13: ='Charges variables'!F14 -> 0 | G13: ='Charges variables'!G14 -> 0 | H13: ='Charges variables'!H14 -> 0 | I13: ='Charges variables'!I14 -> 0 | ... M13: ='Charges variables'!M14 -> 0 | N13: =SUM(B13:M13) -> 0
A14: Publicité, publications, relations publiques | B14: ='Charges variables'!B15 -> 8750 | C14: ='Charges variables'!C15 -> 17500 | D14: ='Charges variables'!D15 -> 26250 | E14: ='Charges variables'!E15 -> 35000 | F14: ='Charges variables'!F15 -> 43750 | G14: ='Charges variables'!G15 -> 52500 | H14: ='Charges variables'!H15 -> 70000 | I14: ='Charges variables'!I15 -> 78750 | ... M14: ='Charges variables'!M15 -> 78750 | N14: =SUM(B14:M14) -> 647500
A15: Frais de télécommunications | B15: ='Charges variables'!B16 -> 50000 | C15: ='Charges variables'!C16 -> 50000 | D15: ='Charges variables'!D16 -> 50000 | E15: ='Charges variables'!E16 -> 50000 | F15: ='Charges variables'!F16 -> 50000 | G15: ='Charges variables'!G16 -> 50000 | H15: ='Charges variables'!H16 -> 50000 | I15: ='Charges variables'!I16 -> 50000 | ... M15: ='Charges variables'!M16 -> 50000 | N15: =SUM(B15:M15) -> 600000
A16: Frais bancaires | B16: ='Charges variables'!B17 -> 5000 | C16: ='Charges variables'!C17 -> 5000 | D16: ='Charges variables'!D17 -> 5000 | E16: ='Charges variables'!E17 -> 5000 | F16: ='Charges variables'!F17 -> 5000 | G16: ='Charges variables'!G17 -> 5000 | H16: ='Charges variables'!H17 -> 5000 | I16: ='Charges variables'!I17 -> 5000 | ... M16: ='Charges variables'!M17 -> 5000 | N16: =SUM(B16:M16) -> 60000
A17: Rémunérations d’intermédiaires et de conseils | B17: ='Charges variables'!B18 -> 17500 | C17: ='Charges variables'!C18 -> 35000 | D17: ='Charges variables'!D18 -> 52500 | E17: ='Charges variables'!E18 -> 70000 | F17: ='Charges variables'!F18 -> 87500 | G17: ='Charges variables'!G18 -> 105000 | H17: ='Charges variables'!H18 -> 140000 | I17: ='Charges variables'!I18 -> 157500 | ... M17: ='Charges variables'!M18 -> 157500 | N17: =SUM(B17:M17) -> 1295000
... A42: Perte de change | B42: ='Charges variables'!B43 -> 0 | C42: ='Charges variables'!C43 -> 0 | D42: ='Charges variables'!D43 -> 0 | E42: ='Charges variables'!E43 -> 0 | F42: ='Charges variables'!F43 -> 0 | G42: ='Charges variables'!G43 -> 0 | H42: ='Charges variables'!H43 -> 0 | I42: ='Charges variables'!I43 -> 0 | ... M42: ='Charges variables'!M43 -> 0 | N42: =SUM(B42:M42) -> 0
N43: =SUM(B43:M43) -> 0
A44: Frais de premier fonctionnement | B44: =SUM(B6:B43) -> 915000.6 | C44: =SUM(C6:C43) -> 1020000 | D44: =SUM(D6:D43) -> 1125000 | E44: =SUM(E6:E43) -> 1230000 | F44: =SUM(F6:F43) -> 1335000 | G44: =SUM(G6:G43) -> 1640000 | H44: =SUM(H6:H43) -> 1850000 | I44: =SUM(I6:I43) -> 1955000 | ... M44: =SUM(M6:M43) -> 1955000 | N44: =SUM(B44:M44) -> 18890001
A45: FONDS DE ROULEMENT | B45: =+B5+B44 -> 915000.6 | C45: =+C5+C44 -> 1020000 | D45: =+D5+D44 -> 1125000 | E45: =+E5+E44 -> 1230000 | F45: =+F5+F44 -> 1335000 | G45: =+G5+G44 -> 1640000 | H45: =+H5+H44 -> 1850000 | I45: =+I5+I44 -> 1955000 | ... N45: =+N5+N44 -> 18890001

Sheet Cout et schema de financement
D2: Schéma de financement
C3: TOTAL | D3: Apport en capital | E3: Apport en compte courant associés | F3: Crédit bail | G3: Emprunts bancaires classique (CMT) | H3: Crédit fournisseurs | I3: autofinancement | J3: Subvention
B4: Immobilisations incorporelles | C4: =SUM('Liste des investissements'!$N$2:$N$20) -> 0 | D4: 1000000 | J4: =C13 -> 35890001
B5: Immobilisations corporelles | C5: =SUM('Liste des investissements'!N21:N49) -> 18000000
B6: Immobilisations financières | C6: =SUM('Liste des investissements'!$A$50:$A$60) -> 0
B7: Total des Investissements | C7: =+SUM(C4:C6) -> 18000000 | D7: =+SUM(D4:D6) -> 1000000 | E7: =+SUM(E4:E6) -> 0 | F7: =+SUM(F4:F6) -> 0 | G7: =+SUM(G4:G6) -> 0 | H7: =+SUM(H4:H6) -> 0 | I7: =+SUM(I4:I6) -> 0 | J7: =SUM(J4:J6) -> 35890001
B8: Marchandises / Matières premières et fournitures | C8: =SUM('Fonds de roulement'!$N$2:$N$4) -> 0
B9: Frais de premier fonctionnement | C9: ='Fonds de roulement'!N44 -> 18890001
B10: besoins en Fonds de roulements | C10: =+SUM(C8:C9) -> 18890001 | D10: =+SUM(D8:D9) -> 0 | E10: =+SUM(E8:E9) -> 0 | F10: =+SUM(F8:F9) -> 0 | G10: =+SUM(G8:G9) -> 0 | H10: =+SUM(H8:H9) -> 0 | I10: =+SUM(I8:I9) -> 0 | J10: =SUM(J8:J9) -> 0
B11: COUT TOTAL DU PROJET | C11: =+C7+C10 -> 36890001 | D11: =+D7+D10 -> 1000000 | E11: =+E7+E10 -> 0 | F11: =+F7+F10 -> 0 | G11: =+G7+G10 -> 0 | H11: =+H7+H10 -> 0 | I11: =+I7+I10 -> 0 | J11: =J7+J10 -> 35890001
C13: =C11-D4 -> 35890001 | D13: =C13-C15 -> 35740001
C15: =D4*0.15 -> 150000

Sheet Calculs financiers
B2: Coût du projet
B3: Montant des investissements | C3: ='Cout et schema de financement'!C7 -> 18000000
B4: Besoin en fonds de roulement | C4: ='Cout et schema de financement'!C10 -> 18890001
B5: Coût du projet | C5: =C3+C4 -> 36890001
B10: COMPTE COURANT ASSOCIE
B11: CMT - Remboursement par amortissement constant du capital -
B12: Somme empruntée | C12: ='Cout et schema de financement'!E11 -> 0
B13: Taux d'intérêt annuel | C13: 0.07
B14: La durée de l'emprunt n | C14: 5
B15: Période n | C15: Capital du en début de période | D15: Intérêt (i) | E15: Amortissements | F15: Annuités
B16: 1 | C16: =C12 -> 0 | D16: =C16*$C$13 -> 0 | E16: =$C$16/$C$14 -> 0 | F16: =D16+E16 -> 0
B17: 2 | C17: =C16-E16 -> 0 | D17: =C17*$C$13 -> 0 | E17: =$C$16/$C$14 -> 0 | F17: =D17+E17 -> 0
B18: 3 | C18: =C17-E17 -> 0 | D18: =C18*$C$13 -> 0 | E18: =$C$16/$C$14 -> 0 | F18: =D18+E18 -> 0
B19: 4 | C19: =C18-E18 -> 0 | D19: =C19*$C$13 -> 0 | E19: =$C$16/$C$14 -> 0 | F19: =D19+E19 -> 0
B20: 5 | C20: =C19-E19 -> 0 | D20: =C20*$C$13 -> 0 | E20: =$C$16/$C$14 -> 0 | F20: =D20+E20 -> 0
B21: 6 | C21: =C20-E20 -> 0 | D21: =C21*$C$13 -> 0 | E21: =$C$16/$C$14 -> 0 | F21: =D21+E21 -> 0
B22: 7 | C22: =C21-E21 -> 0 | D22: =C22*$C$13 -> 0 | E22: =$C$16/$C$14 -> 0 | F22: =D22+E22 -> 0
B23: TOTAL | D23: =SUM(D16:D22) -> 0 | E23: =SUM(E16:E22) -> 0 | F23: =SUM(F16:F22) -> 0
B27: CREDIT A COURT - MOYEN TERME
B29: CMT - Remboursement par amortissement constant du capital
B30: Somme empruntée | C30: =SUM('Cout et schema de financement'!G4:G6)+SUM('Cout et schema de financement'!G8:G9) -> 0
B31: Taux d'intérêt annuel | C31: 0.07
B32: La durée de l'emprunt n | C32: 12
B33: Période n | C33: Capital du en début de période | D33: Intérêt (i) | E33: Amortissements | F33: Mensualités
B34: 1 | C34: =C30 -> 0 | D34: =C34*$C$31 -> 0 | F34: =D34+E34 -> 0
B35: 2 | C35: =C34-E34 -> 0 | D35: =C35*$C$31 -> 0 | F35: =D35+E35 -> 0
B36: 3 | C36: =C35-E35 -> 0 | D36: =C36*$C$31 -> 0 | F36: =D36+E36 -> 0
B37: 4 | C37: =C36-E36 -> 0 | D37: =C37*$C$31 -> 0 | E37: =($C$34/$C$32)+($C$34/$C$32) -> 0 | F37: =D37+E37 -> 0
B38: 5 | C38: =C37-E37 -> 0 | D38: =C38*$C$31 -> 0 | E38: =($C$34/$C$32)+($C$34/$C$32) -> 0 | F38: =D38+E38 -> 0
B39: 6 | C39: =C38-E38 -> 0 | D39: =C39*$C$31 -> 0 | E39: =($C$34/$C$32)+($C$34/$C$32) -> 0 | F39: =D39+E39 -> 0
B40: 7 | C40: =C39-E39 -> 0 | D40: =C40*$C$31 -> 0 | E40: =$C$34/$C$32 -> 0 | F40: =D40+E40 -> 0
B41: 8 | C41: =C40-E40 -> 0 | D41: =C41*$C$31 -> 0 | E41: =$C$34/$C$32 -> 0 | F41: =D41+E41 -> 0
B42: 9 | C42: =C41-E41 -> 0 | D42: =C42*$C$31 -> 0 | E42: =$C$34/$C$32 -> 0 | F42: =D42+E42 -> 0
B43: 10 | C43: =C42-E42 -> 0 | D43: =C43*$C$31 -> 0 | E43: =$C$34/$C$32 -> 0 | F43: =D43+E43 -> 0
B44: 11 | C44: =C43-E43 -> 0 | D44: =C44*$C$31 -> 0 | E44: =$C$34/$C$32 -> 0 | F44: =D44+E44 -> 0
B45: 12 | C45: =C44-E44 -> 0 | D45: =C45*$C$31 -> 0 | E45: =$C$34/$C$32 -> 0 | F45: =D45+E45 -> 0
B46: TOTAL | D46: =SUM(D34:D45) -> 0 | E46: =SUM(E34:E45) -> 0 | F46: =SUM(F34:F45) -> 0
B50: CREDIT BAIL - REMBOURSEMENT PAR AMORTISSEMENT CONSTANT
B53: Somme empruntée | C53: ='Cout et schema de financement'!F11 -> 0
B54: Taux d'intérêt annuel | C54: 0.1
B55: La durée de l'emprunt n | C55: 5
B59: Période n | C59: Capital du en début de période | D59: Intérêt (i) | E59: Amortissements | F59: Le loyer en FCFA | G59: Loyer en Euros
B60: 1 | C60: =C53 -> 0 | D60: =C60*$C$54 -> 0 | E60: =$C$53/$C$55 -> 0 | F60: =D60+E60 -> 0 | G60: =F60/655.957 -> 0
B61: 2 | C61: =C60-E60 -> 0 | D61: =C61*$C$54 -> 0 | E61: =$C$53/$C$55 -> 0 | F61: =D61+E61 -> 0 | G61: =F61/655.957 -> 0
B62: 3 | C62: =C61-E61 -> 0 | D62: =C62*$C$54 -> 0 | E62: =$C$53/$C$55 -> 0 | F62: =D62+E62 -> 0 | G62: =F62/655.957 -> 0
B63: 4 | C63: =C62-E62 -> 0 | D63: =C63*$C$54 -> 0 | E63: =$C$53/$C$55 -> 0 | F63: =D63+E63 -> 0 | G63: =F63/655.957 -> 0
B64: 5 | C64: =C63-E63 -> 0 | D64: =C64*$C$54 -> 0 | E64: =$C$53/$C$55 -> 0 | F64: =D64+E64 -> 0 | G64: =F64/655.957 -> 0
B65: 6 | C65: =C64-E64 -> 0 | D65: =C65*$C$54 -> 0 | E65: =$C$53/$C$55 -> 0 | F65: =D65+E65 -> 0 | G65: =F65/655.957 -> 0
B66: 7 | C66: =C65-E65 -> 0 | D66: =C66*$C$54 -> 0 | E66: =$C$53/$C$55 -> 0 | F66: =D66+E66 -> 0 | G66: =F66/655.957 -> 0
B67: TOTAL | D67: =SUM(D60:D66) -> 0 | E67: =SUM(E60:E66) -> 0 | F67: =SUM(F60:F66) -> 0 | G67: =SUM(G60:G66) -> 0

Sheet Compte d'exploitation prév
J1: z
B2: En FCFA | C2: Année 1 | D2: Année 2 | E2: Année 3 | F2: Année 4 | G2: Année 5
B3: Chiffre d'affaires (CA) | C3: ='Chiffre d''affaires prévisionnel'!O22 -> 12950000 | D3: ='Chiffre d''affaires prévisionnel'!AB22 -> 32725000 | E3: ='Chiffre d''affaires prévisionnel'!AO22 -> 65949016 | F3: ='Chiffre d''affaires prévisionnel'!BB22 -> 0 | G3: ='Chiffre d''affaires prévisionnel'!BO22 -> 0
B4: Charges variables / Achats consommés | C4: ='Charges variables'!N23 -> 9445000 | D4: ='Charges variables'!AA23 -> 20120625 | E4: ='Charges variables'!AN23 -> 34796592 | F4: ='Charges variables'!BA23 -> 0 | G4: ='Charges variables'!BN23 -> 0
B5: Marge brute | C5: =C3-C4 -> 3505000 | D5: =D3-D4 -> 12604375 | E5: =E3-E4 -> 31152424 | F5: =F3-F4 -> 0 | G5: =G3-G4 -> 0
B6: Taux de marge sur couts variables | C6: =C5/C3 -> 0.27065637 | D6: =D5/D3 -> 0.38516043 | E6: =E5/E3 -> 0.47237132 | F6: =F5/F3 -> #DIV/0! | G6: =G5/G3 -> #DIV/0!
B7: Charges fixes / Charges externes | C7: ='Charges fixes'!N24-'Charges fixes'!N15-'Charges fixes'!N16-'Charges fixes'!N17 -> 4556981.2 | D7: ='Charges fixes'!AA24-D9-'Charges fixes'!AA15-'Charges fixes'!AA16-'Charges fixes'!AA17 -> -1451140.1 | E7: ='Charges fixes'!AN24-'Charges fixes'!AN15-'Charges fixes'!AN16-'Charges fixes'!AN17 -> 4574833 | F7: =+'Charges fixes'!BA24-'Charges fixes'!BA15-'Charges fixes'!BA16-'Charges fixes'!BA17 -> 482753.04 | G7: =+'Charges fixes'!BN24-'Charges fixes'!BN15-'Charges fixes'!BN16-'Charges fixes'!BN17 -> 1380924.5
B8: Valeur Ajoutée | C8: =C5-C7 -> -1051981.2 | D8: =D5-D7 -> 14055515 | E8: =E5-E7 -> 26577591 | F8: =F5-F7 -> -482753.04 | G8: =G5-G7 -> -1380924.5
B9: Rémunérations | C9: =+'Charges fixes'!N15+'Charges fixes'!N16 -> 6000000 | D9: ='Charges fixes'!AA15+'Charges fixes'!AA16 -> 6000000 | E9: ='Charges fixes'!AN15+'Charges fixes'!AN16 -> 6000000 | F9: ='Charges fixes'!BA15+'Charges fixes'!BA16 -> 0 | G9: ='Charges fixes'!BN15+'Charges fixes'!BN16 -> 0
B10: Impôts et taxes | C10: ='Charges fixes'!N7+'Charges fixes'!N8+'Charges fixes'!N9+'Charges fixes'!N10+'Charges fixes'!N11+'Charges fixes'!N12+'Charges fixes'!N13+'Charges fixes'!N14+'Charges fixes'!N17 -> 2622981.2 | D10: ='Charges fixes'!AA7+'Charges fixes'!AA8+'Charges fixes'!AA9+'Charges fixes'!AA10+'Charges fixes'!AA11+'Charges fixes'!AA12+'Charges fixes'!AA13+'Charges fixes'!AA14+'Charges fixes'!AA17 -> 2614859.9 | E10: ='Charges fixes'!AN7+'Charges fixes'!AN8+'Charges fixes'!AN9+'Charges fixes'!AN10+'Charges fixes'!AN11+'Charges fixes'!AN12+'Charges fixes'!AN13+'Charges fixes'!AN14+'Charges fixes'!AN17 -> 2640833 | F10: ='Charges fixes'!BA7+'Charges fixes'!BA8+'Charges fixes'!BA9+'Charges fixes'!BA10+'Charges fixes'!BA11+'Charges fixes'!BA12+'Charges fixes'!BA13+'Charges fixes'!BA14+'Charges fixes'!BA17 -> 482753.04 | G10: ='Charges fixes'!BN7+'Charges fixes'!BN8+'Charges fixes'!BN9+'Charges fixes'!BN10+'Charges fixes'!BN11+'Charges fixes'!BN12+'Charges fixes'!BN13+'Charges fixes'!BN14+'Charges fixes'!BN17 -> 1380924.5
